Workbook

Sheet サマリー
A1: 令和9年度 資金繰り検討サマリー(株式会社旭土地建物)
A2: 作成日 2026/10/27 ・ 基礎資料: 令和5〜8年度 勘定科目残高推移表(各年度4〜9月) ・ 単位: 千円
A4: 主要指標 | F4: グラフ用(月次残高)
B5: 社債なし | C5: 社債あり | D5: 差額 | F5: 月 | G5: 社債なし | H5: 社債あり
A6: 現預金(令和8年9月末) | B6: =資金繰り表!C6 -> 207939447 | C6: =資金繰り表!C6 -> 207939447 | D6: =C6-B6 -> 0 | F6: =資金繰り表!C4 -> 46296 | G6: =資金繰り表!C29 -> 205530619 | H6: =資金繰り表!C37 -> 205530619
A7: 令和9年4月 期首残高 | B7: =資金繰り表!J6 -> 193486479 | C7: =資金繰り表!J6+資金繰り表!H36 -> 153861479 | D7: =C7-B7 -> -39625000 | F7: =資金繰り表!D4 -> 46327 | G7: =資金繰り表!D29 -> 203121791 | H7: =資金繰り表!D37 -> 163496791
A8: 令和9年度 期末残高(令和10年3月末) | B8: =資金繰り表!V29 -> 148544479 | C8: =資金繰り表!V37 -> 1.1126102e+08 | D8: =C8-B8 -> -37283460 | F8: =資金繰り表!E4 -> 46357 | G8: =資金繰り表!E29 -> 200712963 | H8: =資金繰り表!E37 -> 161087963
A9: 令和9年度の収支(増減) | B9: =資金繰り表!V27 -> -44942000 | C9: =資金繰り表!V27+資金繰り表!V35 -> -42600460 | D9: =C9-B9 -> 2341540.2 | F9: =資金繰り表!F4 -> 46388 | G9: =資金繰り表!F29 -> 198304135 | H9: =資金繰り表!F37 -> 158679135
A10: 令和9年度の収入計 | B10: =資金繰り表!V13 -> 74056608 | C10: =資金繰り表!V13+資金繰り表!V33 -> 76398148 | D10: =C10-B10 -> 2341540.2 | F10: =資金繰り表!G4 -> 46419 | G10: =資金繰り表!G29 -> 195895307 | H10: =資金繰り表!G37 -> 156270307
A11: 令和9年度の支出計(経費等) | B11: =資金繰り表!V26 -> 118998608 | C11: =資金繰り表!V26 -> 118998608 | D11: =C11-B11 -> 0 | F11: =資金繰り表!H4 -> 46447 | G11: =資金繰り表!H29 -> 193486479 | H11: =資金繰り表!H37 -> 153861479
A12: 対象期間の最低残高 | B12: =MIN(資金繰り表!C29,資金繰り表!D29,資金繰り表!E29,資金繰り表!F29,資金繰り表!G29,資金繰り表!H29,資金繰り表!J29,資金繰り表!K29,資金繰り表!L29,資金繰り表!M29,資金繰り表!N29,資金繰り表!O29,資金繰り表!P29,資金繰り表!Q29,資金繰り表!R29,資金繰り表!S29,資金繰り表!T29,資金繰り表!U29) -> 148544479 | C12: =MIN(資金繰り表!C37,資金繰り表!D37,資金繰り表!E37,資金繰り表!F37,資金繰り表!G37,資金繰り表!H37,資金繰り表!J37,資金繰り表!K37,資金繰り表!L37,資金繰り表!M37,資金繰り表!N37,資金繰り表!O37,資金繰り表!P37,資金繰り表!Q37,資金繰り表!R37,資金繰り表!S37,資金繰り表!T37,資金繰り表!U37) -> 1.1126102e+08 | D12: =C12-B12 -> -37283460 | F12: =資金繰り表!J4 -> 46478 | G12: =資金繰り表!J29 -> 186012210 | H12: =資金繰り表!J37 -> 146387210
A13: 月平均の経費支出(令和9年度) | B13: =資金繰り表!V26/12 -> 9916550.7 | C13: =資金繰り表!V26/12 -> 9916550.7 | D13: =C13-B13 -> 0 | F13: =資金繰り表!K4 -> 46508 | G13: =資金繰り表!K29 -> 181047136 | H13: =資金繰り表!K37 -> 1.4259291e+08
A14: 期末残高の経費月数(手元流動性) | B14: =B8/B13 -> 14.97945 | C14: =C8/C13 -> 11.21973 | D14: =C14-B14 -> -3.7597206 | F14: =資金繰り表!L4 -> 46539 | G14: =資金繰り表!L29 -> 172016008 | H14: =資金繰り表!L37 -> 1.3356178e+08
A15: 社債の年間税引後利息(円ベース) | C15: =社債検討!B8 -> 2341540.2 | F15: =資金繰り表!M4 -> 46569 | G15: =資金繰り表!M29 -> 169366136 | H15: =資金繰り表!M37 -> 1.3091191e+08
A16: 社債の円ベース利回り(税引後) | C16: =社債検討!B10 -> 0.059092498 | F16: =資金繰り表!N4 -> 46600 | G16: =資金繰り表!N29 -> 168560083 | H16: =資金繰り表!N37 -> 1.3010585e+08
A17: 損益分岐の償還時為替(円/USD) | C17: =社債検討!B11 -> 130.40152 | F17: =資金繰り表!O4 -> 46631 | G17: =資金繰り表!O29 -> 162997447 | H17: =資金繰り表!O37 -> 1.2454322e+08
F18: =資金繰り表!P4 -> 46661 | G18: =資金繰り表!P29 -> 160588619 | H18: =資金繰り表!P37 -> 1.2213439e+08
A19: 読み取りのポイント | F19: =資金繰り表!Q4 -> 46692 | G19: =資金繰り表!Q29 -> 158179791 | H19: =資金繰り表!Q37 -> 1.2089633e+08
A20: ・来期は建売の在庫がなく収入は家賃のみ(土地・商品の売却収入は0で計上)。令和8年4〜9月の現預金増加は在庫売却によるもので、家賃と経費だけでは赤字(家賃は最新明細で月約380万円、下期の経費は月約620万円。4月のみ年間計上分の約2,500万円が上乗せされる実績パターンで、内容は要確認)。経費の内訳は「経費内訳」シート参照(保険料が約3割で最大)。 | F20: =資金繰り表!R4 -> 46722 | G20: =資金繰り表!R29 -> 155770963 | H20: =資金繰り表!R37 -> 1.184875e+08
A21: ・令和8年4〜9月は営業損失約8,700万円・経常損失約1億300万円(土地売上が原価割れ)。BS上の商品約8,000万円の売却は見込んでいません。 | F21: =資金繰り表!S4 -> 46753 | G21: =資金繰り表!S29 -> 153362135 | H21: =資金繰り表!S37 -> 1.1607868e+08
A22: ・社債25万USD(約3,950万円)を購入しても、前提どおり臨時収入ゼロの保守的な見積りで現預金は約1億円台を維持。ただし収益が改善しない限り残高は毎年減少します。 | F22: =資金繰り表!T4 -> 46784 | G22: =資金繰り表!T29 -> 150953307 | H22: =資金繰り表!T37 -> 1.1366985e+08
A23: ・7%は米ドル建てのクーポンです。円ベースでは源泉税と為替で変動し、損益分岐は社債検討シートの通り。賃貸アパートとの比較は同シートの仮置き条件で確認してください。 | F23: =資金繰り表!U4 -> 46813 | G23: =資金繰り表!U29 -> 148544479 | H23: =資金繰り表!U37 -> 1.1126102e+08
A24: ・長期未払金が9月に4,691万円へ倍増(前年9月は2,345万円)。支払期日が未確認のため資金繰り表には含めていません。支払時期が決まれば資金繰り表の手入力欄に入れてください。
A25: ・短期貸付金3億6,267万円・未収入金2億5,114万円・前渡金1,500万円は回収予定を反映していません(8〜9月に貸付金が月100万円ずつ減少)。回収計画があれば手入力欄へ。

Sheet 前提
A1: 前提条件(青字・黄色セルを変更すると資金繰り表が再計算されます)
A2: 金額は円。青字=入力値、黒字=計算、緑字=他シート参照。
A4: 1. 開始残高・収入
A5: 期首現預金(令和8年9月末) | B5: 207939447 | C5: BS現預金小計(現金1,082,425+当座33,394,160+普通162,529,499+定期10,933,363)。出典:残高推移表
A6: 賃貸収入 月額(最新の家賃明細) | B6: =家賃明細!B17 -> 3800269 | C6: 令和8年10月15日付「賃貸収入・支出明細」旭土地建物の月額合計(家賃明細シート)
A7: 4月に上乗せされる年間計上分 | B7: =実績!J6-実績!K6 -> 25333380 | C7: 令和8年4月(29.2百万円)と5月(3.9百万円)の差。過去4年とも4月に同規模の計上あり。家賃明細には表れないため内容を要確認(0にすれば除外)
A8: 4月のその他売上 | B8: =実績!J7 -> 3120000 | C8: 令和8年4月実績(売上高4114)
A10: 2. 消費税納付(令和9年5月)
A11: 仮受消費税等(令和8年9月末) | B11: 4249004 | C11: BS負債の部
A12: 仮払消費税等(令和8年9月末) | B12: 2766120 | C12: BS資産の部
A13: 年間換算倍率 | B13: 2 | C13: 上期実績を2倍して年間納付額を概算
A14: 消費税納付見込(令和9年5月払い) | B14: =(B11-B12)*B13 -> 2965768 | C14: 土地売上は非課税のため、賃貸等の課税売上ベースで概算。税理士確認を推奨
A16: 3. 社債(大和証券 提案)
A17: 購入額(額面・USD) | B17: 250000 | C17: 最低購入単位25万ドル(ご提示)
A18: 購入時為替(円/USD) | B18: 158 | C18: OANDA 2026/10/20「158円台半ば」を参考にした仮置き。実際の約定レートに置換
A19: 為替手数料(円/USD) | B19: 0.5 | C19: 仮置き。大和証券へ要確認(購入価格に含まれる場合あり)
A20: 購入年月 | B20: 46327 | C20: 仮置き(申込〜受渡し日に合わせて変更)
A21: 年利(クーポン) | B21: 0.07 | C21: ご提示。「利回り」か「表面利率」か、発行価格が額面かは要確認
A22: 利払回数(年) | B22: 2 | C22: 1=年1回、2=半年ごと。要確認
A23: 国内源泉徴収税率 | B23: 0.15315 | C23: 法人は所得税15.315%が源泉され法人税から控除される想定(欠損のため還付は決算後)。税理士確認
A24: 保有期間(月) | B24: 36 | C24: 3年満期
A25: 利払時の想定為替 | B25: =B18 -> 158 | C25: 既定=購入時と同じ。円高/円安シナリオは上書き
A26: 償還時の想定為替 | B26: =B18 -> 158 | C26: 既定=購入時と同じ。円高/円安シナリオは社債検討シートで分析
A27: 購入代金(円) | B27: =B17*(B18+B19) -> 39625000
A29: 4. 経費の月別パターン(現預金の支出ベース・減価償却費を除く)
A30: 4〜9月=令和8年度の実績(実績シート)。10〜3月=5〜9月の月次中央値(臨時の大口を除いた水準)。令和9年度も同パターンを繰り返す前提。
A31: 項目 | C31: 4月 | D31: 5月 | E31: 6月 | F31: 7月 | G31: 8月 | H31: 9月 | I31: 10月 | J31: 11月 | K31: 12月 | L31: 1月 | M31: 2月 | N31: 3月 | O31: 年間計 | P31: 10〜3月想定月額
A32: 役員報酬 | C32: =実績!J9 -> 6300000 | D32: =実績!K9 -> 900000 | E32: =実績!L9 -> 900000 | F32: =実績!M9 -> 900000 | G32: =実績!N9 -> 900000 | H32: =実績!O9 -> 2400000 | I32: =$P32 -> 900000 | J32: =$P32 -> 900000 | K32: =$P32 -> 900000 | L32: =$P32 -> 900000 | M32: =$P32 -> 900000 | N32: =$P32 -> 900000 | O32: =SUM(C32:N32) -> 17700000 | P32: =MEDIAN(D32:H32) -> 900000
A33: 給与・賞与・福利厚生 | C33: =実績!J10+実績!J11+実績!J12+実績!J13 -> 8133516 | D33: =実績!K10+実績!K11+実績!K12+実績!K13 -> 672558 | E33: =実績!L10+実績!L11+実績!L12+実績!L13 -> 1106054 | F33: =実績!M10+実績!M11+実績!M12+実績!M13 -> 1378300 | G33: =実績!N10+実績!N11+実績!N12+実績!N13 -> 890878 | H33: =実績!O10+実績!O11+実績!O12+実績!O13 -> 1207652 | I33: =$P33 -> 1106054 | J33: =$P33 -> 1106054 | K33: =$P33 -> 1106054 | L33: =$P33 -> 1106054 | M33: =$P33 -> 1106054 | N33: =$P33 -> 1106054 | O33: =SUM(C33:N33) -> 20025282 | P33: =MEDIAN(D33:H33) -> 1106054
A34: 保険料 | C34: =実績!J14 -> 6100386 | D34: =実績!K14 -> 868788 | E34: =実績!L14 -> 9169071 | F34: =実績!M14 -> 2591448 | G34: =実績!N14 -> 1350056 | H34: =実績!O14 -> 4537846 | I34: =$P34 -> 2591448 | J34: =$P34 -> 2591448 | K34: =$P34 -> 2591448 | L34: =$P34 -> 2591448 | M34: =$P34 -> 2591448 | N34: =$P34 -> 2591448 | O34: =SUM(C34:N34) -> 40166283 | P34: =MEDIAN(D34:H34) -> 2591448
A35: 租税公課 | C35: =実績!J15 -> 5496995 | D35: =実績!K15 -> 1719800 | E35: =実績!L15 -> 35500 | F35: =実績!M15 -> 15705 | G35: =実績!N15 -> 22952 | H35: =実績!O15 -> 600 | I35: =$P35 -> 22952 | J35: =$P35 -> 22952 | K35: =$P35 -> 22952 | L35: =$P35 -> 22952 | M35: =$P35 -> 22952 | N35: =$P35 -> 22952 | O35: =SUM(C35:N35) -> 7429264 | P35: =MEDIAN(D35:H35) -> 22952
A36: 水道光熱・通信交通 | C36: =実績!J16+実績!J17 -> 3239627 | D36: =実績!K16+実績!K17 -> 424654 | E36: =実績!L16+実績!L17 -> 507425 | F36: =実績!M16+実績!M17 -> 515232 | G36: =実績!N16+実績!N17 -> 649918 | H36: =実績!O16+実績!O17 -> 518550 | I36: =$P36 -> 515232 | J36: =$P36 -> 515232 | K36: =$P36 -> 515232 | L36: =$P36 -> 515232 | M36: =$P36 -> 515232 | N36: =$P36 -> 515232 | O36: =SUM(C36:N36) -> 8946798 | P36: =MEDIAN(D36:H36) -> 515232
A37: 接待交際・諸会費 | C37: =実績!J18+実績!J19 -> 7770390 | D37: =実績!K18+実績!K19 -> 935455 | E37: =実績!L18+実績!L19 -> 831674 | F37: =実績!M18+実績!M19 -> 753886 | G37: =実績!N18+実績!N19 -> 413189 | H37: =実績!O18+実績!O19 -> 247264 | I37: =$P37 -> 753886 | J37: =$P37 -> 753886 | K37: =$P37 -> 753886 | L37: =$P37 -> 753886 | M37: =$P37 -> 753886 | N37: =$P37 -> 753886 | O37: =SUM(C37:N37) -> 15475174 | P37: =MEDIAN(D37:H37) -> 753886
A38: 修繕・消耗品 | C38: =実績!J20+実績!J21+実績!J22 -> 707887 | D38: =実績!K20+実績!K21+実績!K22 -> 28725 | E38: =実績!L20+実績!L21+実績!L22 -> 25723 | F38: =実績!M20+実績!M21+実績!M22 -> 91475 | G38: =実績!N20+実績!N21+実績!N22 -> 151279 | H38: =実績!O20+実績!O21+実績!O22 -> 255843 | I38: =$P38 -> 91475 | J38: =$P38 -> 91475 | K38: =$P38 -> 91475 | L38: =$P38 -> 91475 | M38: =$P38 -> 91475 | N38: =$P38 -> 91475 | O38: =SUM(C38:N38) -> 1809782 | P38: =MEDIAN(D38:H38) -> 91475
A39: 管理諸費・雑費・その他 | C39: =実績!J23+実績!J24+実績!J25+実績!J26+実績!J27 -> 1979117 | D39: =実績!K23+実績!K24+実績!K25+実績!K26+実績!K27 -> 249595 | E39: =実績!L23+実績!L24+実績!L25+実績!L26+実績!L27 -> 255950 | F39: =実績!M23+実績!M24+実績!M25+実績!M26+実績!M27 -> 204095 | G39: =実績!N23+実績!N24+実績!N25+実績!N26+実績!N27 -> 228050 | H39: =実績!O23+実績!O24+実績!O25+実績!O26+実績!O27 -> 195150 | I39: =$P39 -> 228050 | J39: =$P39 -> 228050 | K39: =$P39 -> 228050 | L39: =$P39 -> 228050 | M39: =$P39 -> 228050 | N39: =$P39 -> 228050 | O39: =SUM(C39:N39) -> 4480257 | P39: =MEDIAN(D39:H39) -> 228050
A40: 経費計 | C40: =SUM(C32:C39) -> 39727918 | D40: =SUM(D32:D39) -> 5799575 | E40: =SUM(E32:E39) -> 12831397 | F40: =SUM(F32:F39) -> 6450141 | G40: =SUM(G32:G39) -> 4606322 | H40: =SUM(H32:H39) -> 9362905 | I40: =SUM(I32:I39) -> 6209097 | J40: =SUM(J32:J39) -> 6209097 | ... P40: =SUM(P32:P39) -> 6209097
A42: 租税公課は4〜5月に年間分が計上される実績パターンのため、10〜3月はほぼゼロになります(実際の納期は固定資産税の納付書でご確認ください)。

Sheet 資金繰り表
A1: 資金繰り表(令和8年10月〜令和10年3月・月次) ※令和9年度=令和9年4月〜令和10年3月
A2: 単位:千円(内部は円)。青字・黄色=手入力欄(土地売却・貸付金回収など臨時項目、初期値0)。経費は支出ベースで減価償却費を除外。
A4: 月 | C4: 46296 | D4: =EDATE(C4,1) -> 46327 | E4: =EDATE(D4,1) -> 46357 | F4: =EDATE(E4,1) -> 46388 | G4: =EDATE(F4,1) -> 46419 | H4: =EDATE(G4,1) -> 46447 | I4: 令和8年度下期計 | J4: =EDATE(H4,1) -> 46478 | K4: =EDATE(J4,1) -> 46508 | L4: =EDATE(K4,1) -> 46539 | M4: =EDATE(L4,1) -> 46569 | N4: =EDATE(M4,1) -> 46600 | O4: =EDATE(N4,1) -> 46631 | P4: =EDATE(O4,1) -> 46661 | Q4: =EDATE(P4,1) -> 46692 | R4: =EDATE(Q4,1) -> 46722 | ... U4: =EDATE(T4,1) -> 46813 | V4: 令和9年度計
A5: 年度 | C5: ="令和"&(YEAR(C4)-IF(MONTH(C4)<4,1,0)-2018)&"年度" -> 令和8年度 | D5: ="令和"&(YEAR(D4)-IF(MONTH(D4)<4,1,0)-2018)&"年度" -> 令和8年度 | E5: ="令和"&(YEAR(E4)-IF(MONTH(E4)<4,1,0)-2018)&"年度" -> 令和8年度 | F5: ="令和"&(YEAR(F4)-IF(MONTH(F4)<4,1,0)-2018)&"年度" -> 令和8年度 | G5: ="令和"&(YEAR(G4)-IF(MONTH(G4)<4,1,0)-2018)&"年度" -> 令和8年度 | H5: ="令和"&(YEAR(H4)-IF(MONTH(H4)<4,1,0)-2018)&"年度" -> 令和8年度 | J5: ="令和"&(YEAR(J4)-IF(MONTH(J4)<4,1,0)-2018)&"年度" -> 令和9年度 | K5: ="令和"&(YEAR(K4)-IF(MONTH(K4)<4,1,0)-2018)&"年度" -> 令和9年度 | L5: ="令和"&(YEAR(L4)-IF(MONTH(L4)<4,1,0)-2018)&"年度" -> 令和9年度 | M5: ="令和"&(YEAR(M4)-IF(MONTH(M4)<4,1,0)-2018)&"年度" -> 令和9年度 | N5: ="令和"&(YEAR(N4)-IF(MONTH(N4)<4,1,0)-2018)&"年度" -> 令和9年度 | O5: ="令和"&(YEAR(O4)-IF(MONTH(O4)<4,1,0)-2018)&"年度" -> 令和9年度 | P5: ="令和"&(YEAR(P4)-IF(MONTH(P4)<4,1,0)-2018)&"年度" -> 令和9年度 | Q5: ="令和"&(YEAR(Q4)-IF(MONTH(Q4)<4,1,0)-2018)&"年度" -> 令和9年度 | ... U5: ="令和"&(YEAR(U4)-IF(MONTH(U4)<4,1,0)-2018)&"年度" -> 令和9年度
A6: 前月繰越現預金(社債なし) | C6: =前提!B5 -> 207939447 | D6: =C29 -> 205530619 | E6: =D29 -> 203121791 | F6: =E29 -> 200712963 | G6: =F29 -> 198304135 | H6: =G29 -> 195895307 | I6: =C6 -> 207939447 | J6: =H29 -> 193486479 | K6: =J29 -> 186012210 | L6: =K29 -> 181047136 | M6: =L29 -> 172016008 | N6: =M29 -> 169366136 | O6: =N29 -> 168560083 | P6: =O29 -> 162997447 | Q6: =P29 -> 160588619 | R6: =Q29 -> 158179791 | ... U6: =T29 -> 150953307 | V6: =J6 -> 193486479
A7: 【収入】
A8: 賃貸収入 | C8: =前提!$B$6+IF(MONTH(C$4)=4,前提!$B$7,0) -> 3800269 | D8: =前提!$B$6+IF(MONTH(D$4)=4,前提!$B$7,0) -> 3800269 | E8: =前提!$B$6+IF(MONTH(E$4)=4,前提!$B$7,0) -> 3800269 | F8: =前提!$B$6+IF(MONTH(F$4)=4,前提!$B$7,0) -> 3800269 | G8: =前提!$B$6+IF(MONTH(G$4)=4,前提!$B$7,0) -> 3800269 | H8: =前提!$B$6+IF(MONTH(H$4)=4,前提!$B$7,0) -> 3800269 | I8: =SUM(C8:H8) -> 22801614 | J8: =前提!$B$6+IF(MONTH(J$4)=4,前提!$B$7,0) -> 29133649 | K8: =前提!$B$6+IF(MONTH(K$4)=4,前提!$B$7,0) -> 3800269 | L8: =前提!$B$6+IF(MONTH(L$4)=4,前提!$B$7,0) -> 3800269 | M8: =前提!$B$6+IF(MONTH(M$4)=4,前提!$B$7,0) -> 3800269 | N8: =前提!$B$6+IF(MONTH(N$4)=4,前提!$B$7,0) -> 3800269 | O8: =前提!$B$6+IF(MONTH(O$4)=4,前提!$B$7,0) -> 3800269 | P8: =前提!$B$6+IF(MONTH(P$4)=4,前提!$B$7,0) -> 3800269 | Q8: =前提!$B$6+IF(MONTH(Q$4)=4,前提!$B$7,0) -> 3800269 | ... U8: =前提!$B$6+IF(MONTH(U$4)=4,前提!$B$7,0) -> 3800269 | V8: =SUM(J8:U8) -> 70936608
A9: その他売上(4月) | C9: =IF(MONTH(C$4)=4,前提!$B$8,0) -> 0 | D9: =IF(MONTH(D$4)=4,前提!$B$8,0) -> 0 | E9: =IF(MONTH(E$4)=4,前提!$B$8,0) -> 0 | F9: =IF(MONTH(F$4)=4,前提!$B$8,0) -> 0 | G9: =IF(MONTH(G$4)=4,前提!$B$8,0) -> 0 | H9: =IF(MONTH(H$4)=4,前提!$B$8,0) -> 0 | I9: =SUM(C9:H9) -> 0 | J9: =IF(MONTH(J$4)=4,前提!$B$8,0) -> 3120000 | K9: =IF(MONTH(K$4)=4,前提!$B$8,0) -> 0 | L9: =IF(MONTH(L$4)=4,前提!$B$8,0) -> 0 | M9: =IF(MONTH(M$4)=4,前提!$B$8,0) -> 0 | N9: =IF(MONTH(N$4)=4,前提!$B$8,0) -> 0 | O9: =IF(MONTH(O$4)=4,前提!$B$8,0) -> 0 | P9: =IF(MONTH(P$4)=4,前提!$B$8,0) -> 0 | Q9: =IF(MONTH(Q$4)=4,前提!$B$8,0) -> 0 | ... U9: =IF(MONTH(U$4)=4,前提!$B$8,0) -> 0 | V9: =SUM(J9:U9) -> 3120000
A10: 土地・商品の売却収入(手入力) | C10: 0 | D10: 0 | E10: 0 | F10: 0 | G10: 0 | H10: 0 | I10: =SUM(C10:H10) -> 0 | J10: 0 | K10: 0 | L10: 0 | M10: 0 | N10: 0 | O10: 0 | P10: 0 | Q10: 0 | R10: 0 | S10: 0 | T10: 0 | U10: 0 | V10: =SUM(J10:U10) -> 0
A11: 貸付金・未収入金の回収(手入力) | C11: 0 | D11: 0 | E11: 0 | F11: 0 | G11: 0 | H11: 0 | I11: =SUM(C11:H11) -> 0 | J11: 0 | K11: 0 | L11: 0 | M11: 0 | N11: 0 | O11: 0 | P11: 0 | Q11: 0 | R11: 0 | S11: 0 | T11: 0 | U11: 0 | V11: =SUM(J11:U11) -> 0
A12: その他臨時収入(手入力) | C12: 0 | D12: 0 | E12: 0 | F12: 0 | G12: 0 | H12: 0 | I12: =SUM(C12:H12) -> 0 | J12: 0 | K12: 0 | L12: 0 | M12: 0 | N12: 0 | O12: 0 | P12: 0 | Q12: 0 | R12: 0 | S12: 0 | T12: 0 | U12: 0 | V12: =SUM(J12:U12) -> 0
A13: 収入計 | C13: =SUM(C8:C12) -> 3800269 | D13: =SUM(D8:D12) -> 3800269 | E13: =SUM(E8:E12) -> 3800269 | F13: =SUM(F8:F12) -> 3800269 | G13: =SUM(G8:G12) -> 3800269 | H13: =SUM(H8:H12) -> 3800269 | I13: =SUM(C13:H13) -> 22801614 | J13: =SUM(J8:J12) -> 32253649 | K13: =SUM(K8:K12) -> 3800269 | L13: =SUM(L8:L12) -> 3800269 | M13: =SUM(M8:M12) -> 3800269 | N13: =SUM(N8:N12) -> 3800269 | O13: =SUM(O8:O12) -> 3800269 | P13: =SUM(P8:P12) -> 3800269 | Q13: =SUM(Q8:Q12) -> 3800269 | ... U13: =SUM(U8:U12) -> 3800269 | V13: =SUM(J13:U13) -> 74056608
A14: 【支出】
A15: 役員報酬 | C15: =INDEX(前提!$C$32:$N$32,MOD(MONTH(C$4)-4,12)+1) -> 900000 | D15: =INDEX(前提!$C$32:$N$32,MOD(MONTH(D$4)-4,12)+1) -> 900000 | E15: =INDEX(前提!$C$32:$N$32,MOD(MONTH(E$4)-4,12)+1) -> 900000 | F15: =INDEX(前提!$C$32:$N$32,MOD(MONTH(F$4)-4,12)+1) -> 900000 | G15: =INDEX(前提!$C$32:$N$32,MOD(MONTH(G$4)-4,12)+1) -> 900000 | H15: =INDEX(前提!$C$32:$N$32,MOD(MONTH(H$4)-4,12)+1) -> 900000 | I15: =SUM(C15:H15) -> 5400000 | J15: =INDEX(前提!$C$32:$N$32,MOD(MONTH(J$4)-4,12)+1) -> 6300000 | K15: =INDEX(前提!$C$32:$N$32,MOD(MONTH(K$4)-4,12)+1) -> 900000 | L15: =INDEX(前提!$C$32:$N$32,MOD(MONTH(L$4)-4,12)+1) -> 900000 | M15: =INDEX(前提!$C$32:$N$32,MOD(MONTH(M$4)-4,12)+1) -> 900000 | N15: =INDEX(前提!$C$32:$N$32,MOD(MONTH(N$4)-4,12)+1) -> 900000 | O15: =INDEX(前提!$C$32:$N$32,MOD(MONTH(O$4)-4,12)+1) -> 2400000 | P15: =INDEX(前提!$C$32:$N$32,MOD(MONTH(P$4)-4,12)+1) -> 900000 | Q15: =INDEX(前提!$C$32:$N$32,MOD(MONTH(Q$4)-4,12)+1) -> 900000 | ... U15: =INDEX(前提!$C$32:$N$32,MOD(MONTH(U$4)-4,12)+1) -> 900000 | V15: =SUM(J15:U15) -> 17700000
A16: 給与・賞与・福利厚生 | C16: =INDEX(前提!$C$33:$N$33,MOD(MONTH(C$4)-4,12)+1) -> 1106054 | D16: =INDEX(前提!$C$33:$N$33,MOD(MONTH(D$4)-4,12)+1) -> 1106054 | E16: =INDEX(前提!$C$33:$N$33,MOD(MONTH(E$4)-4,12)+1) -> 1106054 | F16: =INDEX(前提!$C$33:$N$33,MOD(MONTH(F$4)-4,12)+1) -> 1106054 | G16: =INDEX(前提!$C$33:$N$33,MOD(MONTH(G$4)-4,12)+1) -> 1106054 | H16: =INDEX(前提!$C$33:$N$33,MOD(MONTH(H$4)-4,12)+1) -> 1106054 | I16: =SUM(C16:H16) -> 6636324 | J16: =INDEX(前提!$C$33:$N$33,MOD(MONTH(J$4)-4,12)+1) -> 8133516 | K16: =INDEX(前提!$C$33:$N$33,MOD(MONTH(K$4)-4,12)+1) -> 672558 | L16: =INDEX(前提!$C$33:$N$33,MOD(MONTH(L$4)-4,12)+1) -> 1106054 | M16: =INDEX(前提!$C$33:$N$33,MOD(MONTH(M$4)-4,12)+1) -> 1378300 | N16: =INDEX(前提!$C$33:$N$33,MOD(MONTH(N$4)-4,12)+1) -> 890878 | O16: =INDEX(前提!$C$33:$N$33,MOD(MONTH(O$4)-4,12)+1) -> 1207652 | P16: =INDEX(前提!$C$33:$N$33,MOD(MONTH(P$4)-4,12)+1) -> 1106054 | Q16: =INDEX(前提!$C$33:$N$33,MOD(MONTH(Q$4)-4,12)+1) -> 1106054 | ... U16: =INDEX(前提!$C$33:$N$33,MOD(MONTH(U$4)-4,12)+1) -> 1106054 | V16: =SUM(J16:U16) -> 20025282
A17: 保険料 | C17: =INDEX(前提!$C$34:$N$34,MOD(MONTH(C$4)-4,12)+1) -> 2591448 | D17: =INDEX(前提!$C$34:$N$34,MOD(MONTH(D$4)-4,12)+1) -> 2591448 | E17: =INDEX(前提!$C$34:$N$34,MOD(MONTH(E$4)-4,12)+1) -> 2591448 | F17: =INDEX(前提!$C$34:$N$34,MOD(MONTH(F$4)-4,12)+1) -> 2591448 | G17: =INDEX(前提!$C$34:$N$34,MOD(MONTH(G$4)-4,12)+1) -> 2591448 | H17: =INDEX(前提!$C$34:$N$34,MOD(MONTH(H$4)-4,12)+1) -> 2591448 | I17: =SUM(C17:H17) -> 15548688 | J17: =INDEX(前提!$C$34:$N$34,MOD(MONTH(J$4)-4,12)+1) -> 6100386 | K17: =INDEX(前提!$C$34:$N$34,MOD(MONTH(K$4)-4,12)+1) -> 868788 | L17: =INDEX(前提!$C$34:$N$34,MOD(MONTH(L$4)-4,12)+1) -> 9169071 | M17: =INDEX(前提!$C$34:$N$34,MOD(MONTH(M$4)-4,12)+1) -> 2591448 | N17: =INDEX(前提!$C$34:$N$34,MOD(MONTH(N$4)-4,12)+1) -> 1350056 | O17: =INDEX(前提!$C$34:$N$34,MOD(MONTH(O$4)-4,12)+1) -> 4537846 | P17: =INDEX(前提!$C$34:$N$34,MOD(MONTH(P$4)-4,12)+1) -> 2591448 | Q17: =INDEX(前提!$C$34:$N$34,MOD(MONTH(Q$4)-4,12)+1) -> 2591448 | ... U17: =INDEX(前提!$C$34:$N$34,MOD(MONTH(U$4)-4,12)+1) -> 2591448 | V17: =SUM(J17:U17) -> 40166283
A18: 租税公課 | C18: =INDEX(前提!$C$35:$N$35,MOD(MONTH(C$4)-4,12)+1) -> 22952 | D18: =INDEX(前提!$C$35:$N$35,MOD(MONTH(D$4)-4,12)+1) -> 22952 | E18: =INDEX(前提!$C$35:$N$35,MOD(MONTH(E$4)-4,12)+1) -> 22952 | F18: =INDEX(前提!$C$35:$N$35,MOD(MONTH(F$4)-4,12)+1) -> 22952 | G18: =INDEX(前提!$C$35:$N$35,MOD(MONTH(G$4)-4,12)+1) -> 22952 | H18: =INDEX(前提!$C$35:$N$35,MOD(MONTH(H$4)-4,12)+1) -> 22952 | I18: =SUM(C18:H18) -> 137712 | J18: =INDEX(前提!$C$35:$N$35,MOD(MONTH(J$4)-4,12)+1) -> 5496995 | K18: =INDEX(前提!$C$35:$N$35,MOD(MONTH(K$4)-4,12)+1) -> 1719800 | L18: =INDEX(前提!$C$35:$N$35,MOD(MONTH(L$4)-4,12)+1) -> 35500 | M18: =INDEX(前提!$C$35:$N$35,MOD(MONTH(M$4)-4,12)+1) -> 15705 | N18: =INDEX(前提!$C$35:$N$35,MOD(MONTH(N$4)-4,12)+1) -> 22952 | O18: =INDEX(前提!$C$35:$N$35,MOD(MONTH(O$4)-4,12)+1) -> 600 | P18: =INDEX(前提!$C$35:$N$35,MOD(MONTH(P$4)-4,12)+1) -> 22952 | Q18: =INDEX(前提!$C$35:$N$35,MOD(MONTH(Q$4)-4,12)+1) -> 22952 | ... U18: =INDEX(前提!$C$35:$N$35,MOD(MONTH(U$4)-4,12)+1) -> 22952 | V18: =SUM(J18:U18) -> 7429264
A19: 水道光熱・通信交通 | C19: =INDEX(前提!$C$36:$N$36,MOD(MONTH(C$4)-4,12)+1) -> 515232 | D19: =INDEX(前提!$C$36:$N$36,MOD(MONTH(D$4)-4,12)+1) -> 515232 | E19: =INDEX(前提!$C$36:$N$36,MOD(MONTH(E$4)-4,12)+1) -> 515232 | F19: =INDEX(前提!$C$36:$N$36,MOD(MONTH(F$4)-4,12)+1) -> 515232 | G19: =INDEX(前提!$C$36:$N$36,MOD(MONTH(G$4)-4,12)+1) -> 515232 | H19: =INDEX(前提!$C$36:$N$36,MOD(MONTH(H$4)-4,12)+1) -> 515232 | I19: =SUM(C19:H19) -> 3091392 | J19: =INDEX(前提!$C$36:$N$36,MOD(MONTH(J$4)-4,12)+1) -> 3239627 | K19: =INDEX(前提!$C$36:$N$36,MOD(MONTH(K$4)-4,12)+1) -> 424654 | L19: =INDEX(前提!$C$36:$N$36,MOD(MONTH(L$4)-4,12)+1) -> 507425 | M19: =INDEX(前提!$C$36:$N$36,MOD(MONTH(M$4)-4,12)+1) -> 515232 | N19: =INDEX(前提!$C$36:$N$36,MOD(MONTH(N$4)-4,12)+1) -> 649918 | O19: =INDEX(前提!$C$36:$N$36,MOD(MONTH(O$4)-4,12)+1) -> 518550 | P19: =INDEX(前提!$C$36:$N$36,MOD(MONTH(P$4)-4,12)+1) -> 515232 | Q19: =INDEX(前提!$C$36:$N$36,MOD(MONTH(Q$4)-4,12)+1) -> 515232 | ... U19: =INDEX(前提!$C$36:$N$36,MOD(MONTH(U$4)-4,12)+1) -> 515232 | V19: =SUM(J19:U19) -> 8946798
A20: 接待交際・諸会費 | C20: =INDEX(前提!$C$37:$N$37,MOD(MONTH(C$4)-4,12)+1) -> 753886 | D20: =INDEX(前提!$C$37:$N$37,MOD(MONTH(D$4)-4,12)+1) -> 753886 | E20: =INDEX(前提!$C$37:$N$37,MOD(MONTH(E$4)-4,12)+1) -> 753886 | F20: =INDEX(前提!$C$37:$N$37,MOD(MONTH(F$4)-4,12)+1) -> 753886 | G20: =INDEX(前提!$C$37:$N$37,MOD(MONTH(G$4)-4,12)+1) -> 753886 | H20: =INDEX(前提!$C$37:$N$37,MOD(MONTH(H$4)-4,12)+1) -> 753886 | I20: =SUM(C20:H20) -> 4523316 | J20: =INDEX(前提!$C$37:$N$37,MOD(MONTH(J$4)-4,12)+1) -> 7770390 | K20: =INDEX(前提!$C$37:$N$37,MOD(MONTH(K$4)-4,12)+1) -> 935455 | L20: =INDEX(前提!$C$37:$N$37,MOD(MONTH(L$4)-4,12)+1) -> 831674 | M20: =INDEX(前提!$C$37:$N$37,MOD(MONTH(M$4)-4,12)+1) -> 753886 | N20: =INDEX(前提!$C$37:$N$37,MOD(MONTH(N$4)-4,12)+1) -> 413189 | O20: =INDEX(前提!$C$37:$N$37,MOD(MONTH(O$4)-4,12)+1) -> 247264 | P20: =INDEX(前提!$C$37:$N$37,MOD(MONTH(P$4)-4,12)+1) -> 753886 | Q20: =INDEX(前提!$C$37:$N$37,MOD(MONTH(Q$4)-4,12)+1) -> 753886 | ... U20: =INDEX(前提!$C$37:$N$37,MOD(MONTH(U$4)-4,12)+1) -> 753886 | V20: =SUM(J20:U20) -> 15475174
A21: 修繕・消耗品 | C21: =INDEX(前提!$C$38:$N$38,MOD(MONTH(C$4)-4,12)+1) -> 91475 | D21: =INDEX(前提!$C$38:$N$38,MOD(MONTH(D$4)-4,12)+1) -> 91475 | E21: =INDEX(前提!$C$38:$N$38,MOD(MONTH(E$4)-4,12)+1) -> 91475 | F21: =INDEX(前提!$C$38:$N$38,MOD(MONTH(F$4)-4,12)+1) -> 91475 | G21: =INDEX(前提!$C$38:$N$38,MOD(MONTH(G$4)-4,12)+1) -> 91475 | H21: =INDEX(前提!$C$38:$N$38,MOD(MONTH(H$4)-4,12)+1) -> 91475 | I21: =SUM(C21:H21) -> 548850 | J21: =INDEX(前提!$C$38:$N$38,MOD(MONTH(J$4)-4,12)+1) -> 707887 | K21: =INDEX(前提!$C$38:$N$38,MOD(MONTH(K$4)-4,12)+1) -> 28725 | L21: =INDEX(前提!$C$38:$N$38,MOD(MONTH(L$4)-4,12)+1) -> 25723 | M21: =INDEX(前提!$C$38:$N$38,MOD(MONTH(M$4)-4,12)+1) -> 91475 | N21: =INDEX(前提!$C$38:$N$38,MOD(MONTH(N$4)-4,12)+1) -> 151279 | O21: =INDEX(前提!$C$38:$N$38,MOD(MONTH(O$4)-4,12)+1) -> 255843 | P21: =INDEX(前提!$C$38:$N$38,MOD(MONTH(P$4)-4,12)+1) -> 91475 | Q21: =INDEX(前提!$C$38:$N$38,MOD(MONTH(Q$4)-4,12)+1) -> 91475 | ... U21: =INDEX(前提!$C$38:$N$38,MOD(MONTH(U$4)-4,12)+1) -> 91475 | V21: =SUM(J21:U21) -> 1809782
A22: 管理諸費・雑費・その他 | C22: =INDEX(前提!$C$39:$N$39,MOD(MONTH(C$4)-4,12)+1) -> 228050 | D22: =INDEX(前提!$C$39:$N$39,MOD(MONTH(D$4)-4,12)+1) -> 228050 | E22: =INDEX(前提!$C$39:$N$39,MOD(MONTH(E$4)-4,12)+1) -> 228050 | F22: =INDEX(前提!$C$39:$N$39,MOD(MONTH(F$4)-4,12)+1) -> 228050 | G22: =INDEX(前提!$C$39:$N$39,MOD(MONTH(G$4)-4,12)+1) -> 228050 | H22: =INDEX(前提!$C$39:$N$39,MOD(MONTH(H$4)-4,12)+1) -> 228050 | I22: =SUM(C22:H22) -> 1368300 | J22: =INDEX(前提!$C$39:$N$39,MOD(MONTH(J$4)-4,12)+1) -> 1979117 | K22: =INDEX(前提!$C$39:$N$39,MOD(MONTH(K$4)-4,12)+1) -> 249595 | L22: =INDEX(前提!$C$39:$N$39,MOD(MONTH(L$4)-4,12)+1) -> 255950 | M22: =INDEX(前提!$C$39:$N$39,MOD(MONTH(M$4)-4,12)+1) -> 204095 | N22: =INDEX(前提!$C$39:$N$39,MOD(MONTH(N$4)-4,12)+1) -> 228050 | O22: =INDEX(前提!$C$39:$N$39,MOD(MONTH(O$4)-4,12)+1) -> 195150 | P22: =INDEX(前提!$C$39:$N$39,MOD(MONTH(P$4)-4,12)+1) -> 228050 | Q22: =INDEX(前提!$C$39:$N$39,MOD(MONTH(Q$4)-4,12)+1) -> 228050 | ... U22: =INDEX(前提!$C$39:$N$39,MOD(MONTH(U$4)-4,12)+1) -> 228050 | V22: =SUM(J22:U22) -> 4480257
A23: 消費税納付(令和9年5月) | C23: =IF(AND(YEAR(C$4)=2027,MONTH(C$4)=5),前提!$B$14,0) -> 0 | D23: =IF(AND(YEAR(D$4)=2027,MONTH(D$4)=5),前提!$B$14,0) -> 0 | E23: =IF(AND(YEAR(E$4)=2027,MONTH(E$4)=5),前提!$B$14,0) -> 0 | F23: =IF(AND(YEAR(F$4)=2027,MONTH(F$4)=5),前提!$B$14,0) -> 0 | G23: =IF(AND(YEAR(G$4)=2027,MONTH(G$4)=5),前提!$B$14,0) -> 0 | H23: =IF(AND(YEAR(H$4)=2027,MONTH(H$4)=5),前提!$B$14,0) -> 0 | I23: =SUM(C23:H23) -> 0 | J23: =IF(AND(YEAR(J$4)=2027,MONTH(J$4)=5),前提!$B$14,0) -> 0 | K23: =IF(AND(YEAR(K$4)=2027,MONTH(K$4)=5),前提!$B$14,0) -> 2965768 | L23: =IF(AND(YEAR(L$4)=2027,MONTH(L$4)=5),前提!$B$14,0) -> 0 | M23: =IF(AND(YEAR(M$4)=2027,MONTH(M$4)=5),前提!$B$14,0) -> 0 | N23: =IF(AND(YEAR(N$4)=2027,MONTH(N$4)=5),前提!$B$14,0) -> 0 | O23: =IF(AND(YEAR(O$4)=2027,MONTH(O$4)=5),前提!$B$14,0) -> 0 | P23: =IF(AND(YEAR(P$4)=2027,MONTH(P$4)=5),前提!$B$14,0) -> 0 | Q23: =IF(AND(YEAR(Q$4)=2027,MONTH(Q$4)=5),前提!$B$14,0) -> 0 | ... U23: =IF(AND(YEAR(U$4)=2027,MONTH(U$4)=5),前提!$B$14,0) -> 0 | V23: =SUM(J23:U23) -> 2965768
A24: 長期未払金の支払(手入力・4,691万円の期日未確認) | C24: 0 | D24: 0 | E24: 0 | F24: 0 | G24: 0 | H24: 0 | I24: =SUM(C24:H24) -> 0 | J24: 0 | K24: 0 | L24: 0 | M24: 0 | N24: 0 | O24: 0 | P24: 0 | Q24: 0 | R24: 0 | S24: 0 | T24: 0 | U24: 0 | V24: =SUM(J24:U24) -> 0
A25: その他臨時支出(手入力) | C25: 0 | D25: 0 | E25: 0 | F25: 0 | G25: 0 | H25: 0 | I25: =SUM(C25:H25) -> 0 | J25: 0 | K25: 0 | L25: 0 | M25: 0 | N25: 0 | O25: 0 | P25: 0 | Q25: 0 | R25: 0 | S25: 0 | T25: 0 | U25: 0 | V25: =SUM(J25:U25) -> 0
A26: 支出計 | C26: =SUM(C15:C25) -> 6209097 | D26: =SUM(D15:D25) -> 6209097 | E26: =SUM(E15:E25) -> 6209097 | F26: =SUM(F15:F25) -> 6209097 | G26: =SUM(G15:G25) -> 6209097 | H26: =SUM(H15:H25) -> 6209097 | I26: =SUM(C26:H26) -> 37254582 | J26: =SUM(J15:J25) -> 39727918 | K26: =SUM(K15:K25) -> 8765343 | L26: =SUM(L15:L25) -> 12831397 | M26: =SUM(M15:M25) -> 6450141 | N26: =SUM(N15:N25) -> 4606322 | O26: =SUM(O15:O25) -> 9362905 | P26: =SUM(P15:P25) -> 6209097 | Q26: =SUM(Q15:Q25) -> 6209097 | ... U26: =SUM(U15:U25) -> 6209097 | V26: =SUM(J26:U26) -> 118998608
A27: 収支差額(社債なし) | C27: =C13-C26 -> -2408828 | D27: =D13-D26 -> -2408828 | E27: =E13-E26 -> -2408828 | F27: =F13-F26 -> -2408828 | G27: =G13-G26 -> -2408828 | H27: =H13-H26 -> -2408828 | I27: =SUM(C27:H27) -> -14452968 | J27: =J13-J26 -> -7474269 | K27: =K13-K26 -> -4965074 | L27: =L13-L26 -> -9031128 | M27: =M13-M26 -> -2649872 | N27: =N13-N26 -> -806053 | O27: =O13-O26 -> -5562636 | P27: =P13-P26 -> -2408828 | Q27: =Q13-Q26 -> -2408828 | ... U27: =U13-U26 -> -2408828 | V27: =SUM(J27:U27) -> -44942000
A29: 翌月繰越現預金(社債なし) ① | C29: =C6+C27 -> 205530619 | D29: =D6+D27 -> 203121791 | E29: =E6+E27 -> 200712963 | F29: =F6+F27 -> 198304135 | G29: =G6+G27 -> 195895307 | H29: =H6+H27 -> 193486479 | I29: =H29 -> 193486479 | J29: =J6+J27 -> 186012210 | K29: =K6+K27 -> 181047136 | L29: =L6+L27 -> 172016008 | M29: =M6+M27 -> 169366136 | N29: =N6+N27 -> 168560083 | O29: =O6+O27 -> 162997447 | P29: =P6+P27 -> 160588619 | Q29: =Q6+Q27 -> 158179791 | ... U29: =U6+U27 -> 148544479 | V29: =U29 -> 148544479
A31: 【社債(25万USD・3年)を購入した場合の追加キャッシュフロー】
A32: 社債購入代金 | C32: =IF(((YEAR(C$4)*12+MONTH(C$4))-(YEAR(前提!$B$20)*12+MONTH(前提!$B$20)))=0,-前提!$B$27,0) -> 0 | D32: =IF(((YEAR(D$4)*12+MONTH(D$4))-(YEAR(前提!$B$20)*12+MONTH(前提!$B$20)))=0,-前提!$B$27,0) -> -39625000 | E32: =IF(((YEAR(E$4)*12+MONTH(E$4))-(YEAR(前提!$B$20)*12+MONTH(前提!$B$20)))=0,-前提!$B$27,0) -> 0 | F32: =IF(((YEAR(F$4)*12+MONTH(F$4))-(YEAR(前提!$B$20)*12+MONTH(前提!$B$20)))=0,-前提!$B$27,0) -> 0 | G32: =IF(((YEAR(G$4)*12+MONTH(G$4))-(YEAR(前提!$B$20)*12+MONTH(前提!$B$20)))=0,-前提!$B$27,0) -> 0 | H32: =IF(((YEAR(H$4)*12+MONTH(H$4))-(YEAR(前提!$B$20)*12+MONTH(前提!$B$20)))=0,-前提!$B$27,0) -> 0 | I32: =SUM(C32:H32) -> -39625000 | J32: =IF(((YEAR(J$4)*12+MONTH(J$4))-(YEAR(前提!$B$20)*12+MONTH(前提!$B$20)))=0,-前提!$B$27,0) -> 0 | K32: =IF(((YEAR(K$4)*12+MONTH(K$4))-(YEAR(前提!$B$20)*12+MONTH(前提!$B$20)))=0,-前提!$B$27,0) -> 0 | L32: =IF(((YEAR(L$4)*12+MONTH(L$4))-(YEAR(前提!$B$20)*12+MONTH(前提!$B$20)))=0,-前提!$B$27,0) -> 0 | M32: =IF(((YEAR(M$4)*12+MONTH(M$4))-(YEAR(前提!$B$20)*12+MONTH(前提!$B$20)))=0,-前提!$B$27,0) -> 0 | N32: =IF(((YEAR(N$4)*12+MONTH(N$4))-(YEAR(前提!$B$20)*12+MONTH(前提!$B$20)))=0,-前提!$B$27,0) -> 0 | O32: =IF(((YEAR(O$4)*12+MONTH(O$4))-(YEAR(前提!$B$20)*12+MONTH(前提!$B$20)))=0,-前提!$B$27,0) -> 0 | P32: =IF(((YEAR(P$4)*12+MONTH(P$4))-(YEAR(前提!$B$20)*12+MONTH(前提!$B$20)))=0,-前提!$B$27,0) -> 0 | Q32: =IF(((YEAR(Q$4)*12+MONTH(Q$4))-(YEAR(前提!$B$20)*12+MONTH(前提!$B$20)))=0,-前提!$B$27,0) -> 0 | ... U32: =IF(((YEAR(U$4)*12+MONTH(U$4))-(YEAR(前提!$B$20)*12+MONTH(前提!$B$20)))=0,-前提!$B$27,0) -> 0 | V32: =SUM(J32:U32) -> 0
A33: 社債利息(源泉税引後) | C33: =IF(AND(((YEAR(C$4)*12+MONTH(C$4))-(YEAR(前提!$B$20)*12+MONTH(前提!$B$20)))>0,((YEAR(C$4)*12+MONTH(C$4))-(YEAR(前提!$B$20)*12+MONTH(前提!$B$20)))<=前提!$B$24,MOD(((YEAR(C$4)*12+MONTH(C$4))-(YEAR(前提!$B$20)*12+MONTH(前提!$B$20))),12/前提!$B$22)=0),前提!$B$17*前提!$B$21/前提!$B$22*前提!$B$25*(1-前提!$B$23),0) -> 0 | D33: =IF(AND(((YEAR(D$4)*12+MONTH(D$4))-(YEAR(前提!$B$20)*12+MONTH(前提!$B$20)))>0,((YEAR(D$4)*12+MONTH(D$4))-(YEAR(前提!$B$20)*12+MONTH(前提!$B$20)))<=前提!$B$24,MOD(((YEAR(D$4)*12+MONTH(D$4))-(YEAR(前提!$B$20)*12+MONTH(前提!$B$20))),12/前提!$B$22)=0),前提!$B$17*前提!$B$21/前提!$B$22*前提!$B$25*(1-前提!$B$23),0) -> 0 | E33: =IF(AND(((YEAR(E$4)*12+MONTH(E$4))-(YEAR(前提!$B$20)*12+MONTH(前提!$B$20)))>0,((YEAR(E$4)*12+MONTH(E$4))-(YEAR(前提!$B$20)*12+MONTH(前提!$B$20)))<=前提!$B$24,MOD(((YEAR(E$4)*12+MONTH(E$4))-(YEAR(前提!$B$20)*12+MONTH(前提!$B$20))),12/前提!$B$22)=0),前提!$B$17*前提!$B$21/前提!$B$22*前提!$B$25*(1-前提!$B$23),0) -> 0 | F33: =IF(AND(((YEAR(F$4)*12+MONTH(F$4))-(YEAR(前提!$B$20)*12+MONTH(前提!$B$20)))>0,((YEAR(F$4)*12+MONTH(F$4))-(YEAR(前提!$B$20)*12+MONTH(前提!$B$20)))<=前提!$B$24,MOD(((YEAR(F$4)*12+MONTH(F$4))-(YEAR(前提!$B$20)*12+MONTH(前提!$B$20))),12/前提!$B$22)=0),前提!$B$17*前提!$B$21/前提!$B$22*前提!$B$25*(1-前提!$B$23),0) -> 0 | G33: =IF(AND(((YEAR(G$4)*12+MONTH(G$4))-(YEAR(前提!$B$20)*12+MONTH(前提!$B$20)))>0,((YEAR(G$4)*12+MONTH(G$4))-(YEAR(前提!$B$20)*12+MONTH(前提!$B$20)))<=前提!$B$24,MOD(((YEAR(G$4)*12+MONTH(G$4))-(YEAR(前提!$B$20)*12+MONTH(前提!$B$20))),12/前提!$B$22)=0),前提!$B$17*前提!$B$21/前提!$B$22*前提!$B$25*(1-前提!$B$23),0) -> 0 | H33: =IF(AND(((YEAR(H$4)*12+MONTH(H$4))-(YEAR(前提!$B$20)*12+MONTH(前提!$B$20)))>0,((YEAR(H$4)*12+MONTH(H$4))-(YEAR(前提!$B$20)*12+MONTH(前提!$B$20)))<=前提!$B$24,MOD(((YEAR(H$4)*12+MONTH(H$4))-(YEAR(前提!$B$20)*12+MONTH(前提!$B$20))),12/前提!$B$22)=0),前提!$B$17*前提!$B$21/前提!$B$22*前提!$B$25*(1-前提!$B$23),0) -> 0 | I33: =SUM(C33:H33) -> 0 | J33: =IF(AND(((YEAR(J$4)*12+MONTH(J$4))-(YEAR(前提!$B$20)*12+MONTH(前提!$B$20)))>0,((YEAR(J$4)*12+MONTH(J$4))-(YEAR(前提!$B$20)*12+MONTH(前提!$B$20)))<=前提!$B$24,MOD(((YEAR(J$4)*12+MONTH(J$4))-(YEAR(前提!$B$20)*12+MONTH(前提!$B$20))),12/前提!$B$22)=0),前提!$B$17*前提!$B$21/前提!$B$22*前提!$B$25*(1-前提!$B$23),0) -> 0 | K33: =IF(AND(((YEAR(K$4)*12+MONTH(K$4))-(YEAR(前提!$B$20)*12+MONTH(前提!$B$20)))>0,((YEAR(K$4)*12+MONTH(K$4))-(YEAR(前提!$B$20)*12+MONTH(前提!$B$20)))<=前提!$B$24,MOD(((YEAR(K$4)*12+MONTH(K$4))-(YEAR(前提!$B$20)*12+MONTH(前提!$B$20))),12/前提!$B$22)=0),前提!$B$17*前提!$B$21/前提!$B$22*前提!$B$25*(1-前提!$B$23),0) -> 1170770.1 | L33: =IF(AND(((YEAR(L$4)*12+MONTH(L$4))-(YEAR(前提!$B$20)*12+MONTH(前提!$B$20)))>0,((YEAR(L$4)*12+MONTH(L$4))-(YEAR(前提!$B$20)*12+MONTH(前提!$B$20)))<=前提!$B$24,MOD(((YEAR(L$4)*12+MONTH(L$4))-(YEAR(前提!$B$20)*12+MONTH(前提!$B$20))),12/前提!$B$22)=0),前提!$B$17*前提!$B$21/前提!$B$22*前提!$B$25*(1-前提!$B$23),0) -> 0 | M33: =IF(AND(((YEAR(M$4)*12+MONTH(M$4))-(YEAR(前提!$B$20)*12+MONTH(前提!$B$20)))>0,((YEAR(M$4)*12+MONTH(M$4))-(YEAR(前提!$B$20)*12+MONTH(前提!$B$20)))<=前提!$B$24,MOD(((YEAR(M$4)*12+MONTH(M$4))-(YEAR(前提!$B$20)*12+MONTH(前提!$B$20))),12/前提!$B$22)=0),前提!$B$17*前提!$B$21/前提!$B$22*前提!$B$25*(1-前提!$B$23),0) -> 0 | N33: =IF(AND(((YEAR(N$4)*12+MONTH(N$4))-(YEAR(前提!$B$20)*12+MONTH(前提!$B$20)))>0,((YEAR(N$4)*12+MONTH(N$4))-(YEAR(前提!$B$20)*12+MONTH(前提!$B$20)))<=前提!$B$24,MOD(((YEAR(N$4)*12+MONTH(N$4))-(YEAR(前提!$B$20)*12+MONTH(前提!$B$20))),12/前提!$B$22)=0),前提!$B$17*前提!$B$21/前提!$B$22*前提!$B$25*(1-前提!$B$23),0) -> 0 | O33: =IF(AND(((YEAR(O$4)*12+MONTH(O$4))-(YEAR(前提!$B$20)*12+MONTH(前提!$B$20)))>0,((YEAR(O$4)*12+MONTH(O$4))-(YEAR(前提!$B$20)*12+MONTH(前提!$B$20)))<=前提!$B$24,MOD(((YEAR(O$4)*12+MONTH(O$4))-(YEAR(前提!$B$20)*12+MONTH(前提!$B$20))),12/前提!$B$22)=0),前提!$B$17*前提!$B$21/前提!$B$22*前提!$B$25*(1-前提!$B$23),0) -> 0 | P33: =IF(AND(((YEAR(P$4)*12+MONTH(P$4))-(YEAR(前提!$B$20)*12+MONTH(前提!$B$20)))>0,((YEAR(P$4)*12+MONTH(P$4))-(YEAR(前提!$B$20)*12+MONTH(前提!$B$20)))<=前提!$B$24,MOD(((YEAR(P$4)*12+MONTH(P$4))-(YEAR(前提!$B$20)*12+MONTH(前提!$B$20))),12/前提!$B$22)=0),前提!$B$17*前提!$B$21/前提!$B$22*前提!$B$25*(1-前提!$B$23),0) -> 0 | Q33: =IF(AND(((YEAR(Q$4)*12+MONTH(Q$4))-(YEAR(前提!$B$20)*12+MONTH(前提!$B$20)))>0,((YEAR(Q$4)*12+MONTH(Q$4))-(YEAR(前提!$B$20)*12+MONTH(前提!$B$20)))<=前提!$B$24,MOD(((YEAR(Q$4)*12+MONTH(Q$4))-(YEAR(前提!$B$20)*12+MONTH(前提!$B$20))),12/前提!$B$22)=0),前提!$B$17*前提!$B$21/前提!$B$22*前提!$B$25*(1-前提!$B$23),0) -> 1170770.1 | ... U33: =IF(AND(((YEAR(U$4)*12+MONTH(U$4))-(YEAR(前提!$B$20)*12+MONTH(前提!$B$20)))>0,((YEAR(U$4)*12+MONTH(U$4))-(YEAR(前提!$B$20)*12+MONTH(前提!$B$20)))<=前提!$B$24,MOD(((YEAR(U$4)*12+MONTH(U$4))-(YEAR(前提!$B$20)*12+MONTH(前提!$B$20))),12/前提!$B$22)=0),前提!$B$17*前提!$B$21/前提!$B$22*前提!$B$25*(1-前提!$B$23),0) -> 0 | V33: =SUM(J33:U33) -> 2341540.2
A34: 社債償還金(令和11年11月のため対象期間外) | C34: =IF(((YEAR(C$4)*12+MONTH(C$4))-(YEAR(前提!$B$20)*12+MONTH(前提!$B$20)))=前提!$B$24,前提!$B$17*前提!$B$26,0) -> 0 | D34: =IF(((YEAR(D$4)*12+MONTH(D$4))-(YEAR(前提!$B$20)*12+MONTH(前提!$B$20)))=前提!$B$24,前提!$B$17*前提!$B$26,0) -> 0 | E34: =IF(((YEAR(E$4)*12+MONTH(E$4))-(YEAR(前提!$B$20)*12+MONTH(前提!$B$20)))=前提!$B$24,前提!$B$17*前提!$B$26,0) -> 0 | F34: =IF(((YEAR(F$4)*12+MONTH(F$4))-(YEAR(前提!$B$20)*12+MONTH(前提!$B$20)))=前提!$B$24,前提!$B$17*前提!$B$26,0) -> 0 | G34: =IF(((YEAR(G$4)*12+MONTH(G$4))-(YEAR(前提!$B$20)*12+MONTH(前提!$B$20)))=前提!$B$24,前提!$B$17*前提!$B$26,0) -> 0 | H34: =IF(((YEAR(H$4)*12+MONTH(H$4))-(YEAR(前提!$B$20)*12+MONTH(前提!$B$20)))=前提!$B$24,前提!$B$17*前提!$B$26,0) -> 0 | I34: =SUM(C34:H34) -> 0 | J34: =IF(((YEAR(J$4)*12+MONTH(J$4))-(YEAR(前提!$B$20)*12+MONTH(前提!$B$20)))=前提!$B$24,前提!$B$17*前提!$B$26,0) -> 0 | K34: =IF(((YEAR(K$4)*12+MONTH(K$4))-(YEAR(前提!$B$20)*12+MONTH(前提!$B$20)))=前提!$B$24,前提!$B$17*前提!$B$26,0) -> 0 | L34: =IF(((YEAR(L$4)*12+MONTH(L$4))-(YEAR(前提!$B$20)*12+MONTH(前提!$B$20)))=前提!$B$24,前提!$B$17*前提!$B$26,0) -> 0 | M34: =IF(((YEAR(M$4)*12+MONTH(M$4))-(YEAR(前提!$B$20)*12+MONTH(前提!$B$20)))=前提!$B$24,前提!$B$17*前提!$B$26,0) -> 0 | N34: =IF(((YEAR(N$4)*12+MONTH(N$4))-(YEAR(前提!$B$20)*12+MONTH(前提!$B$20)))=前提!$B$24,前提!$B$17*前提!$B$26,0) -> 0 | O34: =IF(((YEAR(O$4)*12+MONTH(O$4))-(YEAR(前提!$B$20)*12+MONTH(前提!$B$20)))=前提!$B$24,前提!$B$17*前提!$B$26,0) -> 0 | P34: =IF(((YEAR(P$4)*12+MONTH(P$4))-(YEAR(前提!$B$20)*12+MONTH(前提!$B$20)))=前提!$B$24,前提!$B$17*前提!$B$26,0) -> 0 | Q34: =IF(((YEAR(Q$4)*12+MONTH(Q$4))-(YEAR(前提!$B$20)*12+MONTH(前提!$B$20)))=前提!$B$24,前提!$B$17*前提!$B$26,0) -> 0 | ... U34: =IF(((YEAR(U$4)*12+MONTH(U$4))-(YEAR(前提!$B$20)*12+MONTH(前提!$B$20)))=前提!$B$24,前提!$B$17*前提!$B$26,0) -> 0 | V34: =SUM(J34:U34) -> 0
A35: 社債によるキャッシュ増減 | C35: =SUM(C32:C34) -> 0 | D35: =SUM(D32:D34) -> -39625000 | E35: =SUM(E32:E34) -> 0 | F35: =SUM(F32:F34) -> 0 | G35: =SUM(G32:G34) -> 0 | H35: =SUM(H32:H34) -> 0 | I35: =SUM(C35:H35) -> -39625000 | J35: =SUM(J32:J34) -> 0 | K35: =SUM(K32:K34) -> 1170770.1 | L35: =SUM(L32:L34) -> 0 | M35: =SUM(M32:M34) -> 0 | N35: =SUM(N32:N34) -> 0 | O35: =SUM(O32:O34) -> 0 | P35: =SUM(P32:P34) -> 0 | Q35: =SUM(Q32:Q34) -> 1170770.1 | ... U35: =SUM(U32:U34) -> 0 | V35: =SUM(J35:U35) -> 2341540.2
A36: 社債の累計キャッシュ増減 | C36: =C35 -> 0 | D36: =C36+D35 -> -39625000 | E36: =D36+E35 -> -39625000 | F36: =E36+F35 -> -39625000 | G36: =F36+G35 -> -39625000 | H36: =G36+H35 -> -39625000 | I36: =H36 -> -39625000 | J36: =H36+J35 -> -39625000 | K36: =J36+K35 -> -38454230 | L36: =K36+L35 -> -38454230 | M36: =L36+M35 -> -38454230 | N36: =M36+N35 -> -38454230 | O36: =N36+O35 -> -38454230 | P36: =O36+P35 -> -38454230 | Q36: =P36+Q35 -> -37283460 | R36: =Q36+R35 -> -37283460 | ... U36: =T36+U35 -> -37283460 | V36: =U36 -> -37283460
A37: 翌月繰越現預金(社債あり) ② | C37: =C29+C36 -> 205530619 | D37: =D29+D36 -> 163496791 | E37: =E29+E36 -> 161087963 | F37: =F29+F36 -> 158679135 | G37: =G29+G36 -> 156270307 | H37: =H29+H36 -> 153861479 | I37: =H37 -> 153861479 | J37: =J29+J36 -> 146387210 | K37: =K29+K36 -> 1.4259291e+08 | L37: =L29+L36 -> 1.3356178e+08 | M37: =M29+M36 -> 1.3091191e+08 | N37: =N29+N36 -> 1.3010585e+08 | O37: =O29+O36 -> 1.2454322e+08 | P37: =P29+P36 -> 1.2213439e+08 | Q37: =Q29+Q36 -> 1.2089633e+08 | ... U37: =U29+U36 -> 1.1126102e+08 | V37: =U37 -> 1.1126102e+08
A38: 差額(②−①) | C38: =C37-C29 -> 0 | D38: =D37-D29 -> -39625000 | E38: =E37-E29 -> -39625000 | F38: =F37-F29 -> -39625000 | G38: =G37-G29 -> -39625000 | H38: =H37-H29 -> -39625000 | I38: =I37-I29 -> -39625000 | J38: =J37-J29 -> -39625000 | ... V38: =V37-V29 -> -37283460
A40: ※社債は購入月に代金を全額支出、利息は源泉税15.315%控除後で入金する前提。源泉税は欠損のため法人税申告で還付(決算後)となり、この表には含めていません。
A41: ※下期(10〜3月)の月次実績は資料になく、経費は5〜9月の中央値、収入は直近3か月平均で置いた保守的な見積りです。土地売却・貸付金回収は黄色欄に入力すると反映されます。

Sheet 経費内訳
A1: 経費の内訳(令和8年度 4〜9月実績と前年同期比)
A2: 出典: 残高推移表(令和7年度・8年度の4〜9月累計)。金額は円。令和8年度は実績シートから参照。
A4: 科目 | B4: 令和7年度 4〜9月 | C4: 令和8年度 4〜9月 | D4: 増減 | E4: 増減率 | F4: 構成比(R8・減価償却除く) | G4: 月平均(R8) | H4: コメント
A5: 保険料 | B5: 24221849 | C5: =実績!H14 -> 24617595 | D5: =C5-B5 -> 395746 | E5: =IF(B5=0,"-",D5/B5) -> 0.016338389 | F5: =C5/C$24 -> 0.31249225 | G5: =C5/6 -> 4102932.5 | H5: 最大の経費(約3割)。納付月にばらつき。BS前払費用が上期に+840万円増加しており、支払額は費用計上額より多い可能性。払込スケジュールを要確認
A6: 役員報酬 | B6: 12300000 | C6: =実績!H9 -> 12300000 | D6: =C6-B6 -> 0 | E6: =IF(B6=0,"-",D6/B6) -> 0 | F6: =C6/C$24 -> 0.15613445 | G6: =C6/6 -> 2050000 | H6: 月90万円+9月に150万円の上乗せ(前年同額)
A7: 接待交際費 | B7: 8183556 | C7: =実績!H18 -> 9044839 | D7: =C7-B7 -> 861283 | E7: =IF(B7=0,"-",D7/B7) -> 0.10524557 | F7: =C7/C$24 -> 0.1148139 | G7: =C7/6 -> 1507473.2 | H7: 前年比+86万円
A8: 租税公課 | B8: 7581824 | C8: =実績!H15 -> 7291552 | D8: =C8-B8 -> -290272 | E8: =IF(B8=0,"-",D8/B8) -> -0.038285246 | F8: =C8/C$24 -> 0.092557924 | G8: =C8/6 -> 1215258.7 | H8: 4〜5月に集中(固定資産税等)。下期はほぼ発生しない実績パターン
A9: 事務員給与 | B9: 7872787 | C9: =実績!H10 -> 6215372 | D9: =C9-B9 -> -1657415 | E9: =IF(B9=0,"-",D9/B9) -> -0.21052456 | F9: =C9/C$24 -> 0.078897048 | G9: =C9/6 -> 1035895.3 | H9: 前年は6月・7月に増加があり今期は減少
A10: 厚生費 | B10: 3816552 | C10: =実績!H13 -> 4820303 | D10: =C10-B10 -> 1003751 | E10: =IF(B10=0,"-",D10/B10) -> 0.26299943 | F10: =C10/C$24 -> 0.061188241 | G10: =C10/6 -> 803383.83 | H10: 前年比+100万円(+26%)
A11: 通信交通費 | B11: 3555319 | C11: =実績!H17 -> 3566993 | D11: =C11-B11 -> 11674 | E11: =IF(B11=0,"-",D11/B11) -> 0.003283531 | F11: =C11/C$24 -> 0.045278902 | G11: =C11/6 -> 594498.83
A12: 水道光熱費 | B12: 2249822 | C12: =実績!H16 -> 2288413 | D12: =C12-B12 -> 38591 | E12: =IF(B12=0,"-",D12/B12) -> 0.017152913 | F12: =C12/C$24 -> 0.029048789 | G12: =C12/6 -> 381402.17
A13: 諸会費 | B13: 1627291 | C13: =実績!H19 -> 1907019 | D13: =C13-B13 -> 279728 | E13: =IF(B13=0,"-",D13/B13) -> 0.17189796 | F13: =C13/C$24 -> 0.024207428 | G13: =C13/6 -> 317836.5
A14: 法定福利費 | B14: 1607693 | C14: =実績!H12 -> 1703283 | D14: =C14-B14 -> 95590 | E14: =IF(B14=0,"-",D14/B14) -> 0.059457869 | F14: =C14/C$24 -> 0.021621232 | G14: =C14/6 -> 283880.5
A15: 管理諸費 | B15: 2638934 | C15: =実績!H23 -> 1722251 | D15: =C15-B15 -> -916683 | E15: =IF(B15=0,"-",D15/B15) -> -0.34736867 | F15: =C15/C$24 -> 0.021862009 | G15: =C15/6 -> 287041.83 | H15: 前年7月に113万円の臨時計上があり今期は減少
A16: 雑費 | B16: 1409060 | C16: =実績!H24 -> 1321156 | D16: =C16-B16 -> -87904 | E16: =IF(B16=0,"-",D16/B16) -> -0.062384852 | F16: =C16/C$24 -> 0.016770566 | G16: =C16/6 -> 220192.67
A17: 従業員賞与 | B17: 650000 | C17: =実績!H11 -> 650000 | D17: =C17-B17 -> 0 | E17: =IF(B17=0,"-",D17/B17) -> 0 | F17: =C17/C$24 -> 0.0082510075 | G17: =C17/6 -> 108333.33
A18: 備品消耗品費 | B18: 343045 | C18: =実績!H22 -> 629407 | D18: =C18-B18 -> 286362 | E18: =IF(B18=0,"-",D18/B18) -> 0.83476512 | F18: =C18/C$24 -> 0.0079896029 | G18: =C18/6 -> 104901.17 | H18: 8〜9月に増加(前年比+83%)
A19: 修繕費 | B19: 754212 | C19: =実績!H20 -> 413029 | D19: =C19-B19 -> -341183 | E19: =IF(B19=0,"-",D19/B19) -> -0.45237016 | F19: =C19/C$24 -> 0.0052429314 | G19: =C19/6 -> 68838.167
A20: 事務用消耗品費 | B20: 84896 | C20: =実績!H21 -> 218496 | D20: =C20-B20 -> 133600 | E20: =IF(B20=0,"-",D20/B20) -> 1.5736902 | F20: =C20/C$24 -> 0.0027735571 | G20: =C20/6 -> 36416
A21: 広告宣伝費 | B21: 154500 | C21: =実績!H25 -> 38250 | D21: =C21-B21 -> -116250 | E21: =IF(B21=0,"-",D21/B21) -> -0.75242718 | F21: =C21/C$24 -> 0.00048554006 | G21: =C21/6 -> 6375
A22: 新聞図書費 | B22: 1000 | C22: =実績!H26 -> 20300 | D22: =C22-B22 -> 19300 | E22: =IF(B22=0,"-",D22/B22) -> 19.3 | F22: =C22/C$24 -> 0.00025768531 | G22: =C22/6 -> 3383.3333
A23: 寄付金 | B23: 30000 | C23: =実績!H27 -> 10000 | D23: =C23-B23 -> -20000 | E23: =IF(B23=0,"-",D23/B23) -> -0.66666667 | F23: =C23/C$24 -> 0.00012693858 | G23: =C23/6 -> 1666.6667
A24: 経費計(減価償却費を除く) | B24: =SUM(B5:B23) -> 79082340 | C24: =SUM(C5:C23) -> 78778258 | D24: =SUM(D5:D23) -> -304082 | E24: =D24/B24 -> -0.0038451315 | F24: =SUM(F5:F23) -> 1 | G24: =SUM(G5:G23) -> 13129710
A25: 減価償却費(非資金・参考) | B25: 2057517 | C25: =実績!H28 -> 1668000
A27: 資金繰り表での見積り(グループ別)
A28: グループ | B28: 令和8年度 4〜9月(実績) | C28: 令和8年度 10〜3月(見込) | D28: 令和8年度 年間 | E28: 10〜3月の置き方
A29: 役員報酬 | B29: =SUM(前提!C32:H32) -> 12300000 | C29: =SUM(前提!I32:N32) -> 5400000 | D29: =B29+C29 -> 17700000 | E29: 5〜9月の月次中央値×6
A30: 給与・賞与・福利厚生 | B30: =SUM(前提!C33:H33) -> 13388958 | C30: =SUM(前提!I33:N33) -> 6636324 | D30: =B30+C30 -> 20025282 | E30: 5〜9月の月次中央値×6
A31: 保険料 | B31: =SUM(前提!C34:H34) -> 24617595 | C31: =SUM(前提!I34:N34) -> 15548688 | D31: =B31+C31 -> 40166283 | E31: 5〜9月の月次中央値×6
A32: 租税公課 | B32: =SUM(前提!C35:H35) -> 7291552 | C32: =SUM(前提!I35:N35) -> 137712 | D32: =B32+C32 -> 7429264 | E32: 5〜9月の月次中央値×6
A33: 水道光熱・通信交通 | B33: =SUM(前提!C36:H36) -> 5855406 | C33: =SUM(前提!I36:N36) -> 3091392 | D33: =B33+C33 -> 8946798 | E33: 5〜9月の月次中央値×6
A34: 接待交際・諸会費 | B34: =SUM(前提!C37:H37) -> 10951858 | C34: =SUM(前提!I37:N37) -> 4523316 | D34: =B34+C34 -> 15475174 | E34: 5〜9月の月次中央値×6
A35: 修繕・消耗品 | B35: =SUM(前提!C38:H38) -> 1260932 | C35: =SUM(前提!I38:N38) -> 548850 | D35: =B35+C35 -> 1809782 | E35: 5〜9月の月次中央値×6
A36: 管理諸費・雑費・その他 | B36: =SUM(前提!C39:H39) -> 3111957 | C36: =SUM(前提!I39:N39) -> 1368300 | D36: =B36+C36 -> 4480257 | E36: 5〜9月の月次中央値×6
A37: 合計 | B37: =SUM(B29:B36) -> 78778258 | C37: =SUM(C29:C36) -> 37254582 | D37: =SUM(D29:D36) -> 116032840
A38: ※下期の月次実績がないため、令和9年度は同じ年間パターンの繰り返しとして見積もっています。保険料・接待交際費などは実際の予定に合わせて前提シートの月別表を直接修正できます。

Sheet 家賃明細
A1: 賃貸収入明細 (株)旭土地建物(令和8年10月15日付・月額)
A2: 出典: アップロードされた「賃貸収入・支出明細」シート R8.10.15。コインパーキングは令和7年1〜12月の月平均。青字=転記値。
A4: 借主 | B4: 月額家賃(円) | C4: 備考
A5: みずほ銀行 | B5: 212190
A6: ジェントルマン | B6: 165000
A7: XYZ | B7: 159814
A8: 坂本不動産 | B8: 81650 | C8: グループ会社からの家賃
A9: カナコン | B9: 427776
A10: ファミリー歯科 | B10: 203703
A11: 緑園カレージ(10) | B11: 440000
A12: 善部 | B12: 16500
A13: 南万騎が原コインパーキング | B13: 464970 | C13: R7.1〜12平均
A14: 厚木コインパーキング | B14: 628666 | C14: R7.1〜12平均
A15: サカモト(横浜西口) | B15: 1000000 | C15: グループ会社からの家賃
A17: 月額合計 | B17: =SUM(B5:B15) -> 3800269
A18: 元ファイルの合計(検算) | B18: 3800269 | C18: =IF(B17=B18,"一致","差異あり") -> 一致
A19: 家賃支出(元ファイル) | B19: 0 | C19: 旭土地建物の「家賃支出」欄は0
A21: 参考: 令和8年7〜9月の月次賃貸売上(会計上)の平均 | B21: =AVERAGE(実績!M6:O6) -> 3242981.7
A22: 最新明細との差 | B22: =B17-B21 -> 557287.33
A23: ※会計上の4月計上(年間分約2,500万円)は明細の月額に含まれていません。内容(年払い・精算など)を確認してください。

Sheet 社債検討
A1: 社債の採算確認と賃貸アパートとの比較
A2: 数値は前提シートの設定を引用。比較用アパート条件は仮置き(青字)なので、実際の物件資料に置き換えてください。
A4: 1. 社債の損益(為替を購入時のまま固定した場合)
A5: 投資額(円) | B5: =前提!B27 -> 39625000
A6: 年間利息(USD) | B6: =前提!B17*前提!B21 -> 17500
A7: 年間利息(円・税引前) | B7: =B6*前提!B25 -> 2765000
A8: 年間利息(円・源泉税引後) | B8: =B7*(1-前提!B23) -> 2341540.2
A9: 3年間の税引後利息(円) | B9: =B8*前提!B24/12 -> 7024620.8
A10: 円ベース年利回り(税引後・手数料込み) | B10: =B9/B5/(前提!B24/12) -> 0.059092498 | C10: 提示の7%から、源泉税と為替手数料の分だけ低下
A11: 損益分岐の償還時為替(円/USD) | B11: =(B5-B9)/前提!B17 -> 130.40152 | C11: これより円高になると3年トータルで元本割れ(円ベース)
A12: 許容できる円高幅(購入時比) | B12: =1-B11/前提!B18 -> 0.17467394
A14: 2. 償還時の為替別 3年間の損益(円)
A15: 償還時為替(円/USD) | B15: 3年間の損益(円) | C15: 年率換算(単純)
A16: 120 | B16: =B$9+前提!$B$17*A16-B$5 -> -2600379.2 | C16: =B16/B$5/(前提!$B$24/12) -> -0.021874904
A17: 130 | B17: =B$9+前提!$B$17*A17-B$5 -> -100379.25 | C17: =B17/B$5/(前提!$B$24/12) -> -0.00084441009
A18: 140 | B18: =B$9+前提!$B$17*A18-B$5 -> 2399620.8 | C18: =B18/B$5/(前提!$B$24/12) -> 0.020186084
A19: 150 | B19: =B$9+前提!$B$17*A19-B$5 -> 4899620.8 | C19: =B19/B$5/(前提!$B$24/12) -> 0.041216578
A20: 160 | B20: =B$9+前提!$B$17*A20-B$5 -> 7399620.8 | C20: =B20/B$5/(前提!$B$24/12) -> 0.062247073
A21: 170 | B21: =B$9+前提!$B$17*A21-B$5 -> 9899620.8 | C21: =B21/B$5/(前提!$B$24/12) -> 0.083277567
A22: 180 | B22: =B$9+前提!$B$17*A22-B$5 -> 12399621 | C22: =B22/B$5/(前提!$B$24/12) -> 0.10430806
A23: ※利息は購入時為替で円換算、利息への課税は源泉税のみで計算(為替差損益の課税効果は考慮していません)。
A25: 3. 賃貸アパート(同額を現金投資した場合)との比較 ※仮置き
A26: 物件価格(円) | B26: =B5 -> 39625000
A27: 表面利回り(仮置き) | B27: 0.07 | C27: 物件資料の値に置換
A28: 空室・滞納ロス(仮置き) | B28: 0.05
A29: 運営費率(管理・修繕・固定資産税・保険、仮置き) | B29: 0.2
A30: 実質利回り(税引前) | B30: =B27*(1-B28)*(1-B29) -> 0.0532
A31: 社債の円ベース利回り(上記1.より) | B31: =B10 -> 0.059092498
A32: ※アパートは円建てで為替リスクなし・売却可能な実物資産。一方で空室・修繕・出口(売却価格)のリスクと、取得に伴う諸費用があります。
A33: ※貴社は当期が大幅な欠損見込みのため、減価償却による節税効果(アパートの利点)は当面ほぼ見込めません。
A35: 4. 大和証券に確認したい事項
A36: 1. 発行体名と格付(7%は米国債などより大幅に高い水準のため、発行体の信用力を確認)
A37: 2. 7%は「表面利率」か「利回り」か。発行価格は額面100%か(割引・割増の有無)
A38: 3. 期限前償還条項(コーラブル)・利率変動・株価連動など、仕組債の要素がないか
A39: 4. 利払い頻度と利払日、受渡日(購入月の確定)
A40: 5. 為替手数料・販売手数料の総額(円転コスト、償還時の円転コスト)
A41: 6. 中途売却する場合の売却価格の目安と流動性(売れない/大幅値引きのリスク)
A42: 7. 法人の源泉徴収・会計処理(満期保有目的か、期末の為替換算)を顧問税理士に確認
A43: 8. 購入資金25万USDの円転タイミング(為替予約・外貨預金の活用可否)

Sheet 実績
A1: 実績データ(旭土地建物 勘定科目残高推移表より 令和8年度 4月〜9月)
A2: 出典: TKC勘定科目残高推移表(2026/10/27出力)。青字=PDFから転記した累計残高(円)、黒字=月次化の計算。
A4: 科目 | C4: 4月累計 | D4: 5月累計 | E4: 6月累計 | F4: 7月累計 | G4: 8月累計 | H4: 9月累計 | J4: 4月(月次) | K4: 5月(月次) | L4: 6月(月次) | M4: 7月(月次) | N4: 8月(月次) | O4: 9月(月次)
A6: 不動産賃貸売上高 | C6: 29212699 | D6: 33092018 | E6: 38789464 | F6: 42856654 | G6: 45830786 | H6: 48518409 | J6: =C6 -> 29212699 | K6: =D6-C6 -> 3879319 | L6: =E6-D6 -> 5697446 | M6: =F6-E6 -> 4067190 | N6: =G6-F6 -> 2974132 | O6: =H6-G6 -> 2687623
A7: その他売上高(4114) | C7: 3120000 | D7: 3142224 | E7: 3142224 | F7: 3142224 | G7: 3153336 | H7: 3153336 | J7: =C7 -> 3120000 | K7: =D7-C7 -> 22224 | L7: =E7-D7 -> 0 | M7: =F7-E7 -> 0 | N7: =G7-F7 -> 11112 | O7: =H7-G7 -> 0
A8: 土地売上高 | C8: 23224126 | D8: 23224126 | E8: 23224126 | F8: 73274882 | G8: 110288898 | H8: 110288898 | J8: =C8 -> 23224126 | K8: =D8-C8 -> 0 | L8: =E8-D8 -> 0 | M8: =F8-E8 -> 50050756 | N8: =G8-F8 -> 37014016 | O8: =H8-G8 -> 0
A9: 役員報酬 | C9: 6300000 | D9: 7200000 | E9: 8100000 | F9: 9000000 | G9: 9900000 | H9: 12300000 | J9: =C9 -> 6300000 | K9: =D9-C9 -> 900000 | L9: =E9-D9 -> 900000 | M9: =F9-E9 -> 900000 | N9: =G9-F9 -> 900000 | O9: =H9-G9 -> 2400000
A10: 事務員給与 | C10: 3506339 | D10: 3938661 | E10: 4375281 | F10: 5361041 | G10: 5795942 | H10: 6215372 | J10: =C10 -> 3506339 | K10: =D10-C10 -> 432322 | L10: =E10-D10 -> 436620 | M10: =F10-E10 -> 985760 | N10: =G10-F10 -> 434901 | O10: =H10-G10 -> 419430
A11: 従業員賞与 | C11: 650000 | D11: 650000 | E11: 650000 | F11: 650000 | G11: 650000 | H11: 650000 | J11: =C11 -> 650000 | K11: =D11-C11 -> 0 | L11: =E11-D11 -> 0 | M11: =F11-E11 -> 0 | N11: =G11-F11 -> 0 | O11: =H11-G11 -> 0
A12: 法定福利費 | C12: 1006271 | D12: 1004128 | E12: 1252495 | F12: 1372299 | G12: 1495408 | H12: 1703283 | J12: =C12 -> 1006271 | K12: =D12-C12 -> -2143 | L12: =E12-D12 -> 248367 | M12: =F12-E12 -> 119804 | N12: =G12-F12 -> 123109 | O12: =H12-G12 -> 207875
A13: 厚生費 | C13: 2970906 | D13: 3213285 | E13: 3634352 | F13: 3907088 | G13: 4239956 | H13: 4820303 | J13: =C13 -> 2970906 | K13: =D13-C13 -> 242379 | L13: =E13-D13 -> 421067 | M13: =F13-E13 -> 272736 | N13: =G13-F13 -> 332868 | O13: =H13-G13 -> 580347
A14: 保険料 | C14: 6100386 | D14: 6969174 | E14: 16138245 | F14: 18729693 | G14: 20079749 | H14: 24617595 | J14: =C14 -> 6100386 | K14: =D14-C14 -> 868788 | L14: =E14-D14 -> 9169071 | M14: =F14-E14 -> 2591448 | N14: =G14-F14 -> 1350056 | O14: =H14-G14 -> 4537846
A15: 租税公課 | C15: 5496995 | D15: 7216795 | E15: 7252295 | F15: 7268000 | G15: 7290952 | H15: 7291552 | J15: =C15 -> 5496995 | K15: =D15-C15 -> 1719800 | L15: =E15-D15 -> 35500 | M15: =F15-E15 -> 15705 | N15: =G15-F15 -> 22952 | O15: =H15-G15 -> 600
A16: 水道光熱費 | C16: 1244308 | D16: 1408709 | E16: 1596998 | F16: 1827900 | G16: 2055681 | H16: 2288413 | J16: =C16 -> 1244308 | K16: =D16-C16 -> 164401 | L16: =E16-D16 -> 188289 | M16: =F16-E16 -> 230902 | N16: =G16-F16 -> 227781 | O16: =H16-G16 -> 232732
A17: 通信交通費 | C17: 1995319 | D17: 2255572 | E17: 2574708 | F17: 2859038 | G17: 3281175 | H17: 3566993 | J17: =C17 -> 1995319 | K17: =D17-C17 -> 260253 | L17: =E17-D17 -> 319136 | M17: =F17-E17 -> 284330 | N17: =G17-F17 -> 422137 | O17: =H17-G17 -> 285818
... A29: 販売費及び一般管理費(PDF合計) | C29: 40895518 | D29: 46861893 | E29: 59860090 | F29: 66477031 | G29: 71083353 | H29: 80446258 | J29: =C29 -> 40895518 | K29: =D29-C29 -> 5966375 | L29: =E29-D29 -> 12998197 | M29: =F29-E29 -> 6616941 | N29: =G29-F29 -> 4606322 | O29: =H29-G29 -> 9362905
A30: 検算(科目合計−PDF合計 ※0であること) | C30: =SUM(C9:C28)-C29 -> 0 | D30: =SUM(D9:D28)-D29 -> 0 | E30: =SUM(E9:E28)-E29 -> 0 | F30: =SUM(F9:F28)-F29 -> 0 | G30: =SUM(G9:G28)-G29 -> 0 | H30: =SUM(H9:H28)-H29 -> 0 | J30: =SUM(J9:J28)-J29 -> 0 | K30: =SUM(K9:K28)-K29 -> 0 | L30: =SUM(L9:L28)-L29 -> 0 | M30: =SUM(M9:M28)-M29 -> 0 | N30: =SUM(N9:N28)-N29 -> 0 | O30: =SUM(O9:O28)-O29 -> 0
A33: 現預金残高の推移(各年度 4〜9月末、円) ※BS「現預金小計」
A34: 年度 | C34: 4月 | D34: 5月 | E34: 6月 | F34: 7月 | G34: 8月 | H34: 9月 | J34: 9月末→翌4月末の増減
A35: 令和5年度 | C35: 210496736 | D35: 235588670 | E35: 228363600 | F35: 218394670 | G35: 215303200 | H35: 196813496 | J35: =C36-H35 -> -32196116
A36: 令和6年度 | C36: 164617380 | D36: 159086521 | E36: 149819904 | F36: 138952867 | G36: 134547396 | H36: 112635095 | J36: =C37-H36 -> 28731453
A37: 令和7年度 | C37: 141366548 | D37: 138136071 | E37: 126713763 | F37: 110696581 | G37: 112494414 | H37: 122419789 | J37: =C38-H37 -> 21593471
A38: 令和8年度 | C38: 144013260 | D38: 139822640 | E38: 129332969 | F38: 176629765 | G38: 211301042 | H38: 207939447
A40: ※下期(10〜3月)の月次データは今回の資料に含まれていません。9月末→翌4月末の増減には貸付金回収・保険解約等の臨時入金も含まれます。
A42: 賃貸売上(累計→月次、円) 前年度比較
A43: 年度 | C43: 4月(月次) | D43: 5月(月次) | E43: 6月(月次) | F43: 7月(月次) | G43: 8月(月次) | H43: 9月(月次)
A44: 令和5年度 | C44: 30948037 | D44: 4566603 | E44: 5128035 | F44: 4431206 | G44: 3177167 | H44: 7632065
A45: 令和6年度 | C45: 27062023 | D45: 3312630 | E45: 4441632 | F45: 4330181 | G45: 3420777 | H45: 3880873
A46: 令和7年度 | C46: 27354678 | D46: 3731531 | E46: 4537984 | F46: 3922121 | G46: 3891538 | H46: 5518338
A47: 令和8年度 | C47: 29212699 | D47: 3879319 | E47: 5697446 | F47: 4067190 | G47: 2974132 | H47: 2687623
A48: ※4月に年間分と思われる大口計上(約2,500万円)があり、毎年同じパターン。5月以降は月400万円前後で、令和8年度は8〜9月に低下。
