Workbook

Sheet サマリー
A1: 来期(令和9年9月期)資金繰り検討サマリー(株式会社旭土地建物)
A2: 来期=令和8年10月〜令和9年9月(決算月は9月) ・ 基礎資料: 令和5〜8年9月期の勘定科目残高推移表、賃貸収入明細(R8.10.15)、保険一覧(R8.6.10) ・ 単位: 千円
A4: 主要指標 | F4: グラフ用(月次残高)
B5: 社債なし | C5: 社債あり | D5: 差額 | F5: 月 | G5: 社債なし | H5: 社債あり
A6: 期首現預金(令和8年9月末) | B6: =資金繰り表!C6 -> 207939447 | C6: =資金繰り表!C6 -> 207939447 | D6: =C6-B6 -> 0 | F6: =資金繰り表!C4 -> 46296 | G6: =資金繰り表!C29 -> 207423442 | H6: =資金繰り表!C37 -> 207423442
A7: 来期の収入計(家賃のみ) | B7: =資金繰り表!O13 -> 45603228 | C7: =資金繰り表!O13+資金繰り表!O33 -> 46773998 | D7: =C7-B7 -> 1170770.1 | F7: =資金繰り表!D4 -> 46327 | G7: =資金繰り表!D29 -> 204098045 | H7: =資金繰り表!D37 -> 164473045
A8: 来期の支出計(社債ありは購入代金を含む) | B8: =資金繰り表!O26 -> 89310602 | C8: =資金繰り表!O26-資金繰り表!O32-資金繰り表!O34 -> 128935602 | D8: =C8-B8 -> 39625000 | F8: =資金繰り表!E4 -> 46357 | G8: =資金繰り表!E29 -> 201516131 | H8: =資金繰り表!E37 -> 161891131
A9: 来期の収支(増減) | B9: =資金繰り表!O27 -> -43707374 | C9: =資金繰り表!O27+資金繰り表!O35 -> -82161604 | D9: =C9-B9 -> -38454230 | F9: =資金繰り表!F4 -> 46388 | G9: =資金繰り表!F29 -> 200590744 | H9: =資金繰り表!F37 -> 160965744
A10: 来期末残高(令和9年9月末) | B10: =資金繰り表!O29 -> 164232073 | C10: =資金繰り表!O37 -> 1.2577784e+08 | D10: =C10-B10 -> -38454230 | F10: =資金繰り表!G4 -> 46419 | G10: =資金繰り表!G29 -> 199898670 | H10: =資金繰り表!G37 -> 160273670
A11: 来期の最低残高 | B11: =MIN(資金繰り表!C29,資金繰り表!D29,資金繰り表!E29,資金繰り表!F29,資金繰り表!G29,資金繰り表!H29,資金繰り表!I29,資金繰り表!J29,資金繰り表!K29,資金繰り表!L29,資金繰り表!M29,資金繰り表!N29) -> 164232073 | C11: =MIN(資金繰り表!C37,資金繰り表!D37,資金繰り表!E37,資金繰り表!F37,資金繰り表!G37,資金繰り表!H37,資金繰り表!I37,資金繰り表!J37,資金繰り表!K37,資金繰り表!L37,資金繰り表!M37,資金繰り表!N37) -> 1.2577784e+08 | D11: =C11-B11 -> -38454230 | F11: =資金繰り表!H4 -> 46447 | G11: =資金繰り表!H29 -> 199042032 | H11: =資金繰り表!H37 -> 159417032
A12: 月平均の経費支出 | B12: =資金繰り表!O26/12 -> 7442550.2 | C12: =資金繰り表!O26/12 -> 7442550.2 | D12: =C12-B12 -> 0 | F12: =資金繰り表!I4 -> 46478 | G12: =資金繰り表!I29 -> 193180908 | H12: =資金繰り表!I37 -> 153555908
A13: 期末残高の経費月数(手元流動性) | B13: =B10/B12 -> 22.06664 | C13: =C10/C12 -> 16.899831 | D13: =C13-B13 -> -5.1668083 | F13: =資金繰り表!J4 -> 46508 | G13: =資金繰り表!J29 -> 191157532 | H13: =資金繰り表!J37 -> 1.527033e+08
A14: 社債の年間税引後利息(円ベース) | C14: =社債検討!B8 -> 2341540.2 | F14: =資金繰り表!K4 -> 46539 | G14: =資金繰り表!K29 -> 178662178 | H14: =資金繰り表!K37 -> 1.4020795e+08
A15: 社債の円ベース利回り(税引後) | C15: =社債検討!B10 -> 0.059092498 | F15: =資金繰り表!L4 -> 46569 | G15: =資金繰り表!L29 -> 176003236 | H15: =資金繰り表!L37 -> 1.3754901e+08
A16: 損益分岐の償還時為替(円/USD) | C16: =社債検討!B11 -> 130.40152 | F16: =資金繰り表!M4 -> 46600 | G16: =資金繰り表!M29 -> 175654381 | H16: =資金繰り表!M37 -> 1.3720015e+08
A17: 参考: 令和8年9月期の現預金増減(実績) | B17: =実績!N38-実績!N37 -> 85519658 | F17: =資金繰り表!N4 -> 46631 | G17: =資金繰り表!N29 -> 164232073 | H17: =資金繰り表!N37 -> 1.2577784e+08
A19: 読み取りのポイント
A20: ・訂正: 決算月は9月で、事業年度は10月〜9月でした(残高推移表の累計は10月起算)。先に年度を4〜3月として見積もっていたため、期間・数値を作り直しました。
A21: ・来期は建売・土地の在庫がなく収入は家賃のみ(最新明細で月約380万円、年約4,560万円)。令和8年9月期の現預金増加(約8,550万円)は、土地売上約1億1,000万円や貸付金回収など在庫・貸付金の資金化によるもので、家賃と経費だけでは赤字です。
A22: ・経費は令和8年9月期が約7,878万円(月約660万円)で前期並み。保険料は旭土地の保険一覧の現金支払(年約3,367万円、6月・9月に集中)に置き換えており、会計上の保険料(約2,462万円)より約900万円多くなります(差は前払費用に計上されるもの)。
A23: ・令和8年9月期の営業損失は約8,700万円・経常損失約1億300万円(土地売上が原価割れ)。BS上の商品約8,000万円の売却は見込んでいません。
A24: ・社債25万USD(約3,960万円)を購入しても、臨時収入ゼロの保守的な見積りで来期末の現預金は1億円を超えます。ただし家賃だけでは毎年残高が減るため、運転資金として何か月分残すかが判断軸です。
A25: ・7%は米ドル建てのクーポンです。円ベースでは源泉税と為替で変動し、損益分岐は社債検討シートの通り。賃貸アパートとの比較は同シートの仮置き条件で確認してください。
A26: ・長期未払金が令和8年9月に4,691万円へ倍増(毎年9月に2,345万円ずつ計上)。支払期日が未確認のため資金繰り表には含めていません。決まれば手入力欄へ。
A27: ・短期貸付金3億6,267万円・未収入金2億5,114万円・前渡金1,500万円は回収予定を反映していません(令和8年9月期は貸付金が約4,200万円回収)。回収計画があれば手入力欄へ。

Sheet 前提
A1: 前提条件(青字・黄色セルを変更すると資金繰り表が再計算されます)
A2: 来期=令和8年10月〜令和9年9月(令和9年9月期)。金額は円。青字=入力値、黒字=計算、緑字=他シート参照。
A4: 1. 開始残高・収入
A5: 期首現預金(令和8年9月末) | B5: 207939447 | C5: BS現預金小計(現金・当座・普通・定期)。出典:残高推移表
A6: 賃貸収入 月額(最新の家賃明細) | B6: =家賃明細!B17 -> 3800269 | C6: 令和8年10月15日付「賃貸収入・支出明細」旭土地建物の月額合計。毎月同額で計上
A7: 参考: 令和8年9月期の賃貸売上 月平均 | B7: =家賃明細!B21 -> 4043200.8 | C7: 会計上の実績。最新明細との差は家賃明細シート参照
A8: 参考: 令和8年9月期の土地売上 | B8: =実績!N8 -> 110288898 | C8: 来期は建売・土地の在庫がないため見込まない(0)
A9: 保険料の見積り方法(1=保険一覧の支払スケジュール 0=令和8年9月期の実績) | B9: 1 | C9: 1=現金ベース(契約ごとの払込方法・支払月)。0=会計上の保険料(損金計上額ベース)
A10: 2. 消費税納付
A11: 仮受消費税等(令和8年9月末) | B11: 4249004 | C11: BS負債の部
A12: 仮払消費税等(令和8年9月末) | B12: 2766120 | C12: BS資産の部
A13: 納付月(決算の2か月後) | B13: 11 | C13: 9月決算→11月末納付
A14: 消費税納付見込(令和8年9月期分) | B14: =B11-B12 -> 1482884 | C14: 差額の概算。来期分の預り消費税は来々期に納付のため、来期の収入側には含めていません(保守的)
A16: 3. 社債(大和証券 提案)
A17: 購入額(額面・USD) | B17: 250000 | C17: 最低購入単位25万ドル(ご提示)
A18: 購入時為替(円/USD) | B18: 158 | C18: OANDA 2026/10/20「158円台半ば」を参考にした仮置き。実際の約定レートに置換
A19: 為替手数料(円/USD) | B19: 0.5 | C19: 仮置き。大和証券へ要確認(購入価格に含まれる場合あり)
A20: 購入年月 | B20: 46327 | C20: 仮置き(申込〜受渡し日に合わせて変更)
A21: 年利(クーポン) | B21: 0.07 | C21: ご提示。「利回り」か「表面利率」か、発行価格が額面かは要確認
A22: 利払回数(年) | B22: 2 | C22: 1=年1回、2=半年ごと。要確認
A23: 国内源泉徴収税率 | B23: 0.15315 | C23: 法人は所得税15.315%が源泉され法人税から控除される想定(欠損のため還付は決算後)。税理士確認
A24: 保有期間(月) | B24: 36 | C24: 3年満期
A25: 利払時の想定為替 | B25: =B18 -> 158 | C25: 既定=購入時と同じ。円高/円安シナリオは上書き
A26: 償還時の想定為替 | B26: =B18 -> 158 | C26: 既定=購入時と同じ。円高/円安シナリオは社債検討シートで分析
A27: 購入代金(円) | B27: =B17*(B18+B19) -> 39625000
A29: 4. 経費の月別パターン(現預金の支出ベース・減価償却費を除く)
A30: 令和8年9月期(令和7年10月〜令和8年9月)の月次実績を来期の同月に当てはめています。保険料のみ、切替(B9)に応じて保険一覧の現金支払スケジュールを使用。
A31: 項目 | C31: 10月 | D31: 11月 | E31: 12月 | F31: 1月 | G31: 2月 | H31: 3月 | I31: 4月 | J31: 5月 | K31: 6月 | L31: 7月 | M31: 8月 | N31: 9月 | O31: 年間計
A32: 役員報酬 | C32: =実績!P9 -> 900000 | D32: =実績!Q9 -> 900000 | E32: =実績!R9 -> 900000 | F32: =実績!S9 -> 900000 | G32: =実績!T9 -> 900000 | H32: =実績!U9 -> 900000 | I32: =実績!V9 -> 900000 | J32: =実績!W9 -> 900000 | ... N32: =実績!AA9 -> 2400000 | O32: =SUM(C32:N32) -> 12300000
A33: 給与・賞与・福利厚生 | C33: =実績!P10+実績!P11+実績!P12+実績!P13 -> 1218210 | D33: =実績!Q10+実績!Q11+実績!Q12+実績!Q13 -> 840557 | E33: =実績!R10+実績!R11+実績!R12+実績!R13 -> 2300348 | F33: =実績!S10+実績!S11+実績!S12+実績!S13 -> 1061189 | G33: =実績!T10+実績!T11+実績!T12+実績!T13 -> 1016578 | H33: =実績!U10+実績!U11+実績!U12+実績!U13 -> 880854 | I33: =実績!V10+実績!V11+実績!V12+実績!V13 -> 815780 | J33: =実績!W10+実績!W11+実績!W12+実績!W13 -> 672558 | ... N33: =実績!AA10+実績!AA11+実績!AA12+実績!AA13 -> 1207652 | O33: =SUM(C33:N33) -> 13388958
A34: 保険料 | C34: =IF($B$9=1,保険支払!C26,実績!P14) -> 892858 | D34: =IF($B$9=1,保険支払!D26,実績!Q14) -> 892858 | E34: =IF($B$9=1,保険支払!E26,実績!R14) -> 892858 | F34: =IF($B$9=1,保険支払!F26,実績!S14) -> 892858 | G34: =IF($B$9=1,保険支払!G26,実績!T14) -> 892858 | H34: =IF($B$9=1,保険支払!H26,実績!U14) -> 892858 | I34: =IF($B$9=1,保険支払!I26,実績!V14) -> 892858 | J34: =IF($B$9=1,保険支払!J26,実績!W14) -> 892858 | ... N34: =IF($B$9=1,保険支払!N26,実績!AA14) -> 10397518 | O34: =SUM(C34:N34) -> 33667055
A35: 租税公課 | C35: =実績!P15 -> 0 | D35: =実績!Q15 -> 0 | E35: =実績!R15 -> 0 | F35: =実績!S15 -> 71800 | G35: =実績!T15 -> 195769 | H35: =実績!U15 -> 5326 | I35: =実績!V15 -> 5224100 | J35: =実績!W15 -> 1719800 | ... N35: =実績!AA15 -> 600 | O35: =SUM(C35:N35) -> 7291552
A36: 水道光熱・通信交通 | C36: =実績!P16+実績!P17 -> 432715 | D36: =実績!Q16+実績!Q17 -> 441929 | E36: =実績!R16+実績!R17 -> 521112 | F36: =実績!S16+実績!S17 -> 505753 | G36: =実績!T16+実績!T17 -> 383240 | H36: =実績!U16+実績!U17 -> 494526 | I36: =実績!V16+実績!V17 -> 460352 | J36: =実績!W16+実績!W17 -> 424654 | ... N36: =実績!AA16+実績!AA17 -> 518550 | O36: =SUM(C36:N36) -> 5855406
A37: 接待交際・諸会費 | C37: =実績!P18+実績!P19 -> 670756 | D37: =実績!Q18+実績!Q19 -> 2285363 | E37: =実績!R18+実績!R19 -> 1476545 | F37: =実績!S18+実績!S19 -> 680669 | G37: =実績!T18+実績!T19 -> 664213 | H37: =実績!U18+実績!U19 -> 1203941 | I37: =実績!V18+実績!V19 -> 788903 | J37: =実績!W18+実績!W19 -> 935455 | ... N37: =実績!AA18+実績!AA19 -> 247264 | O37: =SUM(C37:N37) -> 10951858
A38: 修繕・消耗品 | C38: =実績!P20+実績!P21+実績!P22 -> 73685 | D38: =実績!Q20+実績!Q21+実績!Q22 -> 22043 | E38: =実績!R20+実績!R21+実績!R22 -> 30011 | F38: =実績!S20+実績!S21+実績!S22 -> 76544 | G38: =実績!T20+実績!T21+実績!T22 -> 122157 | H38: =実績!U20+実績!U21+実績!U22 -> 67497 | I38: =実績!V20+実績!V21+実績!V22 -> 315950 | J38: =実績!W20+実績!W21+実績!W22 -> 28725 | ... N38: =実績!AA20+実績!AA21+実績!AA22 -> 255843 | O38: =SUM(C38:N38) -> 1260932
A39: 管理諸費・雑費・その他 | C39: =実績!P23+実績!P24+実績!P25+実績!P26+実績!P27 -> 128050 | D39: =実績!Q23+実績!Q24+実績!Q25+実績!Q26+実績!Q27 -> 260032 | E39: =実績!R23+実績!R24+実績!R25+実績!R26+実績!R27 -> 261309 | F39: =実績!S23+実績!S24+実績!S25+実績!S26+実績!S27 -> 536843 | G39: =実績!T23+実績!T24+実績!T25+実績!T26+実績!T27 -> 317528 | H39: =実績!U23+実績!U24+実績!U25+実績!U26+実績!U27 -> 211905 | I39: =実績!V23+実績!V24+実績!V25+実績!V26+実績!V27 -> 263450 | J39: =実績!W23+実績!W24+実績!W25+実績!W26+実績!W27 -> 249595 | ... N39: =実績!AA23+実績!AA24+実績!AA25+実績!AA26+実績!AA27 -> 195150 | O39: =SUM(C39:N39) -> 3111957
A40: 経費計 | C40: =SUM(C32:C39) -> 4316274 | D40: =SUM(D32:D39) -> 5642782 | E40: =SUM(E32:E39) -> 6382183 | F40: =SUM(F32:F39) -> 4725656 | G40: =SUM(G32:G39) -> 4492343 | H40: =SUM(H32:H39) -> 4656907 | I40: =SUM(I32:I39) -> 9661393 | J40: =SUM(J32:J39) -> 5823645 | ... O40: =SUM(O32:O39) -> 87827718
A42: 租税公課は4〜5月に集中する実績パターン(固定資産税等)。実際の納期は納付書でご確認ください。9月の数字には決算整理が含まれます。

Sheet 資金繰り表
A1: 資金繰り表(来期: 令和8年10月〜令和9年9月・月次)
A2: 単位:千円(内部は円)。青字・黄色=手入力欄(土地売却・貸付金回収など臨時項目、初期値0)。経費は支出ベースで減価償却費を除外。
A4: 月 | C4: 46296 | D4: =EDATE(C4,1) -> 46327 | E4: =EDATE(D4,1) -> 46357 | F4: =EDATE(E4,1) -> 46388 | G4: =EDATE(F4,1) -> 46419 | H4: =EDATE(G4,1) -> 46447 | I4: =EDATE(H4,1) -> 46478 | J4: =EDATE(I4,1) -> 46508 | K4: =EDATE(J4,1) -> 46539 | ... N4: =EDATE(M4,1) -> 46631 | O4: 来期計
A5: 決算期 | C5: ="令和"&(YEAR(C4)-2018+IF(MONTH(C4)>=10,1,0))&"年9月期" -> 令和9年9月期 | D5: ="令和"&(YEAR(D4)-2018+IF(MONTH(D4)>=10,1,0))&"年9月期" -> 令和9年9月期 | E5: ="令和"&(YEAR(E4)-2018+IF(MONTH(E4)>=10,1,0))&"年9月期" -> 令和9年9月期 | F5: ="令和"&(YEAR(F4)-2018+IF(MONTH(F4)>=10,1,0))&"年9月期" -> 令和9年9月期 | G5: ="令和"&(YEAR(G4)-2018+IF(MONTH(G4)>=10,1,0))&"年9月期" -> 令和9年9月期 | H5: ="令和"&(YEAR(H4)-2018+IF(MONTH(H4)>=10,1,0))&"年9月期" -> 令和9年9月期 | I5: ="令和"&(YEAR(I4)-2018+IF(MONTH(I4)>=10,1,0))&"年9月期" -> 令和9年9月期 | J5: ="令和"&(YEAR(J4)-2018+IF(MONTH(J4)>=10,1,0))&"年9月期" -> 令和9年9月期 | ... N5: ="令和"&(YEAR(N4)-2018+IF(MONTH(N4)>=10,1,0))&"年9月期" -> 令和9年9月期
A6: 前月繰越現預金(社債なし) | C6: =前提!B5 -> 207939447 | D6: =C29 -> 207423442 | E6: =D29 -> 204098045 | F6: =E29 -> 201516131 | G6: =F29 -> 200590744 | H6: =G29 -> 199898670 | I6: =H29 -> 199042032 | J6: =I29 -> 193180908 | K6: =J29 -> 191157532 | ... N6: =M29 -> 175654381 | O6: =C6 -> 207939447
A7: 【収入】
A8: 賃貸収入(最新の家賃明細) | C8: =前提!$B$6 -> 3800269 | D8: =前提!$B$6 -> 3800269 | E8: =前提!$B$6 -> 3800269 | F8: =前提!$B$6 -> 3800269 | G8: =前提!$B$6 -> 3800269 | H8: =前提!$B$6 -> 3800269 | I8: =前提!$B$6 -> 3800269 | J8: =前提!$B$6 -> 3800269 | ... N8: =前提!$B$6 -> 3800269 | O8: =SUM(C8:N8) -> 45603228
A9: その他売上(手数料等・手入力) | C9: 0 | D9: 0 | E9: 0 | F9: 0 | G9: 0 | H9: 0 | I9: 0 | J9: 0 | K9: 0 | L9: 0 | M9: 0 | N9: 0 | O9: =SUM(C9:N9) -> 0
A10: 土地・商品の売却収入(手入力) | C10: 0 | D10: 0 | E10: 0 | F10: 0 | G10: 0 | H10: 0 | I10: 0 | J10: 0 | K10: 0 | L10: 0 | M10: 0 | N10: 0 | O10: =SUM(C10:N10) -> 0
A11: 貸付金・未収入金の回収(手入力) | C11: 0 | D11: 0 | E11: 0 | F11: 0 | G11: 0 | H11: 0 | I11: 0 | J11: 0 | K11: 0 | L11: 0 | M11: 0 | N11: 0 | O11: =SUM(C11:N11) -> 0
A12: その他臨時収入(手入力) | C12: 0 | D12: 0 | E12: 0 | F12: 0 | G12: 0 | H12: 0 | I12: 0 | J12: 0 | K12: 0 | L12: 0 | M12: 0 | N12: 0 | O12: =SUM(C12:N12) -> 0
A13: 収入計 | C13: =SUM(C8:C12) -> 3800269 | D13: =SUM(D8:D12) -> 3800269 | E13: =SUM(E8:E12) -> 3800269 | F13: =SUM(F8:F12) -> 3800269 | G13: =SUM(G8:G12) -> 3800269 | H13: =SUM(H8:H12) -> 3800269 | I13: =SUM(I8:I12) -> 3800269 | J13: =SUM(J8:J12) -> 3800269 | ... N13: =SUM(N8:N12) -> 3800269 | O13: =SUM(C13:N13) -> 45603228
A14: 【支出】
A15: 役員報酬 | C15: =INDEX(前提!$C$32:$N$32,MOD(MONTH(C$4)-10,12)+1) -> 900000 | D15: =INDEX(前提!$C$32:$N$32,MOD(MONTH(D$4)-10,12)+1) -> 900000 | E15: =INDEX(前提!$C$32:$N$32,MOD(MONTH(E$4)-10,12)+1) -> 900000 | F15: =INDEX(前提!$C$32:$N$32,MOD(MONTH(F$4)-10,12)+1) -> 900000 | G15: =INDEX(前提!$C$32:$N$32,MOD(MONTH(G$4)-10,12)+1) -> 900000 | H15: =INDEX(前提!$C$32:$N$32,MOD(MONTH(H$4)-10,12)+1) -> 900000 | I15: =INDEX(前提!$C$32:$N$32,MOD(MONTH(I$4)-10,12)+1) -> 900000 | J15: =INDEX(前提!$C$32:$N$32,MOD(MONTH(J$4)-10,12)+1) -> 900000 | ... N15: =INDEX(前提!$C$32:$N$32,MOD(MONTH(N$4)-10,12)+1) -> 2400000 | O15: =SUM(C15:N15) -> 12300000
A16: 給与・賞与・福利厚生 | C16: =INDEX(前提!$C$33:$N$33,MOD(MONTH(C$4)-10,12)+1) -> 1218210 | D16: =INDEX(前提!$C$33:$N$33,MOD(MONTH(D$4)-10,12)+1) -> 840557 | E16: =INDEX(前提!$C$33:$N$33,MOD(MONTH(E$4)-10,12)+1) -> 2300348 | F16: =INDEX(前提!$C$33:$N$33,MOD(MONTH(F$4)-10,12)+1) -> 1061189 | G16: =INDEX(前提!$C$33:$N$33,MOD(MONTH(G$4)-10,12)+1) -> 1016578 | H16: =INDEX(前提!$C$33:$N$33,MOD(MONTH(H$4)-10,12)+1) -> 880854 | I16: =INDEX(前提!$C$33:$N$33,MOD(MONTH(I$4)-10,12)+1) -> 815780 | J16: =INDEX(前提!$C$33:$N$33,MOD(MONTH(J$4)-10,12)+1) -> 672558 | ... N16: =INDEX(前提!$C$33:$N$33,MOD(MONTH(N$4)-10,12)+1) -> 1207652 | O16: =SUM(C16:N16) -> 13388958
A17: 保険料 | C17: =INDEX(前提!$C$34:$N$34,MOD(MONTH(C$4)-10,12)+1) -> 892858 | D17: =INDEX(前提!$C$34:$N$34,MOD(MONTH(D$4)-10,12)+1) -> 892858 | E17: =INDEX(前提!$C$34:$N$34,MOD(MONTH(E$4)-10,12)+1) -> 892858 | F17: =INDEX(前提!$C$34:$N$34,MOD(MONTH(F$4)-10,12)+1) -> 892858 | G17: =INDEX(前提!$C$34:$N$34,MOD(MONTH(G$4)-10,12)+1) -> 892858 | H17: =INDEX(前提!$C$34:$N$34,MOD(MONTH(H$4)-10,12)+1) -> 892858 | I17: =INDEX(前提!$C$34:$N$34,MOD(MONTH(I$4)-10,12)+1) -> 892858 | J17: =INDEX(前提!$C$34:$N$34,MOD(MONTH(J$4)-10,12)+1) -> 892858 | ... N17: =INDEX(前提!$C$34:$N$34,MOD(MONTH(N$4)-10,12)+1) -> 10397518 | O17: =SUM(C17:N17) -> 33667055
A18: 租税公課 | C18: =INDEX(前提!$C$35:$N$35,MOD(MONTH(C$4)-10,12)+1) -> 0 | D18: =INDEX(前提!$C$35:$N$35,MOD(MONTH(D$4)-10,12)+1) -> 0 | E18: =INDEX(前提!$C$35:$N$35,MOD(MONTH(E$4)-10,12)+1) -> 0 | F18: =INDEX(前提!$C$35:$N$35,MOD(MONTH(F$4)-10,12)+1) -> 71800 | G18: =INDEX(前提!$C$35:$N$35,MOD(MONTH(G$4)-10,12)+1) -> 195769 | H18: =INDEX(前提!$C$35:$N$35,MOD(MONTH(H$4)-10,12)+1) -> 5326 | I18: =INDEX(前提!$C$35:$N$35,MOD(MONTH(I$4)-10,12)+1) -> 5224100 | J18: =INDEX(前提!$C$35:$N$35,MOD(MONTH(J$4)-10,12)+1) -> 1719800 | ... N18: =INDEX(前提!$C$35:$N$35,MOD(MONTH(N$4)-10,12)+1) -> 600 | O18: =SUM(C18:N18) -> 7291552
A19: 水道光熱・通信交通 | C19: =INDEX(前提!$C$36:$N$36,MOD(MONTH(C$4)-10,12)+1) -> 432715 | D19: =INDEX(前提!$C$36:$N$36,MOD(MONTH(D$4)-10,12)+1) -> 441929 | E19: =INDEX(前提!$C$36:$N$36,MOD(MONTH(E$4)-10,12)+1) -> 521112 | F19: =INDEX(前提!$C$36:$N$36,MOD(MONTH(F$4)-10,12)+1) -> 505753 | G19: =INDEX(前提!$C$36:$N$36,MOD(MONTH(G$4)-10,12)+1) -> 383240 | H19: =INDEX(前提!$C$36:$N$36,MOD(MONTH(H$4)-10,12)+1) -> 494526 | I19: =INDEX(前提!$C$36:$N$36,MOD(MONTH(I$4)-10,12)+1) -> 460352 | J19: =INDEX(前提!$C$36:$N$36,MOD(MONTH(J$4)-10,12)+1) -> 424654 | ... N19: =INDEX(前提!$C$36:$N$36,MOD(MONTH(N$4)-10,12)+1) -> 518550 | O19: =SUM(C19:N19) -> 5855406
A20: 接待交際・諸会費 | C20: =INDEX(前提!$C$37:$N$37,MOD(MONTH(C$4)-10,12)+1) -> 670756 | D20: =INDEX(前提!$C$37:$N$37,MOD(MONTH(D$4)-10,12)+1) -> 2285363 | E20: =INDEX(前提!$C$37:$N$37,MOD(MONTH(E$4)-10,12)+1) -> 1476545 | F20: =INDEX(前提!$C$37:$N$37,MOD(MONTH(F$4)-10,12)+1) -> 680669 | G20: =INDEX(前提!$C$37:$N$37,MOD(MONTH(G$4)-10,12)+1) -> 664213 | H20: =INDEX(前提!$C$37:$N$37,MOD(MONTH(H$4)-10,12)+1) -> 1203941 | I20: =INDEX(前提!$C$37:$N$37,MOD(MONTH(I$4)-10,12)+1) -> 788903 | J20: =INDEX(前提!$C$37:$N$37,MOD(MONTH(J$4)-10,12)+1) -> 935455 | ... N20: =INDEX(前提!$C$37:$N$37,MOD(MONTH(N$4)-10,12)+1) -> 247264 | O20: =SUM(C20:N20) -> 10951858
A21: 修繕・消耗品 | C21: =INDEX(前提!$C$38:$N$38,MOD(MONTH(C$4)-10,12)+1) -> 73685 | D21: =INDEX(前提!$C$38:$N$38,MOD(MONTH(D$4)-10,12)+1) -> 22043 | E21: =INDEX(前提!$C$38:$N$38,MOD(MONTH(E$4)-10,12)+1) -> 30011 | F21: =INDEX(前提!$C$38:$N$38,MOD(MONTH(F$4)-10,12)+1) -> 76544 | G21: =INDEX(前提!$C$38:$N$38,MOD(MONTH(G$4)-10,12)+1) -> 122157 | H21: =INDEX(前提!$C$38:$N$38,MOD(MONTH(H$4)-10,12)+1) -> 67497 | I21: =INDEX(前提!$C$38:$N$38,MOD(MONTH(I$4)-10,12)+1) -> 315950 | J21: =INDEX(前提!$C$38:$N$38,MOD(MONTH(J$4)-10,12)+1) -> 28725 | ... N21: =INDEX(前提!$C$38:$N$38,MOD(MONTH(N$4)-10,12)+1) -> 255843 | O21: =SUM(C21:N21) -> 1260932
A22: 管理諸費・雑費・その他 | C22: =INDEX(前提!$C$39:$N$39,MOD(MONTH(C$4)-10,12)+1) -> 128050 | D22: =INDEX(前提!$C$39:$N$39,MOD(MONTH(D$4)-10,12)+1) -> 260032 | E22: =INDEX(前提!$C$39:$N$39,MOD(MONTH(E$4)-10,12)+1) -> 261309 | F22: =INDEX(前提!$C$39:$N$39,MOD(MONTH(F$4)-10,12)+1) -> 536843 | G22: =INDEX(前提!$C$39:$N$39,MOD(MONTH(G$4)-10,12)+1) -> 317528 | H22: =INDEX(前提!$C$39:$N$39,MOD(MONTH(H$4)-10,12)+1) -> 211905 | I22: =INDEX(前提!$C$39:$N$39,MOD(MONTH(I$4)-10,12)+1) -> 263450 | J22: =INDEX(前提!$C$39:$N$39,MOD(MONTH(J$4)-10,12)+1) -> 249595 | ... N22: =INDEX(前提!$C$39:$N$39,MOD(MONTH(N$4)-10,12)+1) -> 195150 | O22: =SUM(C22:N22) -> 3111957
A23: 消費税納付(令和8年9月期分) | C23: =IF(MONTH(C$4)=前提!$B$13,前提!$B$14,0) -> 0 | D23: =IF(MONTH(D$4)=前提!$B$13,前提!$B$14,0) -> 1482884 | E23: =IF(MONTH(E$4)=前提!$B$13,前提!$B$14,0) -> 0 | F23: =IF(MONTH(F$4)=前提!$B$13,前提!$B$14,0) -> 0 | G23: =IF(MONTH(G$4)=前提!$B$13,前提!$B$14,0) -> 0 | H23: =IF(MONTH(H$4)=前提!$B$13,前提!$B$14,0) -> 0 | I23: =IF(MONTH(I$4)=前提!$B$13,前提!$B$14,0) -> 0 | J23: =IF(MONTH(J$4)=前提!$B$13,前提!$B$14,0) -> 0 | ... N23: =IF(MONTH(N$4)=前提!$B$13,前提!$B$14,0) -> 0 | O23: =SUM(C23:N23) -> 1482884
A24: 長期未払金の支払(手入力・4,691万円の期日未確認) | C24: 0 | D24: 0 | E24: 0 | F24: 0 | G24: 0 | H24: 0 | I24: 0 | J24: 0 | K24: 0 | L24: 0 | M24: 0 | N24: 0 | O24: =SUM(C24:N24) -> 0
A25: その他臨時支出(手入力) | C25: 0 | D25: 0 | E25: 0 | F25: 0 | G25: 0 | H25: 0 | I25: 0 | J25: 0 | K25: 0 | L25: 0 | M25: 0 | N25: 0 | O25: =SUM(C25:N25) -> 0
A26: 支出計 | C26: =SUM(C15:C25) -> 4316274 | D26: =SUM(D15:D25) -> 7125666 | E26: =SUM(E15:E25) -> 6382183 | F26: =SUM(F15:F25) -> 4725656 | G26: =SUM(G15:G25) -> 4492343 | H26: =SUM(H15:H25) -> 4656907 | I26: =SUM(I15:I25) -> 9661393 | J26: =SUM(J15:J25) -> 5823645 | ... N26: =SUM(N15:N25) -> 15222577 | O26: =SUM(C26:N26) -> 89310602
A27: 収支差額(社債なし) | C27: =C13-C26 -> -516005 | D27: =D13-D26 -> -3325397 | E27: =E13-E26 -> -2581914 | F27: =F13-F26 -> -925387 | G27: =G13-G26 -> -692074 | H27: =H13-H26 -> -856638 | I27: =I13-I26 -> -5861124 | J27: =J13-J26 -> -2023376 | ... N27: =N13-N26 -> -11422308 | O27: =SUM(C27:N27) -> -43707374
A29: 翌月繰越現預金(社債なし) ① | C29: =C6+C27 -> 207423442 | D29: =D6+D27 -> 204098045 | E29: =E6+E27 -> 201516131 | F29: =F6+F27 -> 200590744 | G29: =G6+G27 -> 199898670 | H29: =H6+H27 -> 199042032 | I29: =I6+I27 -> 193180908 | J29: =J6+J27 -> 191157532 | ... N29: =N6+N27 -> 164232073 | O29: =N29 -> 164232073
A31: 【社債(25万USD・3年)を購入した場合の追加キャッシュフロー】
A32: 社債購入代金 | C32: =IF(((YEAR(C$4)*12+MONTH(C$4))-(YEAR(前提!$B$20)*12+MONTH(前提!$B$20)))=0,-前提!$B$27,0) -> 0 | D32: =IF(((YEAR(D$4)*12+MONTH(D$4))-(YEAR(前提!$B$20)*12+MONTH(前提!$B$20)))=0,-前提!$B$27,0) -> -39625000 | E32: =IF(((YEAR(E$4)*12+MONTH(E$4))-(YEAR(前提!$B$20)*12+MONTH(前提!$B$20)))=0,-前提!$B$27,0) -> 0 | F32: =IF(((YEAR(F$4)*12+MONTH(F$4))-(YEAR(前提!$B$20)*12+MONTH(前提!$B$20)))=0,-前提!$B$27,0) -> 0 | G32: =IF(((YEAR(G$4)*12+MONTH(G$4))-(YEAR(前提!$B$20)*12+MONTH(前提!$B$20)))=0,-前提!$B$27,0) -> 0 | H32: =IF(((YEAR(H$4)*12+MONTH(H$4))-(YEAR(前提!$B$20)*12+MONTH(前提!$B$20)))=0,-前提!$B$27,0) -> 0 | I32: =IF(((YEAR(I$4)*12+MONTH(I$4))-(YEAR(前提!$B$20)*12+MONTH(前提!$B$20)))=0,-前提!$B$27,0) -> 0 | J32: =IF(((YEAR(J$4)*12+MONTH(J$4))-(YEAR(前提!$B$20)*12+MONTH(前提!$B$20)))=0,-前提!$B$27,0) -> 0 | ... N32: =IF(((YEAR(N$4)*12+MONTH(N$4))-(YEAR(前提!$B$20)*12+MONTH(前提!$B$20)))=0,-前提!$B$27,0) -> 0 | O32: =SUM(C32:N32) -> -39625000
A33: 社債利息(源泉税引後) | C33: =IF(AND(((YEAR(C$4)*12+MONTH(C$4))-(YEAR(前提!$B$20)*12+MONTH(前提!$B$20)))>0,((YEAR(C$4)*12+MONTH(C$4))-(YEAR(前提!$B$20)*12+MONTH(前提!$B$20)))<=前提!$B$24,MOD(((YEAR(C$4)*12+MONTH(C$4))-(YEAR(前提!$B$20)*12+MONTH(前提!$B$20))),12/前提!$B$22)=0),前提!$B$17*前提!$B$21/前提!$B$22*前提!$B$25*(1-前提!$B$23),0) -> 0 | D33: =IF(AND(((YEAR(D$4)*12+MONTH(D$4))-(YEAR(前提!$B$20)*12+MONTH(前提!$B$20)))>0,((YEAR(D$4)*12+MONTH(D$4))-(YEAR(前提!$B$20)*12+MONTH(前提!$B$20)))<=前提!$B$24,MOD(((YEAR(D$4)*12+MONTH(D$4))-(YEAR(前提!$B$20)*12+MONTH(前提!$B$20))),12/前提!$B$22)=0),前提!$B$17*前提!$B$21/前提!$B$22*前提!$B$25*(1-前提!$B$23),0) -> 0 | E33: =IF(AND(((YEAR(E$4)*12+MONTH(E$4))-(YEAR(前提!$B$20)*12+MONTH(前提!$B$20)))>0,((YEAR(E$4)*12+MONTH(E$4))-(YEAR(前提!$B$20)*12+MONTH(前提!$B$20)))<=前提!$B$24,MOD(((YEAR(E$4)*12+MONTH(E$4))-(YEAR(前提!$B$20)*12+MONTH(前提!$B$20))),12/前提!$B$22)=0),前提!$B$17*前提!$B$21/前提!$B$22*前提!$B$25*(1-前提!$B$23),0) -> 0 | F33: =IF(AND(((YEAR(F$4)*12+MONTH(F$4))-(YEAR(前提!$B$20)*12+MONTH(前提!$B$20)))>0,((YEAR(F$4)*12+MONTH(F$4))-(YEAR(前提!$B$20)*12+MONTH(前提!$B$20)))<=前提!$B$24,MOD(((YEAR(F$4)*12+MONTH(F$4))-(YEAR(前提!$B$20)*12+MONTH(前提!$B$20))),12/前提!$B$22)=0),前提!$B$17*前提!$B$21/前提!$B$22*前提!$B$25*(1-前提!$B$23),0) -> 0 | G33: =IF(AND(((YEAR(G$4)*12+MONTH(G$4))-(YEAR(前提!$B$20)*12+MONTH(前提!$B$20)))>0,((YEAR(G$4)*12+MONTH(G$4))-(YEAR(前提!$B$20)*12+MONTH(前提!$B$20)))<=前提!$B$24,MOD(((YEAR(G$4)*12+MONTH(G$4))-(YEAR(前提!$B$20)*12+MONTH(前提!$B$20))),12/前提!$B$22)=0),前提!$B$17*前提!$B$21/前提!$B$22*前提!$B$25*(1-前提!$B$23),0) -> 0 | H33: =IF(AND(((YEAR(H$4)*12+MONTH(H$4))-(YEAR(前提!$B$20)*12+MONTH(前提!$B$20)))>0,((YEAR(H$4)*12+MONTH(H$4))-(YEAR(前提!$B$20)*12+MONTH(前提!$B$20)))<=前提!$B$24,MOD(((YEAR(H$4)*12+MONTH(H$4))-(YEAR(前提!$B$20)*12+MONTH(前提!$B$20))),12/前提!$B$22)=0),前提!$B$17*前提!$B$21/前提!$B$22*前提!$B$25*(1-前提!$B$23),0) -> 0 | I33: =IF(AND(((YEAR(I$4)*12+MONTH(I$4))-(YEAR(前提!$B$20)*12+MONTH(前提!$B$20)))>0,((YEAR(I$4)*12+MONTH(I$4))-(YEAR(前提!$B$20)*12+MONTH(前提!$B$20)))<=前提!$B$24,MOD(((YEAR(I$4)*12+MONTH(I$4))-(YEAR(前提!$B$20)*12+MONTH(前提!$B$20))),12/前提!$B$22)=0),前提!$B$17*前提!$B$21/前提!$B$22*前提!$B$25*(1-前提!$B$23),0) -> 0 | J33: =IF(AND(((YEAR(J$4)*12+MONTH(J$4))-(YEAR(前提!$B$20)*12+MONTH(前提!$B$20)))>0,((YEAR(J$4)*12+MONTH(J$4))-(YEAR(前提!$B$20)*12+MONTH(前提!$B$20)))<=前提!$B$24,MOD(((YEAR(J$4)*12+MONTH(J$4))-(YEAR(前提!$B$20)*12+MONTH(前提!$B$20))),12/前提!$B$22)=0),前提!$B$17*前提!$B$21/前提!$B$22*前提!$B$25*(1-前提!$B$23),0) -> 1170770.1 | ... N33: =IF(AND(((YEAR(N$4)*12+MONTH(N$4))-(YEAR(前提!$B$20)*12+MONTH(前提!$B$20)))>0,((YEAR(N$4)*12+MONTH(N$4))-(YEAR(前提!$B$20)*12+MONTH(前提!$B$20)))<=前提!$B$24,MOD(((YEAR(N$4)*12+MONTH(N$4))-(YEAR(前提!$B$20)*12+MONTH(前提!$B$20))),12/前提!$B$22)=0),前提!$B$17*前提!$B$21/前提!$B$22*前提!$B$25*(1-前提!$B$23),0) -> 0 | O33: =SUM(C33:N33) -> 1170770.1
A34: 社債償還金(令和11年11月のため対象期間外) | C34: =IF(((YEAR(C$4)*12+MONTH(C$4))-(YEAR(前提!$B$20)*12+MONTH(前提!$B$20)))=前提!$B$24,前提!$B$17*前提!$B$26,0) -> 0 | D34: =IF(((YEAR(D$4)*12+MONTH(D$4))-(YEAR(前提!$B$20)*12+MONTH(前提!$B$20)))=前提!$B$24,前提!$B$17*前提!$B$26,0) -> 0 | E34: =IF(((YEAR(E$4)*12+MONTH(E$4))-(YEAR(前提!$B$20)*12+MONTH(前提!$B$20)))=前提!$B$24,前提!$B$17*前提!$B$26,0) -> 0 | F34: =IF(((YEAR(F$4)*12+MONTH(F$4))-(YEAR(前提!$B$20)*12+MONTH(前提!$B$20)))=前提!$B$24,前提!$B$17*前提!$B$26,0) -> 0 | G34: =IF(((YEAR(G$4)*12+MONTH(G$4))-(YEAR(前提!$B$20)*12+MONTH(前提!$B$20)))=前提!$B$24,前提!$B$17*前提!$B$26,0) -> 0 | H34: =IF(((YEAR(H$4)*12+MONTH(H$4))-(YEAR(前提!$B$20)*12+MONTH(前提!$B$20)))=前提!$B$24,前提!$B$17*前提!$B$26,0) -> 0 | I34: =IF(((YEAR(I$4)*12+MONTH(I$4))-(YEAR(前提!$B$20)*12+MONTH(前提!$B$20)))=前提!$B$24,前提!$B$17*前提!$B$26,0) -> 0 | J34: =IF(((YEAR(J$4)*12+MONTH(J$4))-(YEAR(前提!$B$20)*12+MONTH(前提!$B$20)))=前提!$B$24,前提!$B$17*前提!$B$26,0) -> 0 | ... N34: =IF(((YEAR(N$4)*12+MONTH(N$4))-(YEAR(前提!$B$20)*12+MONTH(前提!$B$20)))=前提!$B$24,前提!$B$17*前提!$B$26,0) -> 0 | O34: =SUM(C34:N34) -> 0
A35: 社債によるキャッシュ増減 | C35: =SUM(C32:C34) -> 0 | D35: =SUM(D32:D34) -> -39625000 | E35: =SUM(E32:E34) -> 0 | F35: =SUM(F32:F34) -> 0 | G35: =SUM(G32:G34) -> 0 | H35: =SUM(H32:H34) -> 0 | I35: =SUM(I32:I34) -> 0 | J35: =SUM(J32:J34) -> 1170770.1 | ... N35: =SUM(N32:N34) -> 0 | O35: =SUM(C35:N35) -> -38454230
A36: 社債の累計キャッシュ増減 | C36: =C35 -> 0 | D36: =C36+D35 -> -39625000 | E36: =D36+E35 -> -39625000 | F36: =E36+F35 -> -39625000 | G36: =F36+G35 -> -39625000 | H36: =G36+H35 -> -39625000 | I36: =H36+I35 -> -39625000 | J36: =I36+J35 -> -38454230 | K36: =J36+K35 -> -38454230 | ... N36: =M36+N35 -> -38454230 | O36: =N36 -> -38454230
A37: 翌月繰越現預金(社債あり) ② | C37: =C29+C36 -> 207423442 | D37: =D29+D36 -> 164473045 | E37: =E29+E36 -> 161891131 | F37: =F29+F36 -> 160965744 | G37: =G29+G36 -> 160273670 | H37: =H29+H36 -> 159417032 | I37: =I29+I36 -> 153555908 | J37: =J29+J36 -> 1.527033e+08 | ... N37: =N29+N36 -> 1.2577784e+08 | O37: =N37 -> 1.2577784e+08
A38: 差額(②−①) | C38: =C37-C29 -> 0 | D38: =D37-D29 -> -39625000 | E38: =E37-E29 -> -39625000 | F38: =F37-F29 -> -39625000 | G38: =G37-G29 -> -39625000 | H38: =H37-H29 -> -39625000 | I38: =I37-I29 -> -39625000 | J38: =J37-J29 -> -38454230 | ... O38: =O37-O29 -> -38454230
A40: ※社債は購入月に代金を全額支出、利息は源泉税15.315%控除後で入金する前提(来期は5月の1回分のみ。11月分は来々期)。源泉税は欠損のため法人税申告で還付(決算後)となり、この表には含めていません。
A41: ※経費は令和8年9月期の月次実績を同月に当てはめ、保険料は保険一覧の現金支払で置換。土地売却・貸付金回収は黄色欄に入力すると反映されます。

Sheet 経費内訳
A1: 経費の内訳(令和8年9月期実績と過去2期の比較)
A2: 出典: 残高推移表(各期9月末の累計=10月〜9月の1年間)。金額は円。令和8年9月期は実績シートから参照。
A4: 科目 | B4: 令和6年9月期 | C4: 令和7年9月期 | D4: 令和8年9月期 | E4: 前期比(R8−R7) | F4: 前期比率 | G4: 構成比(R8・減価償却除く) | H4: コメント
A5: 保険料 | B5: 16714334 | C5: 24221849 | D5: =実績!N14 -> 24617595 | E5: =D5-C5 -> 395746 | F5: =IF(C5=0,"-",E5/C5) -> 0.016338389 | G5: =D5/D$24 -> 0.31249225 | H5: 最大の経費(約3割)。損金計上額ベース。現金の支払は旭土地の保険一覧で年間約3,367万円(損金にならない約1,298万円は前払費用に計上され、令和8年9月期に前払費用が約840万円増加)
A6: 役員報酬 | B6: 10800000 | C6: 12300000 | D6: =実績!N9 -> 12300000 | E6: =D6-C6 -> 0 | F6: =IF(C6=0,"-",E6/C6) -> 0 | G6: =D6/D$24 -> 0.15613445 | H6: 月90万円+決算月(9月)に150万円の上乗せ(前期同額)
A7: 接待交際費 | B7: 8183403 | C7: 8183556 | D7: =実績!N18 -> 9044839 | E7: =D7-C7 -> 861283 | F7: =IF(C7=0,"-",E7/C7) -> 0.10524557 | G7: =D7/D$24 -> 0.1148139 | H7: 前期比+86万円
A8: 租税公課 | B8: 8471002 | C8: 7581824 | D8: =実績!N15 -> 7291552 | E8: =D8-C8 -> -290272 | F8: =IF(C8=0,"-",E8/C8) -> -0.038285246 | G8: =D8/D$24 -> 0.092557924 | H8: 4〜5月に集中(固定資産税等)
A9: 事務員給与 | B9: 6136056 | C9: 7872787 | D9: =実績!N10 -> 6215372 | E9: =D9-C9 -> -1657415 | F9: =IF(C9=0,"-",E9/C9) -> -0.21052456 | G9: =D9/D$24 -> 0.078897048 | H9: 前期は5〜6月に臨時の増加があり今期は減少
A10: 厚生費 | B10: 3373131 | C10: 3816552 | D10: =実績!N13 -> 4820303 | E10: =D10-C10 -> 1003751 | F10: =IF(C10=0,"-",E10/C10) -> 0.26299943 | G10: =D10/D$24 -> 0.061188241 | H10: 前期比+100万円(+26%)
A11: 通信交通費 | B11: 3218205 | C11: 3555319 | D11: =実績!N17 -> 3566993 | E11: =D11-C11 -> 11674 | F11: =IF(C11=0,"-",E11/C11) -> 0.003283531 | G11: =D11/D$24 -> 0.045278902
A12: 水道光熱費 | B12: 2176488 | C12: 2249822 | D12: =実績!N16 -> 2288413 | E12: =D12-C12 -> 38591 | F12: =IF(C12=0,"-",E12/C12) -> 0.017152913 | G12: =D12/D$24 -> 0.029048789
A13: 諸会費 | B13: 2081082 | C13: 1627291 | D13: =実績!N19 -> 1907019 | E13: =D13-C13 -> 279728 | F13: =IF(C13=0,"-",E13/C13) -> 0.17189796 | G13: =D13/D$24 -> 0.024207428
A14: 法定福利費 | B14: 381113 | C14: 1607693 | D14: =実績!N12 -> 1703283 | E14: =D14-C14 -> 95590 | F14: =IF(C14=0,"-",E14/C14) -> 0.059457869 | G14: =D14/D$24 -> 0.021621232
A15: 管理諸費 | B15: 2298300 | C15: 2638934 | D15: =実績!N23 -> 1722251 | E15: =D15-C15 -> -916683 | F15: =IF(C15=0,"-",E15/C15) -> -0.34736867 | G15: =D15/D$24 -> 0.021862009 | H15: 前期7月に113万円の臨時計上があり今期は減少
A16: 雑費 | B16: 1431588 | C16: 1409060 | D16: =実績!N24 -> 1321156 | E16: =D16-C16 -> -87904 | F16: =IF(C16=0,"-",E16/C16) -> -0.062384852 | G16: =D16/D$24 -> 0.016770566
A17: 従業員賞与 | B17: 1468482 | C17: 650000 | D17: =実績!N11 -> 650000 | E17: =D17-C17 -> 0 | F17: =IF(C17=0,"-",E17/C17) -> 0 | G17: =D17/D$24 -> 0.0082510075
A18: 備品消耗品費 | B18: 310807 | C18: 343045 | D18: =実績!N22 -> 629407 | E18: =D18-C18 -> 286362 | F18: =IF(C18=0,"-",E18/C18) -> 0.83476512 | G18: =D18/D$24 -> 0.0079896029 | H18: 8〜9月に増加(前期比+83%)
A19: 修繕費 | B19: 168747 | C19: 754212 | D19: =実績!N20 -> 413029 | E19: =D19-C19 -> -341183 | F19: =IF(C19=0,"-",E19/C19) -> -0.45237016 | G19: =D19/D$24 -> 0.0052429314
A20: 事務用消耗品費 | B20: 317537 | C20: 84896 | D20: =実績!N21 -> 218496 | E20: =D20-C20 -> 133600 | F20: =IF(C20=0,"-",E20/C20) -> 1.5736902 | G20: =D20/D$24 -> 0.0027735571
A21: 広告宣伝費 | B21: 300000 | C21: 154500 | D21: =実績!N25 -> 38250 | E21: =D21-C21 -> -116250 | F21: =IF(C21=0,"-",E21/C21) -> -0.75242718 | G21: =D21/D$24 -> 0.00048554006
A22: 新聞図書費 | B22: 142616 | C22: 1000 | D22: =実績!N26 -> 20300 | E22: =D22-C22 -> 19300 | F22: =IF(C22=0,"-",E22/C22) -> 19.3 | G22: =D22/D$24 -> 0.00025768531
A23: 寄付金 | B23: 20000 | C23: 30000 | D23: =実績!N27 -> 10000 | E23: =D23-C23 -> -20000 | F23: =IF(C23=0,"-",E23/C23) -> -0.66666667 | G23: =D23/D$24 -> 0.00012693858
A24: 経費計(減価償却費を除く) | B24: =SUM(B5:B23) -> 67992891 | C24: =SUM(C5:C23) -> 79082340 | D24: =SUM(D5:D23) -> 78778258 | E24: =SUM(E5:E23) -> -304082 | F24: =E24/C24 -> -0.0038451315 | G24: =SUM(G5:G23) -> 1
A25: 月平均(令和8年9月期) | D25: =D24/12 -> 6564854.8
A26: 減価償却費(非資金・参考) | B26: 1926812 | C26: 2057517 | D26: =実績!N28 -> 1668000
A28: 来期(令和9年9月期)の見積り(グループ別・資金繰り表の現金ベース)
A29: グループ | B29: 令和8年9月期 実績(会計) | C29: 来期 見込(現金) | D29: 増減 | E29: 備考
A30: 役員報酬 | B30: =D6 -> 12300000 | C30: =資金繰り表!O15 -> 12300000 | D30: =C30-B30 -> 0 | E30: 令和8年9月期の月次実績を同月に当てはめ
A31: 給与・賞与・福利厚生 | B31: =D9+D17+D14+D10 -> 13388958 | C31: =資金繰り表!O16 -> 13388958 | D31: =C31-B31 -> 0 | E31: 令和8年9月期の月次実績を同月に当てはめ
A32: 保険料 | B32: =D5 -> 24617595 | C32: =資金繰り表!O17 -> 33667055 | D32: =C32-B32 -> 9049460 | E32: 保険一覧の現金支払(切替B9)。会計上の保険料との差は前払費用
A33: 租税公課 | B33: =D8 -> 7291552 | C33: =資金繰り表!O18 -> 7291552 | D33: =C33-B33 -> 0 | E33: 令和8年9月期の月次実績を同月に当てはめ
A34: 水道光熱・通信交通 | B34: =D12+D11 -> 5855406 | C34: =資金繰り表!O19 -> 5855406 | D34: =C34-B34 -> 0 | E34: 令和8年9月期の月次実績を同月に当てはめ
A35: 接待交際・諸会費 | B35: =D7+D13 -> 10951858 | C35: =資金繰り表!O20 -> 10951858 | D35: =C35-B35 -> 0 | E35: 令和8年9月期の月次実績を同月に当てはめ
A36: 修繕・消耗品 | B36: =D19+D20+D18 -> 1260932 | C36: =資金繰り表!O21 -> 1260932 | D36: =C36-B36 -> 0 | E36: 令和8年9月期の月次実績を同月に当てはめ
A37: 管理諸費・雑費・その他 | B37: =D15+D16+D21+D22+D23 -> 3111957 | C37: =資金繰り表!O22 -> 3111957 | D37: =C37-B37 -> 0 | E37: 令和8年9月期の月次実績を同月に当てはめ
A38: 合計 | B38: =SUM(B30:B37) -> 78778258 | C38: =SUM(C30:C37) -> 87827718 | D38: =SUM(D30:D37) -> 9049460
A39: ※令和8年9月期の会計上の経費と来期の現金見込の差は、ほぼ保険料(損金にならない部分の現金支払)によるものです。

Sheet 家賃明細
A1: 賃貸収入明細 (株)旭土地建物(令和8年10月15日付・月額)
A2: 出典: アップロードされた「賃貸収入・支出明細」シート R8.10.15。コインパーキングは令和7年1〜12月の月平均。青字=転記値。
A4: 借主 | B4: 月額家賃(円) | C4: 備考
A5: みずほ銀行 | B5: 212190
A6: ジェントルマン | B6: 165000
A7: XYZ | B7: 159814
A8: 坂本不動産 | B8: 81650 | C8: グループ会社からの家賃
A9: カナコン | B9: 427776
A10: ファミリー歯科 | B10: 203703
A11: 緑園カレージ(10) | B11: 440000
A12: 善部 | B12: 16500
A13: 南万騎が原コインパーキング | B13: 464970 | C13: R7.1〜12平均
A14: 厚木コインパーキング | B14: 628666 | C14: R7.1〜12平均
A15: サカモト(横浜西口) | B15: 1000000 | C15: グループ会社からの家賃
A17: 月額合計 | B17: =SUM(B5:B15) -> 3800269
A18: 元ファイルの合計(検算) | B18: 3800269 | C18: =IF(B17=B18,"一致","差異あり") -> 一致
A19: 家賃支出(元ファイル) | B19: 0 | C19: 旭土地建物の「家賃支出」欄は0
A21: 参考: 令和8年9月期の賃貸売上(会計)の月平均 | B21: =実績!N6/12 -> 4043200.8
A22: 最新明細との差 | B22: =B17-B21 -> -242931.75
A23: ※会計の賃貸売上は月ごとに2.7〜6.1百万円とばらつきがあります(実績シート参照)。来期は最新明細の月額を毎月一定として見積もっています。

Sheet 保険一覧
A1: 旭土地建物 保険契約一覧(令和8年6月10日現在)
A2: 出典: アップロードされた保険一覧ファイル「旭土地 2026.6.10」シート。青字=転記値、黒字=計算。保険料は月払=月額、年払=年額。返戻金は万円。
A4: 番号 | B4: 保険会社 | C4: 契約番号 | D4: 加入日 | E4: 契約者 | F4: 保険種類 | G4: 損金割合 | H4: 被保険者 | I4: 保険期間 | J4: 払込方法 | K4: 保険料(円) 月払=月額/年払=年額 | L4: 年間保険料(円) | M4: 年間損金計上額(円) | N4: 保険金 | O4: 返戻金(R8年・万円) | P4: 返戻率(R8年) | Q4: 意向 | R4: 年払の支払月 (加入日の月) | S4: 支払停止年月 (入力で反映) | T4: 備考
A5: 1 | B5: 大同生命 | C5: 679-166564-0 | D5: 44765 | E5: 旭土地 | F5: 全額損金 | G5: 0 | H5: 岡田 優子 | I5: 90歳まで | J5: 払済 | K5: 0 | L5: =IF(J5="月払",K5*12,IF(J5="年払",K5,0)) -> 0 | M5: =L5*G5 -> 0 | N5: 331万円 | O5: 165 | P5: 0.432 | Q5: 随時解約検討 | R5: =IF(J5="年払",MONTH(D5),"")
A6: 2 | B6: 大同生命 | C6: 697-166566-0 | D6: 44765 | E6: 旭土地 | F6: 全額損金 | G6: 0 | H6: 岡田 淳 | I6: 90歳まで | J6: 払済 | K6: 0 | L6: =IF(J6="月払",K6*12,IF(J6="年払",K6,0)) -> 0 | M6: =L6*G6 -> 0 | N6: 388万円 | O6: 266 | P6: 0.458 | Q6: 随時解約検討 | R6: =IF(J6="年払",MONTH(D6),"")
A7: 3 | B7: 大同生命 | C7: 636-016316-0 | D7: 44765 | E7: 旭土地 | F7: 全額損金 | G7: 0 | H7: Ｊ 岡田 優子 | I7: 90歳まで | J7: 払済 | K7: 0 | L7: =IF(J7="月払",K7*12,IF(J7="年払",K7,0)) -> 0 | M7: =L7*G7 -> 0 | N7: 638万円 | O7: 433 | P7: 0.528 | Q7: 2027年度払済？ | R7: =IF(J7="年払",MONTH(D7),"")
A8: 4 | B8: 大同生命 | C8: 656-028099-0 | D8: 44765 | E8: 旭土地 | F8: 全額損金 | G8: 0 | H8: Ｔ 岡田 優子 | I8: 90歳まで | J8: 払済 | K8: 0 | L8: =IF(J8="月払",K8*12,IF(J8="年払",K8,0)) -> 0 | M8: =L8*G8 -> 0 | N8: 622万円 | O8: 241 | P8: 0.449 | Q8: 2030年度払済？ | R8: =IF(J8="年払",MONTH(D8),"")
A9: 5 | B9: 大同生命 | C9: 086-376628-0 | D9: 44166 | E9: 旭土地 | F9: 全損 | G9: 1 | H9: 坂本 武 | I9: 終身 | J9: 月払 | K9: 22820 | L9: =IF(J9="月払",K9*12,IF(J9="年払",K9,0)) -> 273840 | M9: =L9*G9 -> 273840 | N9: 入院 10,000円 | Q9: 保有 | R9: =IF(J9="年払",MONTH(D9),"") | T9: 医療保険(入院日額1万円)。元表の損金計上合計に未算入
A10: 6 | B10: 大同生命 | C10: 636-010531-0 | D10: 44348 | E10: 旭土地 | F10: 全額損金 | G10: 1 | H10: 横山 清美 | I10: Ｊ 90歳まで | J10: 月払 | K10: 49130 | L10: =IF(J10="月払",K10*12,IF(J10="年払",K10,0)) -> 589560 | M10: =L10*G10 -> 589560 | N10: 1,500万円 | O10: 131 | P10: 0.4 | Q10: 保有 | R10: =IF(J10="年払",MONTH(D10),"")
A11: 7 | B11: 大同生命 | C11: 697-074568-0 | D11: 44166 | E11: 旭土地 | F11: 6割損金 | G11: 0.6 | H11: 坂本 武 | I11: 総Ｌ 100歳まで | J11: 月払 | K11: 505120 | L11: =IF(J11="月払",K11*12,IF(J11="年払",K11,0)) -> 6061440 | M11: =L11*G11 -> 3636864 | N11: 10,000万円 | O11: 2247 | P11: 0.688 | Q11: 2027年度払済？ | R11: =IF(J11="年払",MONTH(D11),"")
A12: 8 | B12: 大同生命 | C12: 697-129724-0 | D12: 44531 | E12: 旭土地 | F12: 6割損金 | G12: 0.6 | H12: 横山 清美 | I12: 90歳まで | J12: 月払 | K12: 57687 | L12: =IF(J12="月払",K12*12,IF(J12="年払",K12,0)) -> 692244 | M12: =L12*G12 -> 415346.4 | N12: 3,000万円 | O12: 196 | P12: 0.688 | Q12: 保有 | R12: =IF(J12="年払",MONTH(D12),"")
A13: 9 | B13: 大同生命 | C13: 636-013356-0 | D13: 44531 | E13: 旭土地 | F13: 6割損金 | G13: 0.6 | H13: 坂本 麻莉 | I13: Ｊ 90歳まで | J13: 月払 | K13: 179573 | L13: =IF(J13="月払",K13*12,IF(J13="年払",K13,0)) -> 2154876 | M13: =L13*G13 -> 1292925.6 | N13: 10,000万円 | O13: 654 | P13: 0.675 | Q13: 2027年度払済？ | R13: =IF(J13="年払",MONTH(D13),"")
A14: 10 | B14: 大同生命 | C14: 697-131400-0 | D14: 44531 | E14: 旭土地 | F14: 6割損金 | G14: 0.6 | H14: 坂本 麻莉 | I14: 総Ｌ 90歳まで | J14: 月払 | K14: 49628 | L14: =IF(J14="月払",K14*12,IF(J14="年払",K14,0)) -> 595536 | M14: =L14*G14 -> 357321.6 | N14: 6,000万円 | O14: 456 | P14: 0.646 | Q14: 保有 | R14: =IF(J14="年払",MONTH(D14),"")
A15: 11 | B15: 大同生命 | C15: 697-159957-0 | D15: 44733 | E15: 旭土地 | F15: 全額損金 | G15: 1 | H15: 坂本 武 | I15: 90歳まで | J15: 年払 | K15: 5698547 | L15: =IF(J15="月払",K15*12,IF(J15="年払",K15,0)) -> 5698547 | M15: =L15*G15 -> 5698547 | N15: 10,000万円 | O15: 1138 | P15: 0.5 | Q15: 2026年度払済？ | R15: =IF(J15="年払",MONTH(D15),"") -> 6
A16: 12 | B16: 大同生命 | C16: 656-028100-0 | D16: 44765 | E16: 旭土地 | F16: 全額損金 | G16: 1 | H16: Ｔ 岡田 淳 | I16: 90歳まで | J16: 年払 | K16: 1707660 | L16: =IF(J16="月払",K16*12,IF(J16="年払",K16,0)) -> 1707660 | M16: =L16*G16 -> 1707660 | N16: 15,000万円 | O16: 309 | P16: 0.464 | Q16: 2030年度払済？ | R16: =IF(J16="年払",MONTH(D16),"") -> 7
A17: 13 | B17: 日本生命 | D17: 44739 | E17: 旭土地 | F17: 4割損金 | G17: 0.4 | H17: 坂本 信 | I17: 97歳まで | J17: 年払 | K17: 3027080 | L17: =IF(J17="月払",K17*12,IF(J17="年払",K17,0)) -> 3027080 | M17: =L17*G17 -> 1210832 | N17: 14,000万円 | O17: 1250 | P17: 0.826 | Q17: 保有 | R17: =IF(J17="年払",MONTH(D17),"") -> 6 | T17: 元表の記載: 横浜
A18: 14 | B18: 日本生命 | D18: 44832 | E18: 旭土地 | F18: 4割損金 | G18: 0.4 | H18: 坂本 信 | I18: 97歳まで | J18: 年払 | K18: 4973060 | L18: =IF(J18="月払",K18*12,IF(J18="年払",K18,0)) -> 4973060 | M18: =L18*G18 -> 1989224 | N18: 2,300万円 | O18: 1654 | P18: 0.831 | Q18: 保有 | R18: =IF(J18="年払",MONTH(D18),"") -> 9 | T18: 元表の記載: 三菱
A19: 15 | B19: 日本生命 | D19: 45097 | E19: 旭土地 | F19: 4割損金 | G19: 0.4 | H19: 岡田 淳 | I19: 100歳まで | J19: 年払 | K19: 3014812 | L19: =IF(J19="月払",K19*12,IF(J19="年払",K19,0)) -> 3014812 | M19: =L19*G19 -> 1205924.8 | N19: 12,400万円 | O19: 714 | P19: 0.789 | Q19: 保有 | R19: =IF(J19="年払",MONTH(D19),"") -> 6 | T19: 元表の記載: 横浜
A20: 16 | B20: 日本生命 | D20: 45191 | E20: 旭土地 | F20: 4割損金 | G20: 0.4 | H20: 岡田 淳 | I20: 100歳まで | J20: 年払 | K20: 3014812 | L20: =IF(J20="月払",K20*12,IF(J20="年払",K20,0)) -> 3014812 | M20: =L20*G20 -> 1205924.8 | N20: 12,400万円 | O20: 451 | P20: 0.748 | Q20: 保有 | R20: =IF(J20="年払",MONTH(D20),"") -> 9 | T20: 元表の記載: 横浜
A21: 17 | B21: 明治安田 | D21: 44092 | E21: 旭土地 | F21: 新養老保険 | G21: 0.5 | H21: 坂本 武 | I21: 72歳まで | J21: 年払 | K21: 769825 | L21: =IF(J21="月払",K21*12,IF(J21="年払",K21,0)) -> 769825 | M21: =L21*G21 -> 384912.5 | N21: 700万円 | O21: 461 | P21: 0.881 | Q21: 2030年度解約 | R21: =IF(J21="年払",MONTH(D21),"") -> 9 | T21: 元表の記載: 横浜
A22: 18 | B22: 明治安田 | D22: 44090 | E22: 旭土地 | F22: 新養老保険 | G22: 0.5 | H22: 横山 清美 | I22: 67歳まで | J22: 年払 | K22: 746963 | L22: =IF(J22="月払",K22*12,IF(J22="年払",K22,0)) -> 746963 | M22: =L22*G22 -> 373481.5 | N22: 700万円 | O22: 411 | P22: 0.917 | Q22: 2030年度解約 | R22: =IF(J22="年払",MONTH(D22),"") -> 9 | T22: 元表の記載: 横浜
A23: 19 | B23: 大同生命 | D23: 41821 | E23: 旭土地 | F23: 全損 | G23: 0 | H23: 坂本 麻莉 | I23: 70歳まで | J23: 払済 | K23: 0 | L23: =IF(J23="月払",K23*12,IF(J23="年払",K23,0)) -> 0 | M23: =L23*G23 -> 0 | N23: 1,878万円 | O23: 591 | P23: 0.687 | R23: =IF(J23="年払",MONTH(D23),"") | T23: 元表の右端欄(番号欄に「4」と記載)。番号は本表で19・20に付番
A24: 20 | B24: 大同生命 | D24: 41821 | E24: 旭土地 | F24: 全額損金 | G24: 1 | H24: 坂本 麻莉 | I24: 70歳まで | J24: 月払 | K24: 28900 | L24: =IF(J24="月払",K24*12,IF(J24="年払",K24,0)) -> 346800 | M24: =L24*G24 -> 346800 | N24: 10,000万円 | O24: 289 | P24: 0.667 | R24: =IF(J24="年払",MONTH(D24),"") | T24: 元表の右端欄(番号欄に「11」と記載)。番号は本表で19・20に付番
A25: 合計 | K25: =SUMIFS(K5:K24,J5:J24,"月払") -> 892858 | L25: =SUM(L5:L24) -> 33667055 | M25: =SUM(M5:M24) -> 20689164 | O25: =SUM(O5:O24) -> 12057 | T25: K列合計は月払の月額合計
A27: 集計
A28: 月払の月額合計(円) | E28: =SUMIFS(K5:K24,J5:J24,"月払") -> 892858
A29: 年払の年額合計(円) | E29: =SUMIFS(L5:L24,J5:J24,"年払") -> 22952759
A30: 年間保険料合計(円) | E30: =L25 -> 33667055
A31: 年間損金計上額(円) | E31: =M25 -> 20689164
A32: 損金にならない部分(円・資産計上等) | E32: =L25-M25 -> 12977891
A33: 払済・保険料0の契約数 | E33: =COUNTIF(J5:J24,"払済") -> 5
A34: R8年の返戻金合計(万円) | E34: =O25 -> 12057
A36: 元表との照合 | E36: 本表 | F36: 元表 | G36: 差
A37: 月払の月額合計 番号1〜18(元表 863,958円) | E37: =SUMIFS(K5:K22,J5:J22,"月払") -> 863958 | F37: 863958 | G37: =E37-F37 -> 0
A38: 年払 番号11・12(元表 7,406,207円) | E38: =SUMIFS(L15:L16,J15:J16,"年払") -> 7406207 | F38: 7406207 | G38: =E38-F38 -> 0
A39: 年払 番号13〜18(元表 15,546,552円) | E39: =SUMIFS(L17:L22,J17:J22,"年払") -> 15546552 | F39: 15546552 | G39: =E39-F39 -> 0
A40: 損金計上 番号1〜18の合計(元表 20,068,524円) | E40: =SUM(M5:M22)-M9 -> 20068524 | F40: 20068524 | G40: =E40-F40 -> 0
A42: ※元表の損金計上合計は、番号5(医療保険・年27万円)と別枠の番号20(月額28,900円)を含んでいません。本表の「年間損金計上額」にはこの2件を含めています。
A43: ※年払の支払月は加入日の月と仮定しています(会計上の保険料の計上月とおおむね一致)。実際の払込日は保険証券・引落口座で確認してください。
A44: ※「支払停止年月」(黄色)に払済・解約の予定月を入れると、その月以降の支払が保険支払シートから除かれます。空欄=継続。
A45: ※Ｊ=三大疾病(特約上皮内癌) / Ｔ=身体障害+障害死亡 / Ｌ=病気死亡・事故死(総合型Ｌ=ＡＩＧの損害付き)。被保険者名の頭記号は元表のまま。

Sheet 保険支払
A1: 保険料の支払カレンダー(現金ベース・円)
A2: 保険一覧の払込方法・保険料から月別に展開。月払=毎月、年払=加入日の月、払済=0。支払停止年月(保険一覧のS列)を入れるとその月以降は0になります。
A4: 番号・保険会社・被保険者 | C4: 46296 | D4: =EDATE(C4,1) -> 46327 | E4: =EDATE(D4,1) -> 46357 | F4: =EDATE(E4,1) -> 46388 | G4: =EDATE(F4,1) -> 46419 | H4: =EDATE(G4,1) -> 46447 | I4: =EDATE(H4,1) -> 46478 | J4: =EDATE(I4,1) -> 46508 | K4: =EDATE(J4,1) -> 46539 | ... N4: =EDATE(M4,1) -> 46631 | O4: 期間計 | P4: 来期計 (R8/10〜R9/9)
A6: =保険一覧!A5&" "&保険一覧!B5&" "&保険一覧!H5 -> 1 大同生命 岡田 優子 | C6: =IF(OR(保険一覧!$S5="",C$4<保険一覧!$S5),IF(保険一覧!$J5="月払",保険一覧!$K5,IF(AND(保険一覧!$J5="年払",MONTH(C$4)=保険一覧!$R5),保険一覧!$K5,0)),0) -> 0 | D6: =IF(OR(保険一覧!$S5="",D$4<保険一覧!$S5),IF(保険一覧!$J5="月払",保険一覧!$K5,IF(AND(保険一覧!$J5="年払",MONTH(D$4)=保険一覧!$R5),保険一覧!$K5,0)),0) -> 0 | E6: =IF(OR(保険一覧!$S5="",E$4<保険一覧!$S5),IF(保険一覧!$J5="月払",保険一覧!$K5,IF(AND(保険一覧!$J5="年払",MONTH(E$4)=保険一覧!$R5),保険一覧!$K5,0)),0) -> 0 | F6: =IF(OR(保険一覧!$S5="",F$4<保険一覧!$S5),IF(保険一覧!$J5="月払",保険一覧!$K5,IF(AND(保険一覧!$J5="年払",MONTH(F$4)=保険一覧!$R5),保険一覧!$K5,0)),0) -> 0 | G6: =IF(OR(保険一覧!$S5="",G$4<保険一覧!$S5),IF(保険一覧!$J5="月払",保険一覧!$K5,IF(AND(保険一覧!$J5="年払",MONTH(G$4)=保険一覧!$R5),保険一覧!$K5,0)),0) -> 0 | H6: =IF(OR(保険一覧!$S5="",H$4<保険一覧!$S5),IF(保険一覧!$J5="月払",保険一覧!$K5,IF(AND(保険一覧!$J5="年払",MONTH(H$4)=保険一覧!$R5),保険一覧!$K5,0)),0) -> 0 | I6: =IF(OR(保険一覧!$S5="",I$4<保険一覧!$S5),IF(保険一覧!$J5="月払",保険一覧!$K5,IF(AND(保険一覧!$J5="年払",MONTH(I$4)=保険一覧!$R5),保険一覧!$K5,0)),0) -> 0 | J6: =IF(OR(保険一覧!$S5="",J$4<保険一覧!$S5),IF(保険一覧!$J5="月払",保険一覧!$K5,IF(AND(保険一覧!$J5="年払",MONTH(J$4)=保険一覧!$R5),保険一覧!$K5,0)),0) -> 0 | ... N6: =IF(OR(保険一覧!$S5="",N$4<保険一覧!$S5),IF(保険一覧!$J5="月払",保険一覧!$K5,IF(AND(保険一覧!$J5="年払",MONTH(N$4)=保険一覧!$R5),保険一覧!$K5,0)),0) -> 0 | O6: =SUM(C6:N6) -> 0 | P6: =SUMIFS(C6:N6,$C$4:$N$4,">="&DATE(2026,10,1),$C$4:$N$4,"<="&DATE(2027,9,1)) -> 0
A7: =保険一覧!A6&" "&保険一覧!B6&" "&保険一覧!H6 -> 2 大同生命 岡田 淳 | C7: =IF(OR(保険一覧!$S6="",C$4<保険一覧!$S6),IF(保険一覧!$J6="月払",保険一覧!$K6,IF(AND(保険一覧!$J6="年払",MONTH(C$4)=保険一覧!$R6),保険一覧!$K6,0)),0) -> 0 | D7: =IF(OR(保険一覧!$S6="",D$4<保険一覧!$S6),IF(保険一覧!$J6="月払",保険一覧!$K6,IF(AND(保険一覧!$J6="年払",MONTH(D$4)=保険一覧!$R6),保険一覧!$K6,0)),0) -> 0 | E7: =IF(OR(保険一覧!$S6="",E$4<保険一覧!$S6),IF(保険一覧!$J6="月払",保険一覧!$K6,IF(AND(保険一覧!$J6="年払",MONTH(E$4)=保険一覧!$R6),保険一覧!$K6,0)),0) -> 0 | F7: =IF(OR(保険一覧!$S6="",F$4<保険一覧!$S6),IF(保険一覧!$J6="月払",保険一覧!$K6,IF(AND(保険一覧!$J6="年払",MONTH(F$4)=保険一覧!$R6),保険一覧!$K6,0)),0) -> 0 | G7: =IF(OR(保険一覧!$S6="",G$4<保険一覧!$S6),IF(保険一覧!$J6="月払",保険一覧!$K6,IF(AND(保険一覧!$J6="年払",MONTH(G$4)=保険一覧!$R6),保険一覧!$K6,0)),0) -> 0 | H7: =IF(OR(保険一覧!$S6="",H$4<保険一覧!$S6),IF(保険一覧!$J6="月払",保険一覧!$K6,IF(AND(保険一覧!$J6="年払",MONTH(H$4)=保険一覧!$R6),保険一覧!$K6,0)),0) -> 0 | I7: =IF(OR(保険一覧!$S6="",I$4<保険一覧!$S6),IF(保険一覧!$J6="月払",保険一覧!$K6,IF(AND(保険一覧!$J6="年払",MONTH(I$4)=保険一覧!$R6),保険一覧!$K6,0)),0) -> 0 | J7: =IF(OR(保険一覧!$S6="",J$4<保険一覧!$S6),IF(保険一覧!$J6="月払",保険一覧!$K6,IF(AND(保険一覧!$J6="年払",MONTH(J$4)=保険一覧!$R6),保険一覧!$K6,0)),0) -> 0 | ... N7: =IF(OR(保険一覧!$S6="",N$4<保険一覧!$S6),IF(保険一覧!$J6="月払",保険一覧!$K6,IF(AND(保険一覧!$J6="年払",MONTH(N$4)=保険一覧!$R6),保険一覧!$K6,0)),0) -> 0 | O7: =SUM(C7:N7) -> 0 | P7: =SUMIFS(C7:N7,$C$4:$N$4,">="&DATE(2026,10,1),$C$4:$N$4,"<="&DATE(2027,9,1)) -> 0
A8: =保険一覧!A7&" "&保険一覧!B7&" "&保険一覧!H7 -> 3 大同生命 Ｊ 岡田 優子 | C8: =IF(OR(保険一覧!$S7="",C$4<保険一覧!$S7),IF(保険一覧!$J7="月払",保険一覧!$K7,IF(AND(保険一覧!$J7="年払",MONTH(C$4)=保険一覧!$R7),保険一覧!$K7,0)),0) -> 0 | D8: =IF(OR(保険一覧!$S7="",D$4<保険一覧!$S7),IF(保険一覧!$J7="月払",保険一覧!$K7,IF(AND(保険一覧!$J7="年払",MONTH(D$4)=保険一覧!$R7),保険一覧!$K7,0)),0) -> 0 | E8: =IF(OR(保険一覧!$S7="",E$4<保険一覧!$S7),IF(保険一覧!$J7="月払",保険一覧!$K7,IF(AND(保険一覧!$J7="年払",MONTH(E$4)=保険一覧!$R7),保険一覧!$K7,0)),0) -> 0 | F8: =IF(OR(保険一覧!$S7="",F$4<保険一覧!$S7),IF(保険一覧!$J7="月払",保険一覧!$K7,IF(AND(保険一覧!$J7="年払",MONTH(F$4)=保険一覧!$R7),保険一覧!$K7,0)),0) -> 0 | G8: =IF(OR(保険一覧!$S7="",G$4<保険一覧!$S7),IF(保険一覧!$J7="月払",保険一覧!$K7,IF(AND(保険一覧!$J7="年払",MONTH(G$4)=保険一覧!$R7),保険一覧!$K7,0)),0) -> 0 | H8: =IF(OR(保険一覧!$S7="",H$4<保険一覧!$S7),IF(保険一覧!$J7="月払",保険一覧!$K7,IF(AND(保険一覧!$J7="年払",MONTH(H$4)=保険一覧!$R7),保険一覧!$K7,0)),0) -> 0 | I8: =IF(OR(保険一覧!$S7="",I$4<保険一覧!$S7),IF(保険一覧!$J7="月払",保険一覧!$K7,IF(AND(保険一覧!$J7="年払",MONTH(I$4)=保険一覧!$R7),保険一覧!$K7,0)),0) -> 0 | J8: =IF(OR(保険一覧!$S7="",J$4<保険一覧!$S7),IF(保険一覧!$J7="月払",保険一覧!$K7,IF(AND(保険一覧!$J7="年払",MONTH(J$4)=保険一覧!$R7),保険一覧!$K7,0)),0) -> 0 | ... N8: =IF(OR(保険一覧!$S7="",N$4<保険一覧!$S7),IF(保険一覧!$J7="月払",保険一覧!$K7,IF(AND(保険一覧!$J7="年払",MONTH(N$4)=保険一覧!$R7),保険一覧!$K7,0)),0) -> 0 | O8: =SUM(C8:N8) -> 0 | P8: =SUMIFS(C8:N8,$C$4:$N$4,">="&DATE(2026,10,1),$C$4:$N$4,"<="&DATE(2027,9,1)) -> 0
A9: =保険一覧!A8&" "&保険一覧!B8&" "&保険一覧!H8 -> 4 大同生命 Ｔ 岡田 優子 | C9: =IF(OR(保険一覧!$S8="",C$4<保険一覧!$S8),IF(保険一覧!$J8="月払",保険一覧!$K8,IF(AND(保険一覧!$J8="年払",MONTH(C$4)=保険一覧!$R8),保険一覧!$K8,0)),0) -> 0 | D9: =IF(OR(保険一覧!$S8="",D$4<保険一覧!$S8),IF(保険一覧!$J8="月払",保険一覧!$K8,IF(AND(保険一覧!$J8="年払",MONTH(D$4)=保険一覧!$R8),保険一覧!$K8,0)),0) -> 0 | E9: =IF(OR(保険一覧!$S8="",E$4<保険一覧!$S8),IF(保険一覧!$J8="月払",保険一覧!$K8,IF(AND(保険一覧!$J8="年払",MONTH(E$4)=保険一覧!$R8),保険一覧!$K8,0)),0) -> 0 | F9: =IF(OR(保険一覧!$S8="",F$4<保険一覧!$S8),IF(保険一覧!$J8="月払",保険一覧!$K8,IF(AND(保険一覧!$J8="年払",MONTH(F$4)=保険一覧!$R8),保険一覧!$K8,0)),0) -> 0 | G9: =IF(OR(保険一覧!$S8="",G$4<保険一覧!$S8),IF(保険一覧!$J8="月払",保険一覧!$K8,IF(AND(保険一覧!$J8="年払",MONTH(G$4)=保険一覧!$R8),保険一覧!$K8,0)),0) -> 0 | H9: =IF(OR(保険一覧!$S8="",H$4<保険一覧!$S8),IF(保険一覧!$J8="月払",保険一覧!$K8,IF(AND(保険一覧!$J8="年払",MONTH(H$4)=保険一覧!$R8),保険一覧!$K8,0)),0) -> 0 | I9: =IF(OR(保険一覧!$S8="",I$4<保険一覧!$S8),IF(保険一覧!$J8="月払",保険一覧!$K8,IF(AND(保険一覧!$J8="年払",MONTH(I$4)=保険一覧!$R8),保険一覧!$K8,0)),0) -> 0 | J9: =IF(OR(保険一覧!$S8="",J$4<保険一覧!$S8),IF(保険一覧!$J8="月払",保険一覧!$K8,IF(AND(保険一覧!$J8="年払",MONTH(J$4)=保険一覧!$R8),保険一覧!$K8,0)),0) -> 0 | ... N9: =IF(OR(保険一覧!$S8="",N$4<保険一覧!$S8),IF(保険一覧!$J8="月払",保険一覧!$K8,IF(AND(保険一覧!$J8="年払",MONTH(N$4)=保険一覧!$R8),保険一覧!$K8,0)),0) -> 0 | O9: =SUM(C9:N9) -> 0 | P9: =SUMIFS(C9:N9,$C$4:$N$4,">="&DATE(2026,10,1),$C$4:$N$4,"<="&DATE(2027,9,1)) -> 0
A10: =保険一覧!A9&" "&保険一覧!B9&" "&保険一覧!H9 -> 5 大同生命 坂本 武 | C10: =IF(OR(保険一覧!$S9="",C$4<保険一覧!$S9),IF(保険一覧!$J9="月払",保険一覧!$K9,IF(AND(保険一覧!$J9="年払",MONTH(C$4)=保険一覧!$R9),保険一覧!$K9,0)),0) -> 22820 | D10: =IF(OR(保険一覧!$S9="",D$4<保険一覧!$S9),IF(保険一覧!$J9="月払",保険一覧!$K9,IF(AND(保険一覧!$J9="年払",MONTH(D$4)=保険一覧!$R9),保険一覧!$K9,0)),0) -> 22820 | E10: =IF(OR(保険一覧!$S9="",E$4<保険一覧!$S9),IF(保険一覧!$J9="月払",保険一覧!$K9,IF(AND(保険一覧!$J9="年払",MONTH(E$4)=保険一覧!$R9),保険一覧!$K9,0)),0) -> 22820 | F10: =IF(OR(保険一覧!$S9="",F$4<保険一覧!$S9),IF(保険一覧!$J9="月払",保険一覧!$K9,IF(AND(保険一覧!$J9="年払",MONTH(F$4)=保険一覧!$R9),保険一覧!$K9,0)),0) -> 22820 | G10: =IF(OR(保険一覧!$S9="",G$4<保険一覧!$S9),IF(保険一覧!$J9="月払",保険一覧!$K9,IF(AND(保険一覧!$J9="年払",MONTH(G$4)=保険一覧!$R9),保険一覧!$K9,0)),0) -> 22820 | H10: =IF(OR(保険一覧!$S9="",H$4<保険一覧!$S9),IF(保険一覧!$J9="月払",保険一覧!$K9,IF(AND(保険一覧!$J9="年払",MONTH(H$4)=保険一覧!$R9),保険一覧!$K9,0)),0) -> 22820 | I10: =IF(OR(保険一覧!$S9="",I$4<保険一覧!$S9),IF(保険一覧!$J9="月払",保険一覧!$K9,IF(AND(保険一覧!$J9="年払",MONTH(I$4)=保険一覧!$R9),保険一覧!$K9,0)),0) -> 22820 | J10: =IF(OR(保険一覧!$S9="",J$4<保険一覧!$S9),IF(保険一覧!$J9="月払",保険一覧!$K9,IF(AND(保険一覧!$J9="年払",MONTH(J$4)=保険一覧!$R9),保険一覧!$K9,0)),0) -> 22820 | ... N10: =IF(OR(保険一覧!$S9="",N$4<保険一覧!$S9),IF(保険一覧!$J9="月払",保険一覧!$K9,IF(AND(保険一覧!$J9="年払",MONTH(N$4)=保険一覧!$R9),保険一覧!$K9,0)),0) -> 22820 | O10: =SUM(C10:N10) -> 273840 | P10: =SUMIFS(C10:N10,$C$4:$N$4,">="&DATE(2026,10,1),$C$4:$N$4,"<="&DATE(2027,9,1)) -> 273840
A11: =保険一覧!A10&" "&保険一覧!B10&" "&保険一覧!H10 -> 6 大同生命 横山 清美 | C11: =IF(OR(保険一覧!$S10="",C$4<保険一覧!$S10),IF(保険一覧!$J10="月払",保険一覧!$K10,IF(AND(保険一覧!$J10="年払",MONTH(C$4)=保険一覧!$R10),保険一覧!$K10,0)),0) -> 49130 | D11: =IF(OR(保険一覧!$S10="",D$4<保険一覧!$S10),IF(保険一覧!$J10="月払",保険一覧!$K10,IF(AND(保険一覧!$J10="年払",MONTH(D$4)=保険一覧!$R10),保険一覧!$K10,0)),0) -> 49130 | E11: =IF(OR(保険一覧!$S10="",E$4<保険一覧!$S10),IF(保険一覧!$J10="月払",保険一覧!$K10,IF(AND(保険一覧!$J10="年払",MONTH(E$4)=保険一覧!$R10),保険一覧!$K10,0)),0) -> 49130 | F11: =IF(OR(保険一覧!$S10="",F$4<保険一覧!$S10),IF(保険一覧!$J10="月払",保険一覧!$K10,IF(AND(保険一覧!$J10="年払",MONTH(F$4)=保険一覧!$R10),保険一覧!$K10,0)),0) -> 49130 | G11: =IF(OR(保険一覧!$S10="",G$4<保険一覧!$S10),IF(保険一覧!$J10="月払",保険一覧!$K10,IF(AND(保険一覧!$J10="年払",MONTH(G$4)=保険一覧!$R10),保険一覧!$K10,0)),0) -> 49130 | H11: =IF(OR(保険一覧!$S10="",H$4<保険一覧!$S10),IF(保険一覧!$J10="月払",保険一覧!$K10,IF(AND(保険一覧!$J10="年払",MONTH(H$4)=保険一覧!$R10),保険一覧!$K10,0)),0) -> 49130 | I11: =IF(OR(保険一覧!$S10="",I$4<保険一覧!$S10),IF(保険一覧!$J10="月払",保険一覧!$K10,IF(AND(保険一覧!$J10="年払",MONTH(I$4)=保険一覧!$R10),保険一覧!$K10,0)),0) -> 49130 | J11: =IF(OR(保険一覧!$S10="",J$4<保険一覧!$S10),IF(保険一覧!$J10="月払",保険一覧!$K10,IF(AND(保険一覧!$J10="年払",MONTH(J$4)=保険一覧!$R10),保険一覧!$K10,0)),0) -> 49130 | ... N11: =IF(OR(保険一覧!$S10="",N$4<保険一覧!$S10),IF(保険一覧!$J10="月払",保険一覧!$K10,IF(AND(保険一覧!$J10="年払",MONTH(N$4)=保険一覧!$R10),保険一覧!$K10,0)),0) -> 49130 | O11: =SUM(C11:N11) -> 589560 | P11: =SUMIFS(C11:N11,$C$4:$N$4,">="&DATE(2026,10,1),$C$4:$N$4,"<="&DATE(2027,9,1)) -> 589560
A12: =保険一覧!A11&" "&保険一覧!B11&" "&保険一覧!H11 -> 7 大同生命 坂本 武 | C12: =IF(OR(保険一覧!$S11="",C$4<保険一覧!$S11),IF(保険一覧!$J11="月払",保険一覧!$K11,IF(AND(保険一覧!$J11="年払",MONTH(C$4)=保険一覧!$R11),保険一覧!$K11,0)),0) -> 505120 | D12: =IF(OR(保険一覧!$S11="",D$4<保険一覧!$S11),IF(保険一覧!$J11="月払",保険一覧!$K11,IF(AND(保険一覧!$J11="年払",MONTH(D$4)=保険一覧!$R11),保険一覧!$K11,0)),0) -> 505120 | E12: =IF(OR(保険一覧!$S11="",E$4<保険一覧!$S11),IF(保険一覧!$J11="月払",保険一覧!$K11,IF(AND(保険一覧!$J11="年払",MONTH(E$4)=保険一覧!$R11),保険一覧!$K11,0)),0) -> 505120 | F12: =IF(OR(保険一覧!$S11="",F$4<保険一覧!$S11),IF(保険一覧!$J11="月払",保険一覧!$K11,IF(AND(保険一覧!$J11="年払",MONTH(F$4)=保険一覧!$R11),保険一覧!$K11,0)),0) -> 505120 | G12: =IF(OR(保険一覧!$S11="",G$4<保険一覧!$S11),IF(保険一覧!$J11="月払",保険一覧!$K11,IF(AND(保険一覧!$J11="年払",MONTH(G$4)=保険一覧!$R11),保険一覧!$K11,0)),0) -> 505120 | H12: =IF(OR(保険一覧!$S11="",H$4<保険一覧!$S11),IF(保険一覧!$J11="月払",保険一覧!$K11,IF(AND(保険一覧!$J11="年払",MONTH(H$4)=保険一覧!$R11),保険一覧!$K11,0)),0) -> 505120 | I12: =IF(OR(保険一覧!$S11="",I$4<保険一覧!$S11),IF(保険一覧!$J11="月払",保険一覧!$K11,IF(AND(保険一覧!$J11="年払",MONTH(I$4)=保険一覧!$R11),保険一覧!$K11,0)),0) -> 505120 | J12: =IF(OR(保険一覧!$S11="",J$4<保険一覧!$S11),IF(保険一覧!$J11="月払",保険一覧!$K11,IF(AND(保険一覧!$J11="年払",MONTH(J$4)=保険一覧!$R11),保険一覧!$K11,0)),0) -> 505120 | ... N12: =IF(OR(保険一覧!$S11="",N$4<保険一覧!$S11),IF(保険一覧!$J11="月払",保険一覧!$K11,IF(AND(保険一覧!$J11="年払",MONTH(N$4)=保険一覧!$R11),保険一覧!$K11,0)),0) -> 505120 | O12: =SUM(C12:N12) -> 6061440 | P12: =SUMIFS(C12:N12,$C$4:$N$4,">="&DATE(2026,10,1),$C$4:$N$4,"<="&DATE(2027,9,1)) -> 6061440
A13: =保険一覧!A12&" "&保険一覧!B12&" "&保険一覧!H12 -> 8 大同生命 横山 清美 | C13: =IF(OR(保険一覧!$S12="",C$4<保険一覧!$S12),IF(保険一覧!$J12="月払",保険一覧!$K12,IF(AND(保険一覧!$J12="年払",MONTH(C$4)=保険一覧!$R12),保険一覧!$K12,0)),0) -> 57687 | D13: =IF(OR(保険一覧!$S12="",D$4<保険一覧!$S12),IF(保険一覧!$J12="月払",保険一覧!$K12,IF(AND(保険一覧!$J12="年払",MONTH(D$4)=保険一覧!$R12),保険一覧!$K12,0)),0) -> 57687 | E13: =IF(OR(保険一覧!$S12="",E$4<保険一覧!$S12),IF(保険一覧!$J12="月払",保険一覧!$K12,IF(AND(保険一覧!$J12="年払",MONTH(E$4)=保険一覧!$R12),保険一覧!$K12,0)),0) -> 57687 | F13: =IF(OR(保険一覧!$S12="",F$4<保険一覧!$S12),IF(保険一覧!$J12="月払",保険一覧!$K12,IF(AND(保険一覧!$J12="年払",MONTH(F$4)=保険一覧!$R12),保険一覧!$K12,0)),0) -> 57687 | G13: =IF(OR(保険一覧!$S12="",G$4<保険一覧!$S12),IF(保険一覧!$J12="月払",保険一覧!$K12,IF(AND(保険一覧!$J12="年払",MONTH(G$4)=保険一覧!$R12),保険一覧!$K12,0)),0) -> 57687 | H13: =IF(OR(保険一覧!$S12="",H$4<保険一覧!$S12),IF(保険一覧!$J12="月払",保険一覧!$K12,IF(AND(保険一覧!$J12="年払",MONTH(H$4)=保険一覧!$R12),保険一覧!$K12,0)),0) -> 57687 | I13: =IF(OR(保険一覧!$S12="",I$4<保険一覧!$S12),IF(保険一覧!$J12="月払",保険一覧!$K12,IF(AND(保険一覧!$J12="年払",MONTH(I$4)=保険一覧!$R12),保険一覧!$K12,0)),0) -> 57687 | J13: =IF(OR(保険一覧!$S12="",J$4<保険一覧!$S12),IF(保険一覧!$J12="月払",保険一覧!$K12,IF(AND(保険一覧!$J12="年払",MONTH(J$4)=保険一覧!$R12),保険一覧!$K12,0)),0) -> 57687 | ... N13: =IF(OR(保険一覧!$S12="",N$4<保険一覧!$S12),IF(保険一覧!$J12="月払",保険一覧!$K12,IF(AND(保険一覧!$J12="年払",MONTH(N$4)=保険一覧!$R12),保険一覧!$K12,0)),0) -> 57687 | O13: =SUM(C13:N13) -> 692244 | P13: =SUMIFS(C13:N13,$C$4:$N$4,">="&DATE(2026,10,1),$C$4:$N$4,"<="&DATE(2027,9,1)) -> 692244
A14: =保険一覧!A13&" "&保険一覧!B13&" "&保険一覧!H13 -> 9 大同生命 坂本 麻莉 | C14: =IF(OR(保険一覧!$S13="",C$4<保険一覧!$S13),IF(保険一覧!$J13="月払",保険一覧!$K13,IF(AND(保険一覧!$J13="年払",MONTH(C$4)=保険一覧!$R13),保険一覧!$K13,0)),0) -> 179573 | D14: =IF(OR(保険一覧!$S13="",D$4<保険一覧!$S13),IF(保険一覧!$J13="月払",保険一覧!$K13,IF(AND(保険一覧!$J13="年払",MONTH(D$4)=保険一覧!$R13),保険一覧!$K13,0)),0) -> 179573 | E14: =IF(OR(保険一覧!$S13="",E$4<保険一覧!$S13),IF(保険一覧!$J13="月払",保険一覧!$K13,IF(AND(保険一覧!$J13="年払",MONTH(E$4)=保険一覧!$R13),保険一覧!$K13,0)),0) -> 179573 | F14: =IF(OR(保険一覧!$S13="",F$4<保険一覧!$S13),IF(保険一覧!$J13="月払",保険一覧!$K13,IF(AND(保険一覧!$J13="年払",MONTH(F$4)=保険一覧!$R13),保険一覧!$K13,0)),0) -> 179573 | G14: =IF(OR(保険一覧!$S13="",G$4<保険一覧!$S13),IF(保険一覧!$J13="月払",保険一覧!$K13,IF(AND(保険一覧!$J13="年払",MONTH(G$4)=保険一覧!$R13),保険一覧!$K13,0)),0) -> 179573 | H14: =IF(OR(保険一覧!$S13="",H$4<保険一覧!$S13),IF(保険一覧!$J13="月払",保険一覧!$K13,IF(AND(保険一覧!$J13="年払",MONTH(H$4)=保険一覧!$R13),保険一覧!$K13,0)),0) -> 179573 | I14: =IF(OR(保険一覧!$S13="",I$4<保険一覧!$S13),IF(保険一覧!$J13="月払",保険一覧!$K13,IF(AND(保険一覧!$J13="年払",MONTH(I$4)=保険一覧!$R13),保険一覧!$K13,0)),0) -> 179573 | J14: =IF(OR(保険一覧!$S13="",J$4<保険一覧!$S13),IF(保険一覧!$J13="月払",保険一覧!$K13,IF(AND(保険一覧!$J13="年払",MONTH(J$4)=保険一覧!$R13),保険一覧!$K13,0)),0) -> 179573 | ... N14: =IF(OR(保険一覧!$S13="",N$4<保険一覧!$S13),IF(保険一覧!$J13="月払",保険一覧!$K13,IF(AND(保険一覧!$J13="年払",MONTH(N$4)=保険一覧!$R13),保険一覧!$K13,0)),0) -> 179573 | O14: =SUM(C14:N14) -> 2154876 | P14: =SUMIFS(C14:N14,$C$4:$N$4,">="&DATE(2026,10,1),$C$4:$N$4,"<="&DATE(2027,9,1)) -> 2154876
A15: =保険一覧!A14&" "&保険一覧!B14&" "&保険一覧!H14 -> 10 大同生命 坂本 麻莉 | C15: =IF(OR(保険一覧!$S14="",C$4<保険一覧!$S14),IF(保険一覧!$J14="月払",保険一覧!$K14,IF(AND(保険一覧!$J14="年払",MONTH(C$4)=保険一覧!$R14),保険一覧!$K14,0)),0) -> 49628 | D15: =IF(OR(保険一覧!$S14="",D$4<保険一覧!$S14),IF(保険一覧!$J14="月払",保険一覧!$K14,IF(AND(保険一覧!$J14="年払",MONTH(D$4)=保険一覧!$R14),保険一覧!$K14,0)),0) -> 49628 | E15: =IF(OR(保険一覧!$S14="",E$4<保険一覧!$S14),IF(保険一覧!$J14="月払",保険一覧!$K14,IF(AND(保険一覧!$J14="年払",MONTH(E$4)=保険一覧!$R14),保険一覧!$K14,0)),0) -> 49628 | F15: =IF(OR(保険一覧!$S14="",F$4<保険一覧!$S14),IF(保険一覧!$J14="月払",保険一覧!$K14,IF(AND(保険一覧!$J14="年払",MONTH(F$4)=保険一覧!$R14),保険一覧!$K14,0)),0) -> 49628 | G15: =IF(OR(保険一覧!$S14="",G$4<保険一覧!$S14),IF(保険一覧!$J14="月払",保険一覧!$K14,IF(AND(保険一覧!$J14="年払",MONTH(G$4)=保険一覧!$R14),保険一覧!$K14,0)),0) -> 49628 | H15: =IF(OR(保険一覧!$S14="",H$4<保険一覧!$S14),IF(保険一覧!$J14="月払",保険一覧!$K14,IF(AND(保険一覧!$J14="年払",MONTH(H$4)=保険一覧!$R14),保険一覧!$K14,0)),0) -> 49628 | I15: =IF(OR(保険一覧!$S14="",I$4<保険一覧!$S14),IF(保険一覧!$J14="月払",保険一覧!$K14,IF(AND(保険一覧!$J14="年払",MONTH(I$4)=保険一覧!$R14),保険一覧!$K14,0)),0) -> 49628 | J15: =IF(OR(保険一覧!$S14="",J$4<保険一覧!$S14),IF(保険一覧!$J14="月払",保険一覧!$K14,IF(AND(保険一覧!$J14="年払",MONTH(J$4)=保険一覧!$R14),保険一覧!$K14,0)),0) -> 49628 | ... N15: =IF(OR(保険一覧!$S14="",N$4<保険一覧!$S14),IF(保険一覧!$J14="月払",保険一覧!$K14,IF(AND(保険一覧!$J14="年払",MONTH(N$4)=保険一覧!$R14),保険一覧!$K14,0)),0) -> 49628 | O15: =SUM(C15:N15) -> 595536 | P15: =SUMIFS(C15:N15,$C$4:$N$4,">="&DATE(2026,10,1),$C$4:$N$4,"<="&DATE(2027,9,1)) -> 595536
A16: =保険一覧!A15&" "&保険一覧!B15&" "&保険一覧!H15 -> 11 大同生命 坂本 武 | C16: =IF(OR(保険一覧!$S15="",C$4<保険一覧!$S15),IF(保険一覧!$J15="月払",保険一覧!$K15,IF(AND(保険一覧!$J15="年払",MONTH(C$4)=保険一覧!$R15),保険一覧!$K15,0)),0) -> 0 | D16: =IF(OR(保険一覧!$S15="",D$4<保険一覧!$S15),IF(保険一覧!$J15="月払",保険一覧!$K15,IF(AND(保険一覧!$J15="年払",MONTH(D$4)=保険一覧!$R15),保険一覧!$K15,0)),0) -> 0 | E16: =IF(OR(保険一覧!$S15="",E$4<保険一覧!$S15),IF(保険一覧!$J15="月払",保険一覧!$K15,IF(AND(保険一覧!$J15="年払",MONTH(E$4)=保険一覧!$R15),保険一覧!$K15,0)),0) -> 0 | F16: =IF(OR(保険一覧!$S15="",F$4<保険一覧!$S15),IF(保険一覧!$J15="月払",保険一覧!$K15,IF(AND(保険一覧!$J15="年払",MONTH(F$4)=保険一覧!$R15),保険一覧!$K15,0)),0) -> 0 | G16: =IF(OR(保険一覧!$S15="",G$4<保険一覧!$S15),IF(保険一覧!$J15="月払",保険一覧!$K15,IF(AND(保険一覧!$J15="年払",MONTH(G$4)=保険一覧!$R15),保険一覧!$K15,0)),0) -> 0 | H16: =IF(OR(保険一覧!$S15="",H$4<保険一覧!$S15),IF(保険一覧!$J15="月払",保険一覧!$K15,IF(AND(保険一覧!$J15="年払",MONTH(H$4)=保険一覧!$R15),保険一覧!$K15,0)),0) -> 0 | I16: =IF(OR(保険一覧!$S15="",I$4<保険一覧!$S15),IF(保険一覧!$J15="月払",保険一覧!$K15,IF(AND(保険一覧!$J15="年払",MONTH(I$4)=保険一覧!$R15),保険一覧!$K15,0)),0) -> 0 | J16: =IF(OR(保険一覧!$S15="",J$4<保険一覧!$S15),IF(保険一覧!$J15="月払",保険一覧!$K15,IF(AND(保険一覧!$J15="年払",MONTH(J$4)=保険一覧!$R15),保険一覧!$K15,0)),0) -> 0 | ... N16: =IF(OR(保険一覧!$S15="",N$4<保険一覧!$S15),IF(保険一覧!$J15="月払",保険一覧!$K15,IF(AND(保険一覧!$J15="年払",MONTH(N$4)=保険一覧!$R15),保険一覧!$K15,0)),0) -> 0 | O16: =SUM(C16:N16) -> 5698547 | P16: =SUMIFS(C16:N16,$C$4:$N$4,">="&DATE(2026,10,1),$C$4:$N$4,"<="&DATE(2027,9,1)) -> 5698547
A17: =保険一覧!A16&" "&保険一覧!B16&" "&保険一覧!H16 -> 12 大同生命 Ｔ 岡田 淳 | C17: =IF(OR(保険一覧!$S16="",C$4<保険一覧!$S16),IF(保険一覧!$J16="月払",保険一覧!$K16,IF(AND(保険一覧!$J16="年払",MONTH(C$4)=保険一覧!$R16),保険一覧!$K16,0)),0) -> 0 | D17: =IF(OR(保険一覧!$S16="",D$4<保険一覧!$S16),IF(保険一覧!$J16="月払",保険一覧!$K16,IF(AND(保険一覧!$J16="年払",MONTH(D$4)=保険一覧!$R16),保険一覧!$K16,0)),0) -> 0 | E17: =IF(OR(保険一覧!$S16="",E$4<保険一覧!$S16),IF(保険一覧!$J16="月払",保険一覧!$K16,IF(AND(保険一覧!$J16="年払",MONTH(E$4)=保険一覧!$R16),保険一覧!$K16,0)),0) -> 0 | F17: =IF(OR(保険一覧!$S16="",F$4<保険一覧!$S16),IF(保険一覧!$J16="月払",保険一覧!$K16,IF(AND(保険一覧!$J16="年払",MONTH(F$4)=保険一覧!$R16),保険一覧!$K16,0)),0) -> 0 | G17: =IF(OR(保険一覧!$S16="",G$4<保険一覧!$S16),IF(保険一覧!$J16="月払",保険一覧!$K16,IF(AND(保険一覧!$J16="年払",MONTH(G$4)=保険一覧!$R16),保険一覧!$K16,0)),0) -> 0 | H17: =IF(OR(保険一覧!$S16="",H$4<保険一覧!$S16),IF(保険一覧!$J16="月払",保険一覧!$K16,IF(AND(保険一覧!$J16="年払",MONTH(H$4)=保険一覧!$R16),保険一覧!$K16,0)),0) -> 0 | I17: =IF(OR(保険一覧!$S16="",I$4<保険一覧!$S16),IF(保険一覧!$J16="月払",保険一覧!$K16,IF(AND(保険一覧!$J16="年払",MONTH(I$4)=保険一覧!$R16),保険一覧!$K16,0)),0) -> 0 | J17: =IF(OR(保険一覧!$S16="",J$4<保険一覧!$S16),IF(保険一覧!$J16="月払",保険一覧!$K16,IF(AND(保険一覧!$J16="年払",MONTH(J$4)=保険一覧!$R16),保険一覧!$K16,0)),0) -> 0 | ... N17: =IF(OR(保険一覧!$S16="",N$4<保険一覧!$S16),IF(保険一覧!$J16="月払",保険一覧!$K16,IF(AND(保険一覧!$J16="年払",MONTH(N$4)=保険一覧!$R16),保険一覧!$K16,0)),0) -> 0 | O17: =SUM(C17:N17) -> 1707660 | P17: =SUMIFS(C17:N17,$C$4:$N$4,">="&DATE(2026,10,1),$C$4:$N$4,"<="&DATE(2027,9,1)) -> 1707660
... A25: =保険一覧!A24&" "&保険一覧!B24&" "&保険一覧!H24 -> 20 大同生命 坂本 麻莉 | C25: =IF(OR(保険一覧!$S24="",C$4<保険一覧!$S24),IF(保険一覧!$J24="月払",保険一覧!$K24,IF(AND(保険一覧!$J24="年払",MONTH(C$4)=保険一覧!$R24),保険一覧!$K24,0)),0) -> 28900 | D25: =IF(OR(保険一覧!$S24="",D$4<保険一覧!$S24),IF(保険一覧!$J24="月払",保険一覧!$K24,IF(AND(保険一覧!$J24="年払",MONTH(D$4)=保険一覧!$R24),保険一覧!$K24,0)),0) -> 28900 | E25: =IF(OR(保険一覧!$S24="",E$4<保険一覧!$S24),IF(保険一覧!$J24="月払",保険一覧!$K24,IF(AND(保険一覧!$J24="年払",MONTH(E$4)=保険一覧!$R24),保険一覧!$K24,0)),0) -> 28900 | F25: =IF(OR(保険一覧!$S24="",F$4<保険一覧!$S24),IF(保険一覧!$J24="月払",保険一覧!$K24,IF(AND(保険一覧!$J24="年払",MONTH(F$4)=保険一覧!$R24),保険一覧!$K24,0)),0) -> 28900 | G25: =IF(OR(保険一覧!$S24="",G$4<保険一覧!$S24),IF(保険一覧!$J24="月払",保険一覧!$K24,IF(AND(保険一覧!$J24="年払",MONTH(G$4)=保険一覧!$R24),保険一覧!$K24,0)),0) -> 28900 | H25: =IF(OR(保険一覧!$S24="",H$4<保険一覧!$S24),IF(保険一覧!$J24="月払",保険一覧!$K24,IF(AND(保険一覧!$J24="年払",MONTH(H$4)=保険一覧!$R24),保険一覧!$K24,0)),0) -> 28900 | I25: =IF(OR(保険一覧!$S24="",I$4<保険一覧!$S24),IF(保険一覧!$J24="月払",保険一覧!$K24,IF(AND(保険一覧!$J24="年払",MONTH(I$4)=保険一覧!$R24),保険一覧!$K24,0)),0) -> 28900 | J25: =IF(OR(保険一覧!$S24="",J$4<保険一覧!$S24),IF(保険一覧!$J24="月払",保険一覧!$K24,IF(AND(保険一覧!$J24="年払",MONTH(J$4)=保険一覧!$R24),保険一覧!$K24,0)),0) -> 28900 | ... N25: =IF(OR(保険一覧!$S24="",N$4<保険一覧!$S24),IF(保険一覧!$J24="月払",保険一覧!$K24,IF(AND(保険一覧!$J24="年払",MONTH(N$4)=保険一覧!$R24),保険一覧!$K24,0)),0) -> 28900 | O25: =SUM(C25:N25) -> 346800 | P25: =SUMIFS(C25:N25,$C$4:$N$4,">="&DATE(2026,10,1),$C$4:$N$4,"<="&DATE(2027,9,1)) -> 346800
A26: 保険料 現金支払計 | C26: =SUM(C6:C25) -> 892858 | D26: =SUM(D6:D25) -> 892858 | E26: =SUM(E6:E25) -> 892858 | F26: =SUM(F6:F25) -> 892858 | G26: =SUM(G6:G25) -> 892858 | H26: =SUM(H6:H25) -> 892858 | I26: =SUM(I6:I25) -> 892858 | J26: =SUM(J6:J25) -> 892858 | ... P26: =SUM(P6:P25) -> 33667055
A28: ※来期計は令和8年10月〜令和9年9月(令和9年9月期)の合計。年払の支払月は加入日の月と仮定しています。

Sheet 返戻金推移
A1: 解約返戻金の推移(万円)・旭土地建物
A2: 出典: 保険一覧ファイル「旭土地 2026.6.10」。各年の返戻金(万円)と返戻率。番号5(医療保険)は元表に推移なし。
A4: 年 | B4: =保険一覧!A5&" "&保険一覧!B5&CHAR(10)&保険一覧!H5 -> 1 大同生命 岡田 優子 | C4: =保険一覧!A6&" "&保険一覧!B6&CHAR(10)&保険一覧!H6 -> 2 大同生命 岡田 淳 | D4: =保険一覧!A7&" "&保険一覧!B7&CHAR(10)&保険一覧!H7 -> 3 大同生命 Ｊ 岡田 優子 | E4: =保険一覧!A8&" "&保険一覧!B8&CHAR(10)&保険一覧!H8 -> 4 大同生命 Ｔ 岡田 優子 | F4: =保険一覧!A9&" "&保険一覧!B9&CHAR(10)&保険一覧!H9 -> 5 大同生命 坂本 武 | G4: =保険一覧!A10&" "&保険一覧!B10&CHAR(10)&保険一覧!H10 -> 6 大同生命 横山 清美 | H4: =保険一覧!A11&" "&保険一覧!B11&CHAR(10)&保険一覧!H11 -> 7 大同生命 坂本 武 | I4: =保険一覧!A12&" "&保険一覧!B12&CHAR(10)&保険一覧!H12 -> 8 大同生命 横山 清美 | J4: =保険一覧!A13&" "&保険一覧!B13&CHAR(10)&保険一覧!H13 -> 9 大同生命 坂本 麻莉 | K4: =保険一覧!A14&" "&保険一覧!B14&CHAR(10)&保険一覧!H14 -> 10 大同生命 坂本 麻莉 | L4: =保険一覧!A15&" "&保険一覧!B15&CHAR(10)&保険一覧!H15 -> 11 大同生命 坂本 武 | M4: =保険一覧!A16&" "&保険一覧!B16&CHAR(10)&保険一覧!H16 -> 12 大同生命 Ｔ 岡田 淳 | N4: =保険一覧!A17&" "&保険一覧!B17&CHAR(10)&保険一覧!H17 -> 13 日本生命 坂本 信 | O4: =保険一覧!A18&" "&保険一覧!B18&CHAR(10)&保険一覧!H18 -> 14 日本生命 坂本 信 | P4: =保険一覧!A19&" "&保険一覧!B19&CHAR(10)&保険一覧!H19 -> 15 日本生命 岡田 淳 | Q4: =保険一覧!A20&" "&保険一覧!B20&CHAR(10)&保険一覧!H20 -> 16 日本生命 岡田 淳 | R4: =保険一覧!A21&" "&保険一覧!B21&CHAR(10)&保険一覧!H21 -> 17 明治安田 坂本 武 | S4: =保険一覧!A22&" "&保険一覧!B22&CHAR(10)&保険一覧!H22 -> 18 明治安田 横山 清美 | T4: =保険一覧!A23&" "&保険一覧!B23&CHAR(10)&保険一覧!H23 -> 19 大同生命 坂本 麻莉 | U4: =保険一覧!A24&" "&保険一覧!B24&CHAR(10)&保険一覧!H24 -> 20 大同生命 坂本 麻莉 | V4: 合計
A5: 2025年 | B5: 159 | C5: 257 | D5: 292 | E5: 167 | G5: 108 | H5: 1839 | I5: 149 | J5: 503 | K5: 116 | L5: 849 | M5: 220 | N5: 982 | O5: 1201 | P5: 451 | Q5: 188 | R5: 384 | S5: 340 | T5: 591 | U5: 267 | V5: =SUM(B5:U5) -> 9063
A6: 2026年 | B6: 165 | C6: 266 | D6: 433 | E6: 241 | G6: 131 | H6: 2247 | I6: 196 | J6: 654 | K6: 456 | L6: 1138 | M6: 309 | N6: 1250 | O6: 1654 | P6: 714 | Q6: 451 | R6: 461 | S6: 411 | T6: 591 | U6: 289 | V6: =SUM(B6:U6) -> 12057
A7: 2027年 | B7: 165 | C7: 267 | D7: 434 | E7: 316 | G7: 154 | H7: 2651 | I7: 242 | J7: 800 | K7: 196 | L7: 1422 | M7: 399 | N7: 1516 | O7: 2114 | P7: 975 | Q7: 714 | R7: 538 | S7: 482 | T7: 590 | U7: 310 | V7: =SUM(B7:U7) -> 14285
A8: 2028年 | B8: 166 | C8: 270 | D8: 434 | E8: 389 | G8: 176 | H8: 3049 | I8: 287 | J8: 944 | K8: 236 | L8: 1701 | M8: 488 | N8: 1780 | O8: 2578 | P8: 1238 | Q8: 975 | R8: 615 | S8: 554 | T8: 589 | U8: 331 | V8: =SUM(B8:U8) -> 16800
A9: 2029年 | B9: 166 | C9: 271 | D9: 435 | E9: 462 | G9: 198 | H9: 3442 | I9: 333 | J9: 1083 | K9: 276 | L9: 1974 | M9: 577 | N9: 2046 | O9: 3044 | P9: 1500 | Q9: 1238 | R9: 692 | S9: 626 | T9: 586 | U9: 351 | V9: =SUM(B9:U9) -> 19300
A10: 2030年 | B10: 167 | C10: 272 | D10: 435 | E10: 535 | G10: 217 | H10: 3828 | I10: 377 | J10: 1220 | K10: 316 | L10: 2238 | M10: 667 | N10: 2311 | O10: 3518 | P10: 1760 | Q10: 1500 | R10: 769 | S10: 700 | T10: 584 | U10: 371 | V10: =SUM(B10:U10) -> 21785
A11: 2031年 | B11: 167 | C11: 273 | D11: 435 | E11: 608 | G11: 235 | H11: 4193 | I11: 421 | J11: 1354 | K11: 356 | L11: 2494 | M11: 756 | N11: 2576 | O11: 3995 | P11: 2022 | Q11: 1760 | T11: 580 | U11: 390 | V11: =SUM(B11:U11) -> 22615
A12: 2032年 | B12: 168 | C12: 274 | D12: 435 | E12: 680 | G12: 250 | H12: 4533 | I12: 464 | J12: 1484 | K12: 395 | L12: 2740 | M12: 845 | N12: 2832 | O12: 4479 | P12: 2281 | Q12: 2022 | T12: 576 | U12: 409 | V12: =SUM(B12:U12) -> 24867
A13: 2033年 | B13: 168 | C13: 275 | D13: 435 | E13: 747 | G13: 262 | H13: 4861 | I13: 505 | J13: 1607 | K13: 433 | L13: 2947 | M13: 930 | N13: 3088 | O13: 4956 | P13: 2540 | Q13: 2281 | T13: 570 | U13: 427 | V13: =SUM(B13:U13) -> 27032
A14: 2034年 | B14: 169 | C14: 276 | D14: 435 | E14: 814 | G14: 272 | H14: 5175 | I14: 544 | J14: 1728 | K14: 471 | L14: 3138 | M14: 1015 | N14: 3341 | O14: 5440 | P14: 2791 | Q14: 2540 | T14: 564 | U14: 443 | V14: =SUM(B14:U14) -> 29156
A15: 2035年 | B15: 169 | C15: 277 | D15: 434 | E15: 880 | G15: 280 | H15: 5473 | I15: 582 | J15: 1845 | K15: 508 | L15: 3310 | M15: 1098 | N15: 3595 | O15: 5926 | P15: 3041 | Q15: 2791 | T15: 557 | U15: 458 | V15: =SUM(B15:U15) -> 31224
A17: 返戻率(R8年) | B17: 0.432 | C17: 0.458 | D17: 0.528 | E17: 0.449 | G17: 0.4 | H17: 0.688 | I17: 0.688 | J17: 0.675 | K17: 0.646 | L17: 0.5 | M17: 0.464 | N17: 0.826 | O17: 0.831 | P17: 0.789 | Q17: 0.748 | R17: 0.881 | S17: 0.917 | T17: 0.687 | U17: 0.667
A18: 意向 | B18: 随時解約検討 | C18: 随時解約検討 | D18: 2027年度払済？ | E18: 2030年度払済？ | F18: 保有 | G18: 保有 | H18: 2027年度払済？ | I18: 保有 | J18: 2027年度払済？ | K18: 保有 | L18: 2026年度払済？ | M18: 2030年度払済？ | N18: 保有 | O18: 保有 | P18: 保有 | Q18: 保有 | R18: 2030年度解約 | S18: 2030年度解約
A20: ※返戻金は各年の見込額(万円)。合計は期間満了済みの契約が抜けるため、年が進むと減る箇所があります。解約時の課税関係(返戻金−資産計上額)は税理士に確認してください。

Sheet 社債検討
A1: 社債の採算確認と賃貸アパートとの比較
A2: 数値は前提シートの設定を引用。比較用アパート条件は仮置き(青字)なので、実際の物件資料に置き換えてください。
A4: 1. 社債の損益(為替を購入時のまま固定した場合)
A5: 投資額(円) | B5: =前提!B27 -> 39625000
A6: 年間利息(USD) | B6: =前提!B17*前提!B21 -> 17500
A7: 年間利息(円・税引前) | B7: =B6*前提!B25 -> 2765000
A8: 年間利息(円・源泉税引後) | B8: =B7*(1-前提!B23) -> 2341540.2
A9: 3年間の税引後利息(円) | B9: =B8*前提!B24/12 -> 7024620.8
A10: 円ベース年利回り(税引後・手数料込み) | B10: =B9/B5/(前提!B24/12) -> 0.059092498 | C10: 提示の7%から、源泉税と為替手数料の分だけ低下
A11: 損益分岐の償還時為替(円/USD) | B11: =(B5-B9)/前提!B17 -> 130.40152 | C11: これより円高になると3年トータルで元本割れ(円ベース)
A12: 許容できる円高幅(購入時比) | B12: =1-B11/前提!B18 -> 0.17467394
A14: 2. 償還時の為替別 3年間の損益(円)
A15: 償還時為替(円/USD) | B15: 3年間の損益(円) | C15: 年率換算(単純)
A16: 120 | B16: =B$9+前提!$B$17*A16-B$5 -> -2600379.2 | C16: =B16/B$5/(前提!$B$24/12) -> -0.021874904
A17: 130 | B17: =B$9+前提!$B$17*A17-B$5 -> -100379.25 | C17: =B17/B$5/(前提!$B$24/12) -> -0.00084441009
A18: 140 | B18: =B$9+前提!$B$17*A18-B$5 -> 2399620.8 | C18: =B18/B$5/(前提!$B$24/12) -> 0.020186084
A19: 150 | B19: =B$9+前提!$B$17*A19-B$5 -> 4899620.8 | C19: =B19/B$5/(前提!$B$24/12) -> 0.041216578
A20: 160 | B20: =B$9+前提!$B$17*A20-B$5 -> 7399620.8 | C20: =B20/B$5/(前提!$B$24/12) -> 0.062247073
A21: 170 | B21: =B$9+前提!$B$17*A21-B$5 -> 9899620.8 | C21: =B21/B$5/(前提!$B$24/12) -> 0.083277567
A22: 180 | B22: =B$9+前提!$B$17*A22-B$5 -> 12399621 | C22: =B22/B$5/(前提!$B$24/12) -> 0.10430806
A23: ※利息は購入時為替で円換算、利息への課税は源泉税のみで計算(為替差損益の課税効果は考慮していません)。
A25: 3. 賃貸アパート(同額を現金投資した場合)との比較 ※仮置き
A26: 物件価格(円) | B26: =B5 -> 39625000
A27: 表面利回り(仮置き) | B27: 0.07 | C27: 物件資料の値に置換
A28: 空室・滞納ロス(仮置き) | B28: 0.05
A29: 運営費率(管理・修繕・固定資産税・保険、仮置き) | B29: 0.2
A30: 実質利回り(税引前) | B30: =B27*(1-B28)*(1-B29) -> 0.0532
A31: 社債の円ベース利回り(上記1.より) | B31: =B10 -> 0.059092498
A32: ※アパートは円建てで為替リスクなし・売却可能な実物資産。一方で空室・修繕・出口(売却価格)のリスクと、取得に伴う諸費用があります。
A33: ※貴社は令和8年9月期が大幅な欠損のため、減価償却による節税効果(アパートの利点)は当面ほぼ見込めません。
A35: 4. 大和証券に確認したい事項
A36: 1. 発行体名と格付(7%は米国債などより大幅に高い水準のため、発行体の信用力を確認)
A37: 2. 7%は「表面利率」か「利回り」か。発行価格は額面100%か(割引・割増の有無)
A38: 3. 期限前償還条項(コーラブル)・利率変動・株価連動など、仕組債の要素がないか
A39: 4. 利払い頻度と利払日、受渡日(購入月の確定)
A40: 5. 為替手数料・販売手数料の総額(円転コスト、償還時の円転コスト)
A41: 6. 中途売却する場合の売却価格の目安と流動性(売れない/大幅値引きのリスク)
A42: 7. 法人の源泉徴収・会計処理(満期保有目的か、期末の為替換算)を顧問税理士に確認
A43: 8. 購入資金25万USDの円転タイミング(為替予約・外貨預金の活用可否)

Sheet 実績
A1: 実績データ(旭土地建物 令和8年9月期 = 令和7年10月〜令和8年9月)
A2: 出典: TKC勘定科目残高推移表(2026/10/27出力)。決算月は9月、累計残高は10月起算。青字=PDF転記の累計(円)、黒字=月次への換算。
A4: 科目 | C4: 10月累計 | D4: 11月累計 | E4: 12月累計 | F4: 1月累計 | G4: 2月累計 | H4: 3月累計 | I4: 4月累計 | J4: 5月累計 | K4: 6月累計 | L4: 7月累計 | M4: 8月累計 | N4: 9月累計 | P4: 10月(月次) | Q4: 11月(月次) | R4: 12月(月次) | S4: 1月(月次) | T4: 2月(月次) | U4: 3月(月次) | V4: 4月(月次) | W4: 5月(月次) | X4: 6月(月次) | Y4: 7月(月次) | Z4: 8月(月次) | AA4: 9月(月次)
A6: 不動産賃貸売上高 | C6: 4088247 | D6: 7650673 | E6: 12553109 | F6: 15938888 | G6: 18786815 | H6: 24888219 | I6: 29212699 | J6: 33092018 | K6: 38789464 | L6: 42856654 | M6: 45830786 | N6: 48518409 | P6: =C6 -> 4088247 | Q6: =D6-C6 -> 3562426 | R6: =E6-D6 -> 4902436 | S6: =F6-E6 -> 3385779 | T6: =G6-F6 -> 2847927 | U6: =H6-G6 -> 6101404 | V6: =I6-H6 -> 4324480 | W6: =J6-I6 -> 3879319 | X6: =K6-J6 -> 5697446 | ... AA6: =N6-M6 -> 2687623
A7: その他売上高(4114) | C7: 0 | D7: 0 | E7: 0 | F7: 0 | G7: 0 | H7: 3120000 | I7: 3120000 | J7: 3142224 | K7: 3142224 | L7: 3142224 | M7: 3153336 | N7: 3153336 | P7: =C7 -> 0 | Q7: =D7-C7 -> 0 | R7: =E7-D7 -> 0 | S7: =F7-E7 -> 0 | T7: =G7-F7 -> 0 | U7: =H7-G7 -> 3120000 | V7: =I7-H7 -> 0 | W7: =J7-I7 -> 22224 | X7: =K7-J7 -> 0 | ... AA7: =N7-M7 -> 0
A8: 土地売上高 | C8: 0 | D8: 0 | E8: 0 | F8: 0 | G8: 0 | H8: 23224126 | I8: 23224126 | J8: 23224126 | K8: 23224126 | L8: 73274882 | M8: 110288898 | N8: 110288898 | P8: =C8 -> 0 | Q8: =D8-C8 -> 0 | R8: =E8-D8 -> 0 | S8: =F8-E8 -> 0 | T8: =G8-F8 -> 0 | U8: =H8-G8 -> 23224126 | V8: =I8-H8 -> 0 | W8: =J8-I8 -> 0 | X8: =K8-J8 -> 0 | ... AA8: =N8-M8 -> 0
A9: 役員報酬 | C9: 900000 | D9: 1800000 | E9: 2700000 | F9: 3600000 | G9: 4500000 | H9: 5400000 | I9: 6300000 | J9: 7200000 | K9: 8100000 | L9: 9000000 | M9: 9900000 | N9: 12300000 | P9: =C9 -> 900000 | Q9: =D9-C9 -> 900000 | R9: =E9-D9 -> 900000 | S9: =F9-E9 -> 900000 | T9: =G9-F9 -> 900000 | U9: =H9-G9 -> 900000 | V9: =I9-H9 -> 900000 | W9: =J9-I9 -> 900000 | X9: =K9-J9 -> 900000 | ... AA9: =N9-M9 -> 2400000
A10: 事務員給与 | C10: 584901 | D10: 1164645 | E10: 1750405 | F10: 2188744 | G10: 2637397 | H10: 3073157 | I10: 3506339 | J10: 3938661 | K10: 4375281 | L10: 5361041 | M10: 5795942 | N10: 6215372 | P10: =C10 -> 584901 | Q10: =D10-C10 -> 579744 | R10: =E10-D10 -> 585760 | S10: =F10-E10 -> 438339 | T10: =G10-F10 -> 448653 | U10: =H10-G10 -> 435760 | V10: =I10-H10 -> 433182 | W10: =J10-I10 -> 432322 | X10: =K10-J10 -> 436620 | ... AA10: =N10-M10 -> 419430
A11: 従業員賞与 | C11: 0 | D11: 0 | E11: 650000 | F11: 650000 | G11: 650000 | H11: 650000 | I11: 650000 | J11: 650000 | K11: 650000 | L11: 650000 | M11: 650000 | N11: 650000 | P11: =C11 -> 0 | Q11: =D11-C11 -> 0 | R11: =E11-D11 -> 650000 | S11: =F11-E11 -> 0 | T11: =G11-F11 -> 0 | U11: =H11-G11 -> 0 | V11: =I11-H11 -> 0 | W11: =J11-I11 -> 0 | X11: =K11-J11 -> 0 | ... AA11: =N11-M11 -> 0
A12: 法定福利費 | C12: 194262 | D12: 191957 | E12: 310289 | F12: 432179 | G12: 637960 | H12: 884118 | I12: 1006271 | J12: 1004128 | K12: 1252495 | L12: 1372299 | M12: 1495408 | N12: 1703283 | P12: =C12 -> 194262 | Q12: =D12-C12 -> -2305 | R12: =E12-D12 -> 118332 | S12: =F12-E12 -> 121890 | T12: =G12-F12 -> 205781 | U12: =H12-G12 -> 246158 | V12: =I12-H12 -> 122153 | W12: =J12-I12 -> -2143 | X12: =K12-J12 -> 248367 | ... AA12: =N12-M12 -> 207875
A13: 厚生費 | C13: 439047 | D13: 702165 | E13: 1648421 | F13: 2149381 | G13: 2511525 | H13: 2710461 | I13: 2970906 | J13: 3213285 | K13: 3634352 | L13: 3907088 | M13: 4239956 | N13: 4820303 | P13: =C13 -> 439047 | Q13: =D13-C13 -> 263118 | R13: =E13-D13 -> 946256 | S13: =F13-E13 -> 500960 | T13: =G13-F13 -> 362144 | U13: =H13-G13 -> 198936 | V13: =I13-H13 -> 260445 | W13: =J13-I13 -> 242379 | X13: =K13-J13 -> 421067 | ... AA13: =N13-M13 -> 580347
A14: 保険料 | C14: 877958 | D14: 1741916 | E14: 2605874 | F14: 3494022 | G14: 4362810 | H14: 5231598 | I14: 6100386 | J14: 6969174 | K14: 16138245 | L14: 18729693 | M14: 20079749 | N14: 24617595 | P14: =C14 -> 877958 | Q14: =D14-C14 -> 863958 | R14: =E14-D14 -> 863958 | S14: =F14-E14 -> 888148 | T14: =G14-F14 -> 868788 | U14: =H14-G14 -> 868788 | V14: =I14-H14 -> 868788 | W14: =J14-I14 -> 868788 | X14: =K14-J14 -> 9169071 | ... AA14: =N14-M14 -> 4537846
A15: 租税公課 | C15: 0 | D15: 0 | E15: 0 | F15: 71800 | G15: 267569 | H15: 272895 | I15: 5496995 | J15: 7216795 | K15: 7252295 | L15: 7268000 | M15: 7290952 | N15: 7291552 | P15: =C15 -> 0 | Q15: =D15-C15 -> 0 | R15: =E15-D15 -> 0 | S15: =F15-E15 -> 71800 | T15: =G15-F15 -> 195769 | U15: =H15-G15 -> 5326 | V15: =I15-H15 -> 5224100 | W15: =J15-I15 -> 1719800 | X15: =K15-J15 -> 35500 | ... AA15: =N15-M15 -> 600
A16: 水道光熱費 | C16: 211751 | D16: 376793 | E16: 546034 | F16: 722765 | G16: 904238 | H16: 1082755 | I16: 1244308 | J16: 1408709 | K16: 1596998 | L16: 1827900 | M16: 2055681 | N16: 2288413 | P16: =C16 -> 211751 | Q16: =D16-C16 -> 165042 | R16: =E16-D16 -> 169241 | S16: =F16-E16 -> 176731 | T16: =G16-F16 -> 181473 | U16: =H16-G16 -> 178517 | V16: =I16-H16 -> 161553 | W16: =J16-I16 -> 164401 | X16: =K16-J16 -> 188289 | ... AA16: =N16-M16 -> 232732
A17: 通信交通費 | C17: 220964 | D17: 497851 | E17: 849722 | F17: 1178744 | G17: 1380511 | H17: 1696520 | I17: 1995319 | J17: 2255572 | K17: 2574708 | L17: 2859038 | M17: 3281175 | N17: 3566993 | P17: =C17 -> 220964 | Q17: =D17-C17 -> 276887 | R17: =E17-D17 -> 351871 | S17: =F17-E17 -> 329022 | T17: =G17-F17 -> 201767 | U17: =H17-G17 -> 316009 | V17: =I17-H17 -> 298799 | W17: =J17-I17 -> 260253 | X17: =K17-J17 -> 319136 | ... AA17: =N17-M17 -> 285818
... A29: 販売費及び一般管理費(PDF合計) | C29: 4468174 | D29: 10248856 | E29: 16768939 | F29: 21656685 | G29: 26291758 | H29: 31091395 | I29: 40895518 | J29: 46861893 | K29: 59860090 | L29: 66477031 | M29: 71083353 | N29: 80446258 | P29: =C29 -> 4468174 | Q29: =D29-C29 -> 5780682 | R29: =E29-D29 -> 6520083 | S29: =F29-E29 -> 4887746 | T29: =G29-F29 -> 4635073 | U29: =H29-G29 -> 4799637 | V29: =I29-H29 -> 9804123 | W29: =J29-I29 -> 5966375 | X29: =K29-J29 -> 12998197 | ... AA29: =N29-M29 -> 9362905
A30: 検算(科目合計−PDF合計 ※0であること) | C30: =SUM(C9:C28)-C29 -> 0 | D30: =SUM(D9:D28)-D29 -> 0 | E30: =SUM(E9:E28)-E29 -> 0 | F30: =SUM(F9:F28)-F29 -> 0 | G30: =SUM(G9:G28)-G29 -> 0 | H30: =SUM(H9:H28)-H29 -> 0 | I30: =SUM(I9:I28)-I29 -> 0 | J30: =SUM(J9:J28)-J29 -> 0 | ... N30: =SUM(N9:N28)-N29 -> 0 | P30: =SUM(P9:P28)-P29 -> 0 | Q30: =SUM(Q9:Q28)-Q29 -> 0 | R30: =SUM(R9:R28)-R29 -> 0 | S30: =SUM(S9:S28)-S29 -> 0 | T30: =SUM(T9:T28)-T29 -> 0 | U30: =SUM(U9:U28)-U29 -> 0 | V30: =SUM(V9:V28)-V29 -> 0 | W30: =SUM(W9:W28)-W29 -> 0 | ... AA30: =SUM(AA9:AA28)-AA29 -> 0
A33: 期別の月次推移(令和5〜8年9月期・10月〜9月)
A34: 現預金 月末残高(円) | C34: 10月 | D34: 11月 | E34: 12月 | F34: 1月 | G34: 2月 | H34: 3月 | I34: 4月 | J34: 5月 | K34: 6月 | L34: 7月 | M34: 8月 | N34: 9月
A35: 令和5年9月期 | C35: 117605905 | D35: 153924696 | E35: 193632544 | F35: 211943443 | G35: 212439933 | H35: 215208179 | I35: 210496736 | J35: 235588670 | K35: 228363600 | L35: 218394670 | M35: 215303200 | N35: 196813496
A36: 令和6年9月期 | C36: 194315770 | D36: 210241731 | E36: 209040302 | F36: 207397677 | G36: 207028738 | H36: 217316212 | I36: 164617380 | J36: 159086521 | K36: 149819904 | L36: 138952867 | M36: 134547396 | N36: 112635095
A37: 令和7年9月期 | C37: 203406019 | D37: 203310852 | E37: 165051323 | F37: 158615543 | G37: 132414824 | H37: 137505588 | I37: 141366548 | J37: 138136071 | K37: 126713763 | L37: 110696581 | M37: 112494414 | N37: 122419789
A38: 令和8年9月期 | C38: 122156452 | D38: 119724005 | E38: 118857258 | F38: 114964571 | G38: 113618547 | H38: 164353319 | I38: 144013260 | J38: 139822640 | K38: 129332969 | L38: 176629765 | M38: 211301042 | N38: 207939447
A40: 賃貸売上 月次(円・累計の差分) | C40: 10月 | D40: 11月 | E40: 12月 | F40: 1月 | G40: 2月 | H40: 3月 | I40: 4月 | J40: 5月 | K40: 6月 | L40: 7月 | M40: 8月 | N40: 9月
A41: 令和5年9月期 | C41: 4526228 | D41: 4491718 | E41: 4885971 | F41: 4502081 | G41: 3748020 | H41: 4567056 | I41: 4226963 | J41: 4566603 | K41: 5128035 | L41: 4431206 | M41: 3177167 | N41: 7632065
A42: 令和6年9月期 | C42: 3568995 | D42: 2982519 | E42: 3539127 | F42: 3442139 | G42: 5112422 | H42: 4057457 | I42: 4359364 | J42: 3312630 | K42: 4441632 | L42: 4330181 | M42: 3420777 | N42: 3880873
A43: 令和7年9月期 | C43: 3859635 | D43: 3722648 | E43: 4363808 | F43: 4074287 | G43: 3393648 | H43: 4418167 | I43: 3522485 | J43: 3731531 | K43: 4537984 | L43: 3922121 | M43: 3891538 | N43: 5518338
A44: 令和8年9月期 | C44: 4088247 | D44: 3562426 | E44: 4902436 | F44: 3385779 | G44: 2847927 | H44: 6101404 | I44: 4324480 | J44: 3879319 | K44: 5697446 | L44: 4067190 | M44: 2974132 | N44: 2687623
A46: 販売費及び一般管理費 月次(円・累計の差分) | C46: 10月 | D46: 11月 | E46: 12月 | F46: 1月 | G46: 2月 | H46: 3月 | I46: 4月 | J46: 5月 | K46: 6月 | L46: 7月 | M46: 8月 | N46: 9月
A47: 令和5年9月期 | C47: 3730822 | D47: 5751241 | E47: 5463383 | F47: 8738899 | G47: 4620849 | H47: 4264997 | I47: 9373198 | J47: 7304313 | K47: 14354570 | L47: 13715674 | M47: 6879925 | N47: -5633204
A48: 令和6年9月期 | C48: 8362903 | D48: 3626242 | E48: 5413639 | F48: 4351584 | G48: 4194159 | H48: 3406758 | I48: 9202277 | J48: 6702667 | K48: 11713388 | L48: 9211827 | M48: 4959421 | N48: -101126
A49: 令和7年9月期 | C49: 3323746 | D49: 4678574 | E49: 5586526 | F49: 4896649 | G49: 4951562 | H49: 4734892 | I49: 10014533 | J49: 6099776 | K49: 13590835 | L49: 14354967 | M49: 1947306 | N49: 6960491
A50: 令和8年9月期 | C50: 4468174 | D50: 5780682 | E50: 6520083 | F50: 4887746 | G50: 4635073 | H50: 4799637 | I50: 9804123 | J50: 5966375 | K50: 12998197 | L50: 6616941 | M50: 4606322 | N50: 9362905
A52: ※9月は決算整理(棚卸・保険の資産計上・未払計上など)を含みます。令和5・6年9月期の9月の販管費がマイナスなのは決算整理による戻しです。
